Workbook

Sheet Overview_Strategies
A1: BÁO CÁO KẾT QUẢ DIGITAL SAT BLUEBOOK
A2: Đề thi | B2: Digital SAT Practice Test — October 2026 (INT-B)
A3: Học sinh | B3: Học sinh
A4: Email học sinh | B4: Chưa cung cấp
A5: Mục tiêu điểm | B5: 1400+
A6: Thời gian nộp | B6: ---
A7: Giáo viên phụ trách | B7: Mike Pham Bá Hong Son (Google for Education Innovator: https://edudirectory.withgoogle.com/profiles/5087615831769088) - mikepham358@gmail.com
A8: Nguồn tài liệu | B8: Tham khảo từ hocsat.com
A10: BẢNG TỔNG KẾT ĐIỂM SỐ
A11: Tổng số câu | B11: =Performance_Summary!D9
A12: Số câu đã làm | B12: =Performance_Summary!E9
A13: Số câu đúng Lần 1 (100%) | B13: =Performance_Summary!F9
A14: Số câu đúng Lần 2 (66.7%) | B14: =COUNTIF(RW_Module1!M5:M31, "✅ Đúng ở L2") + COUNTIF(RW_Module2!M5:M31, "✅ Đúng ở L2") + COUNTIF(Math_Module1!M5:M26, "✅ Đúng ở L2") + COUNTIF(Math_Module2!M5:M26, "✅ Đúng ở L2")
A15: Số câu đúng Lần 3 (33.3%) | B15: =COUNTIF(RW_Module1!M5:M31, "✅ Đúng ở L3") + COUNTIF(RW_Module2!M5:M31, "✅ Đúng ở L3") + COUNTIF(Math_Module1!M5:M26, "✅ Đúng ở L3") + COUNTIF(Math_Module2!M5:M26, "✅ Đúng ở L3")
A16: Hiệu suất điểm | B16: =Performance_Summary!K9
A17: Điểm ước tính | B17: =ROUND(400 + Performance_Summary!K9 * 1200, 0) & " / 1600"
A18: Số lần thử sai ghi sổ | B18: =COUNTA(SAT_Error_Log_Tracker!A2:A100)

Sheet Performance_Summary
A1: BẢNG TỔNG HỢP KẾT QUẢ VÀ THEO DÕI TIẾN ĐỘ (OCTOBER 2026 TEST)
A2: Tự động cập nhật số câu đã làm, số lần đúng ngay Lần 1, đếm số cột sai và điểm hiệu suất (%) theo thời gian thực
A4: STT | B4: Tên Module / Phân vùng | C4: Tên Tab trong Excel | D4: Tổng số câu | E4: Đã làm Lần 1 | F4: Đúng ngay L1 | G4: Đúng ở L2/L3 | H4: Tổng số cột Sai | I4: Chưa đúng | J4: Tỷ lệ Đúng L1 (%) | K4: Điểm Hiệu suất TB (%)
A5: 1 | B5: Reading & Writing Module 1 | C5: RW_Module1 | D5: =COUNTA(RW_Module1!A5:A31) | E5: =COUNTIF(RW_Module1!F5:F31, "<>") | F5: =COUNTIF(RW_Module1!G5:G31, "✅ Đúng") | G5: =COUNTIF(RW_Module1!M5:M31, "✅ Đúng ở L2") + COUNTIF(RW_Module1!M5:M31, "✅ Đúng ở L3") | H5: =SUM(RW_Module1!L5:L31) | I5: =D5 - F5 - G5 | J5: =IF(E5>0, F5/E5, 0) | K5: =IF(D5>0, AVERAGE(RW_Module1!N5:N31), 0)
A6: 2 | B6: Reading & Writing Module 2 | C6: RW_Module2 | D6: =COUNTA(RW_Module2!A5:A31) | E6: =COUNTIF(RW_Module2!F5:F31, "<>") | F6: =COUNTIF(RW_Module2!G5:G31, "✅ Đúng") | G6: =COUNTIF(RW_Module2!M5:M31, "✅ Đúng ở L2") + COUNTIF(RW_Module2!M5:M31, "✅ Đúng ở L3") | H6: =SUM(RW_Module2!L5:L31) | I6: =D6 - F6 - G6 | J6: =IF(E6>0, F6/E6, 0) | K6: =IF(D6>0, AVERAGE(RW_Module2!N5:N31), 0)
A7: 3 | B7: Math Module 1 | C7: Math_Module1 | D7: =COUNTA(Math_Module1!A5:A26) | E7: =COUNTIF(Math_Module1!F5:F26, "<>") | F7: =COUNTIF(Math_Module1!G5:G26, "✅ Đúng") | G7: =COUNTIF(Math_Module1!M5:M26, "✅ Đúng ở L2") + COUNTIF(Math_Module1!M5:M26, "✅ Đúng ở L3") | H7: =SUM(Math_Module1!L5:L26) | I7: =D7 - F7 - G7 | J7: =IF(E7>0, F7/E7, 0) | K7: =IF(D7>0, AVERAGE(Math_Module1!N5:N26), 0)
A8: 4 | B8: Math Module 2 | C8: Math_Module2 | D8: =COUNTA(Math_Module2!A5:A26) | E8: =COUNTIF(Math_Module2!F5:F26, "<>") | F8: =COUNTIF(Math_Module2!G5:G26, "✅ Đúng") | G8: =COUNTIF(Math_Module2!M5:M26, "✅ Đúng ở L2") + COUNTIF(Math_Module2!M5:M26, "✅ Đúng ở L3") | H8: =SUM(Math_Module2!L5:L26) | I8: =D8 - F8 - G8 | J8: =IF(E8>0, F8/E8, 0) | K8: =IF(D8>0, AVERAGE(Math_Module2!N5:N26), 0)
B9: TỔNG CỘNG TOÀN BỘ ĐỀ THI | C9: --- | D9: =SUM(D5:D8) | E9: =SUM(E5:E8) | F9: =SUM(F5:F8) | G9: =SUM(G5:G8) | H9: =SUM(H5:H8) | I9: =SUM(I5:I8) | J9: =IF(E9>0, F9/E9, 0) | K9: =IF(D9>0, AVERAGE(K5:K8), 0)

Sheet SAT_Error_Log_Tracker
A1: STT | B1: Mã câu | C1: Module | D1: Chủ đề / Kỹ năng | E1: Nhóm bẫy SAT | F1: Phân tích nguyên nhân & Bài học | G1: Ghi chú tư duy | H1: Từ mới / Thuật ngữ | I1: Tình trạng | J1: Thời gian

Sheet RW_Module1
A1: Digital SAT Practice Test - October 2026: Reading & Writing Module 1
A2: Chiến thuật: Tự thử sức ở Lần 1 (Cột F) -> Nhận phản hồi tự động & Gợi ý định hướng logic mà không làm lộ đáp án.
A4: Q# | B4: Topic / Skill Focus | C4: Passage & Context | D4: Question Prompt / Calculator | E4: Options / Choices (No Answer) | F4: Lần thử 1 | G4: Kết quả L1 | H4: Lần thử 2 | I4: Kết quả L2 | J4: Lần thử 3 | K4: Kết quả L3 | L4: Tổng số cột Sai | M4: Trạng thái Hoàn thành | N4: Hiệu suất (%) | O4: Hint / Gợi ý Đa tầng (Không đáp án) | P4: Strategic Tip / Formula
A5: Q1 | B5: Vocabulary in Context (Precision) | C5: ______ the source of a malfunction in a complex electrical system can be a painstaking, time-consuming process: a repair technician may need to test each individual component one by one until the specific part causing the problematic behavior is identified. | D5: Which choice completes the text with the most logical and precise word or phrase? | E5: A. Lựa chọn A B. Lựa chọn B C. Lựa chọn C D. Lựa chọn D | G5: =IF(ISBLANK(F5), "⏳ Chờ đáp án", IF(UPPER(TRIM(F5))="B", "✅ Đúng", "❌ Sai")) | I5: =IF(ISBLANK(H5), "", IF(UPPER(TRIM(H5))="B", "✅ Đúng", "❌ Sai")) | K5: =IF(ISBLANK(J5), "", IF(UPPER(TRIM(J5))="B", "✅ Đúng", "❌ Sai")) | L5: =COUNTIF(G5, "❌ Sai") + COUNTIF(I5, "❌ Sai") + COUNTIF(K5, "❌ Sai") | M5: =IF(ISBLANK(F5), "⏳ Chờ làm", IF(G5="✅ Đúng", "✅ Đúng ngay L1", IF(I5="✅ Đúng", "✅ Đúng ở L2", IF(K5="✅ Đúng", "✅ Đúng ở L3", "❌ Chưa đúng sau 3 lần")))) | N5: =IF(G5="✅ Đúng", 1, IF(I5="✅ Đúng", 0.667, IF(K5="✅ Đúng", 0.333, 0))) | O5: =IF(ISBLANK(F5), "💡 Nhập đáp án vào Lần thử 1", IF(OR(G5="✅ Đúng", I5="✅ Đúng", K5="✅ Đúng"), "✨ Xuất sắc! Bạn đã làm đúng.", IF(NOT(ISBLANK(J5)), "💡 Gợi ý Tầng 3 (Chốt phương pháp): " & "Loại trừ các từ mang nghĩa tạo mới hay điều chỉnh chung; chọn động từ chỉ việc cô lập/xác định nguyên nhân đơn lẻ.", IF(NOT(ISBLANK(H5)), "💡 Gợi ý Tầng 2 (Manh mối cấu trúc & Loại trừ): " & "Chú ý cụm từ 'test each individual component one by one' thể hiện việc khoanh vùng chính xác bộ phận lỗi.", "💡 Gợi ý Tầng 1 (Định hướng bối cảnh): " & "Xác định vai trò của động từ cần điền trong bối cảnh kỹ thuật sửa chữa hệ thống điện.")))) | P5: =IF(OR(G5="✅ Đúng", I5="✅ Đúng", K5="✅ Đúng"), "Isolating = identifying/singling out the specific cause of a problem.", "🔒 Trả lời đúng để mở khóa Strategic Tip!")
A6: Q2 | B6: Vocabulary in Context (Biological Processes) | C6: Single-celled foraminifera inhabiting coastal waters experience significant environmental salinity changes during tidal cycles. How, then, do they ______ internal salt levels? Some organisms maintain high concentrations of phosphates that allow them to affect the concentration of internal electrolytes— including salt—in response to external changes. It may be that coastal foraminifera do the same. | D6: Which choice completes the text with the most logical and precise word or phrase? | E6: A. Lựa chọn A B. Lựa chọn B C. Lựa chọn C D. Lựa chọn D | G6: =IF(ISBLANK(F6), "⏳ Chờ đáp án", IF(UPPER(TRIM(F6))="D", "✅ Đúng", "❌ Sai")) | I6: =IF(ISBLANK(H6), "", IF(UPPER(TRIM(H6))="D", "✅ Đúng", "❌ Sai")) | K6: =IF(ISBLANK(J6), "", IF(UPPER(TRIM(J6))="D", "✅ Đúng", "❌ Sai")) | L6: =COUNTIF(G6, "❌ Sai") + COUNTIF(I6, "❌ Sai") + COUNTIF(K6, "❌ Sai") | M6: =IF(ISBLANK(F6), "⏳ Chờ làm", IF(G6="✅ Đúng", "✅ Đúng ngay L1", IF(I6="✅ Đúng", "✅ Đúng ở L2", IF(K6="✅ Đúng", "✅ Đúng ở L3", "❌ Chưa đúng sau 3 lần")))) | N6: =IF(G6="✅ Đúng", 1, IF(I6="✅ Đúng", 0.667, IF(K6="✅ Đúng", 0.333, 0))) | O6: =IF(ISBLANK(F6), "💡 Nhập đáp án vào Lần thử 1", IF(OR(G6="✅ Đúng", I6="✅ Đúng", K6="✅ Đúng"), "✨ Xuất sắc! Bạn đã làm đúng.", IF(NOT(ISBLANK(J6)), "💡 Gợi ý Tầng 3 (Chốt phương pháp): " & "Loại bỏ các động từ mang nghĩa phá hủy hay làm xáo trộn; tìm từ chỉ sự điều hòa/kiểm soát sinh học.", IF(NOT(ISBLANK(H6)), "💡 Gợi ý Tầng 2 (Manh mối cấu trúc & Loại trừ): " & "Cần một động từ miêu tả việc kiểm soát và duy trì mức độ ổn định của nồng độ muối.", "💡 Gợi ý Tầng 1 (Định hướng bối cảnh): " & "Phân tích cơ chế sinh học điều chỉnh độ mặn nội bào của loài cá ngừ được miêu tả.")))) | P6: =IF(OR(G6="✅ Đúng", I6="✅ Đúng", K6="✅ Đúng"), "Regulate = control or maintain at a steady level.", "🔒 Trả lời đúng để mở khóa Strategic Tip!")
A7: Q3 | B7: Vocabulary in Context (Research Approaches) | C7: Though most studies of the effect of altitude on blood chemistry usually concentrate on people who live above sea level, researchers Suleiman A. Al-Sweedan and Moath Alhaj have instead chosen the ______ path in their recent work of studying the blood of people who live below sea level, in locations such as the California towns of Westmorland and Thermal. | D7: Which choice completes the text with the most logical and precise word or phrase? | E7: A. Lựa chọn A B. Lựa chọn B C. Lựa chọn C D. Lựa chọn D | G7: =IF(ISBLANK(F7), "⏳ Chờ đáp án", IF(UPPER(TRIM(F7))="B", "✅ Đúng", "❌ Sai")) | I7: =IF(ISBLANK(H7), "", IF(UPPER(TRIM(H7))="B", "✅ Đúng", "❌ Sai")) | K7: =IF(ISBLANK(J7), "", IF(UPPER(TRIM(J7))="B", "✅ Đúng", "❌ Sai")) | L7: =COUNTIF(G7, "❌ Sai") + COUNTIF(I7, "❌ Sai") + COUNTIF(K7, "❌ Sai") | M7: =IF(ISBLANK(F7), "⏳ Chờ làm", IF(G7="✅ Đúng", "✅ Đúng ngay L1", IF(I7="✅ Đúng", "✅ Đúng ở L2", IF(K7="✅ Đúng", "✅ Đúng ở L3", "❌ Chưa đúng sau 3 lần")))) | N7: =IF(G7="✅ Đúng", 1, IF(I7="✅ Đúng", 0.667, IF(K7="✅ Đúng", 0.333, 0))) | O7: =IF(ISBLANK(F7), "💡 Nhập đáp án vào Lần thử 1", IF(OR(G7="✅ Đúng", I7="✅ Đúng", K7="✅ Đúng"), "✨ Xuất sắc! Bạn đã làm đúng.", IF(NOT(ISBLANK(J7)), "💡 Gợi ý Tầng 3 (Chốt phương pháp): " & "Cần từ miêu tả phương pháp làm việc khác biệt, đi ngược hoặc khác với lối tư duy truyền thống.", IF(NOT(ISBLANK(H7)), "💡 Gợi ý Tầng 2 (Manh mối cấu trúc & Loại trừ): " & "Chú ý từ nối hoặc ngữ cảnh đối lập giữa việc nghiên cứu trên đất liền và độ sâu dưới mực nước biển.", "💡 Gợi ý Tầng 1 (Định hướng bối cảnh): " & "Phân tích hướng tiếp cận nghiên cứu của nhóm tác giả đối với môi trường đại dương.")))) | P7: =IF(OR(G7="✅ Đúng", I7="✅ Đúng", K7="✅ Đúng"), "Innovative = introducing new, original, or unusual methods.", "🔒 Trả lời đúng để mở khóa Strategic Tip!")
A8: Q4 | B8: Vocabulary in Context (Sufficiency) | C8: While once ______, basic computer security training that only teaches recognition of obvious scams cannot provide enough protection against today’s sophisticated fake emails, which employ such subtle deception techniques that many organizations now require their staff to complete comprehensive cybersecurity education programs. | D8: Which choice completes the text with the most logical and precise word or phrase? | E8: A. Lựa chọn A B. Lựa chọn B C. Lựa chọn C D. Lựa chọn D | G8: =IF(ISBLANK(F8), "⏳ Chờ đáp án", IF(UPPER(TRIM(F8))="C", "✅ Đúng", "❌ Sai")) | I8: =IF(ISBLANK(H8), "", IF(UPPER(TRIM(H8))="C", "✅ Đúng", "❌ Sai")) | K8: =IF(ISBLANK(J8), "", IF(UPPER(TRIM(J8))="C", "✅ Đúng", "❌ Sai")) | L8: =COUNTIF(G8, "❌ Sai") + COUNTIF(I8, "❌ Sai") + COUNTIF(K8, "❌ Sai") | M8: =IF(ISBLANK(F8), "⏳ Chờ làm", IF(G8="✅ Đúng", "✅ Đúng ngay L1", IF(I8="✅ Đúng", "✅ Đúng ở L2", IF(K8="✅ Đúng", "✅ Đúng ở L3", "❌ Chưa đúng sau 3 lần")))) | N8: =IF(G8="✅ Đúng", 1, IF(I8="✅ Đúng", 0.667, IF(K8="✅ Đúng", 0.333, 0))) | O8: =IF(ISBLANK(F8), "💡 Nhập đáp án vào Lần thử 1", IF(OR(G8="✅ Đúng", I8="✅ Đúng", K8="✅ Đúng"), "✨ Xuất sắc! Bạn đã làm đúng.", IF(NOT(ISBLANK(J8)), "💡 Gợi ý Tầng 3 (Chốt phương pháp): " & "Chọn từ miêu tả sự đầy đủ/thỏa đáng; loại các từ mang nghĩa thái quá hoặc không đủ.", IF(NOT(ISBLANK(H8)), "💡 Gợi ý Tầng 2 (Manh mối cấu trúc & Loại trừ): " & "Chú ý vế đối lập phía sau về các đòn tấn công tinh vi đòi hỏi cấp độ bảo vệ cao hơn.", "💡 Gợi ý Tầng 1 (Định hướng bối cảnh): " & "Đọc kỹ câu văn để xác định mức độ hoặc giới hạn bảo vệ của việc đào tạo cơ bản.")))) | P8: =IF(OR(G8="✅ Đúng", I8="✅ Đúng", K8="✅ Đúng"), "Sufficient = adequate or enough for a specific requirement.", "🔒 Trả lời đúng để mở khóa Strategic Tip!")
A9: Q5 | B9: Text Structure & Overall Purpose | C9: What is a city? The answer depends on where you live! Many countries define an area as a city based on how many people live there. However, not every country uses the same numbers. Iceland defines a city as an area with a population of at least 200, while the Netherlands defines a city as having a minimum population of 20,000. Some countries even define cities using other factors, like if there is a local government. | D9: Which choice best describes the overall structure of the text? | E9: A. Lựa chọn A B. Lựa chọn B C. Lựa chọn C D. Lựa chọn D | G9: =IF(ISBLANK(F9), "⏳ Chờ đáp án", IF(UPPER(TRIM(F9))="B", "✅ Đúng", "❌ Sai")) | I9: =IF(ISBLANK(H9), "", IF(UPPER(TRIM(H9))="B", "✅ Đúng", "❌ Sai")) | K9: =IF(ISBLANK(J9), "", IF(UPPER(TRIM(J9))="B", "✅ Đúng", "❌ Sai")) | L9: =COUNTIF(G9, "❌ Sai") + COUNTIF(I9, "❌ Sai") + COUNTIF(K9, "❌ Sai") | M9: =IF(ISBLANK(F9), "⏳ Chờ làm", IF(G9="✅ Đúng", "✅ Đúng ngay L1", IF(I9="✅ Đúng", "✅ Đúng ở L2", IF(K9="✅ Đúng", "✅ Đúng ở L3", "❌ Chưa đúng sau 3 lần")))) | N9: =IF(G9="✅ Đúng", 1, IF(I9="✅ Đúng", 0.667, IF(K9="✅ Đúng", 0.333, 0))) | O9: =IF(ISBLANK(F9), "💡 Nhập đáp án vào Lần thử 1", IF(OR(G9="✅ Đúng", I9="✅ Đúng", K9="✅ Đúng"), "✨ Xuất sắc! Bạn đã làm đúng.", IF(NOT(ISBLANK(J9)), "💡 Gợi ý Tầng 3 (Chốt phương pháp): " & "Mục đích chính là trình bày các quan điểm đa dạng về một khái niệm thay vì chỉ bảo vệ một góc nhìn duy nhất.", IF(NOT(ISBLANK(H9)), "💡 Gợi ý Tầng 2 (Manh mối cấu trúc & Loại trừ): " & "Bài đọc bắt đầu bằng câu hỏi 'What is a city?' và đưa ra các góc nhìn định nghĩa khác nhau.", "💡 Gợi ý Tầng 1 (Định hướng bối cảnh): " & "Xác định cấu trúc tổng thể của bài đọc từ câu hỏi mở đầu đến các câu tiếp theo.")))) | P9: =IF(OR(G9="✅ Đúng", I9="✅ Đúng", K9="✅ Đúng"), "Mô hình cấu trúc: Question -> Multiple Explanations/Answers.", "🔒 Trả lời đúng để mở khóa Strategic Tip!")
A10: Q6 | B10: Main Purpose (Literary Narrative) | C10: The following text is adapted from the 1940 novel The Hamlet by William Faulkner. In rural Mississippi, a man is riding a horse toward the residence of someone he intends to meet with about a business matter. He was breathing hard but not because he had been galloping. On the contrary, since he had approached near enough to his destination to believe he could have seen smoke if there had been smoke, he had ridden slower and slower. Nevertheless he now sat the horse before the gap in the fence, breathing hard enough through his nose and even sweating a little, looking at the sagging broken-backed cabin set in its inevitable treeless and grassless plot and weathered to the color of an old bee-hive, with that expression of tense and rapid speculation of a man approaching a dud howitzer [artillery] shell. ©1967 by Estelle Faulkner and Jill Faulkner Summers | D10: Which choice best states the main purpose of the text? | E10: A. Lựa chọn A B. Lựa chọn B C. Lựa chọn C D. Lựa chọn D | G10: =IF(ISBLANK(F10), "⏳ Chờ đáp án", IF(UPPER(TRIM(F10))="D", "✅ Đúng", "❌ Sai")) | I10: =IF(ISBLANK(H10), "", IF(UPPER(TRIM(H10))="D", "✅ Đúng", "❌ Sai")) | K10: =IF(ISBLANK(J10), "", IF(UPPER(TRIM(J10))="D", "✅ Đúng", "❌ Sai")) | L10: =COUNTIF(G10, "❌ Sai") + COUNTIF(I10, "❌ Sai") + COUNTIF(K10, "❌ Sai") | M10: =IF(ISBLANK(F10), "⏳ Chờ làm", IF(G10="✅ Đúng", "✅ Đúng ngay L1", IF(I10="✅ Đúng", "✅ Đúng ở L2", IF(K10="✅ Đúng", "✅ Đúng ở L3", "❌ Chưa đúng sau 3 lần")))) | N10: =IF(G10="✅ Đúng", 1, IF(I10="✅ Đúng", 0.667, IF(K10="✅ Đúng", 0.333, 0))) | O10: =IF(ISBLANK(F10), "💡 Nhập đáp án vào Lần thử 1", IF(OR(G10="✅ Đúng", I10="✅ Đúng", K10="✅ Đúng"), "✨ Xuất sắc! Bạn đã làm đúng.", IF(NOT(ISBLANK(J10)), "💡 Gợi ý Tầng 3 (Chốt phương pháp): " & "Mục đích chính là thể hiện trạng thái tâm lý lo âu/căng thẳng của nhân vật qua hành vi cụ thể.", IF(NOT(ISBLANK(H10)), "💡 Gợi ý Tầng 2 (Manh mối cấu trúc & Loại trừ): " & "Chú ý các dấu hiệu như thở gấp, đổ mồ hôi và nét mặt căng thẳng trong bối cảnh truyện.", "💡 Gợi ý Tầng 1 (Định hướng bối cảnh): " & "Tập trung vào các chi tiết miêu tả cảm xúc và biểu hiện thể chất của nhân vật.")))) | P10: =IF(OR(G10="✅ Đúng", I10="✅ Đúng", K10="✅ Đúng"), "Văn xuôi hư cấu: Biểu hiện thể chất phản ánh trạng thái tâm lý nhân vật.", "🔒 Trả lời đúng để mở khóa Strategic Tip!")
A11: Q7 | B11: Main Purpose (Informational Text) | C11: Modern forestry offers diverse career opportunities that integrate scientific knowledge with hands-on environmental work. Arborists assess tree health and perform maintenance such as pruning to promote safety and prevent problems. Forestry technicians collect data on growth patterns and biodiversity in the wild. Forest ecologists conduct field research and analyze ecosystems to understand how forests respond to changes in weather patterns. With this blend of scientific understanding and practical application, forestry professionals address a variety of complex environmental challenges. | D11: Which choice best describes the main purpose of the text? | E11: A. Lựa chọn A B. Lựa chọn B C. Lựa chọn C D. Lựa chọn D | G11: =IF(ISBLANK(F11), "⏳ Chờ đáp án", IF(UPPER(TRIM(F11))="D", "✅ Đúng", "❌ Sai")) | I11: =IF(ISBLANK(H11), "", IF(UPPER(TRIM(H11))="D", "✅ Đúng", "❌ Sai")) | K11: =IF(ISBLANK(J11), "", IF(UPPER(TRIM(J11))="D", "✅ Đúng", "❌ Sai")) | L11: =COUNTIF(G11, "❌ Sai") + COUNTIF(I11, "❌ Sai") + COUNTIF(K11, "❌ Sai") | M11: =IF(ISBLANK(F11), "⏳ Chờ làm", IF(G11="✅ Đúng", "✅ Đúng ngay L1", IF(I11="✅ Đúng", "✅ Đúng ở L2", IF(K11="✅ Đúng", "✅ Đúng ở L3", "❌ Chưa đúng sau 3 lần")))) | N11: =IF(G11="✅ Đúng", 1, IF(I11="✅ Đúng", 0.667, IF(K11="✅ Đúng", 0.333, 0))) | O11: =IF(ISBLANK(F11), "💡 Nhập đáp án vào Lần thử 1", IF(OR(G11="✅ Đúng", I11="✅ Đúng", K11="✅ Đúng"), "✨ Xuất sắc! Bạn đã làm đúng.", IF(NOT(ISBLANK(J11)), "💡 Gợi ý Tầng 3 (Chốt phương pháp): " & "Mục đích là tổng quan các cơ hội nghề nghiệp đa dạng trong lĩnh vực được nêu.", IF(NOT(ISBLANK(H11)), "💡 Gợi ý Tầng 2 (Manh mối cấu trúc & Loại trừ): " & "Đoạn văn liệt kê các hướng đi công việc và cơ hội phát triển trong ngành lâm nghiệp.", "💡 Gợi ý Tầng 1 (Định hướng bối cảnh): " & "So sánh câu mở đầu và câu kết thúc của bài đọc để xác định chủ đề xuyên suốt.")))) | P11: =IF(OR(G11="✅ Đúng", I11="✅ Đúng", K11="✅ Đúng"), "Main Purpose = Topic (Forestry Careers) + So What? (Integrate science and practical work).", "🔒 Trả lời đúng để mở khóa Strategic Tip!")
A12: Q8 | B12: Detail & Literal Comprehension | C12: James Fong and his team claim to have discovered a new color, which they named olo. Olo is a very saturated blue-green color that can’t be seen with the human eye under natural conditions. In the human eye, long, medium, and short cones in the retina help sense bright light and color. Olo can only be seen by activating the medium cones alone. Fong and team activated these cones by using a targeted laser technology to stimulate just the medium cone cells. | D12: According to the text, how can the color olo be seen? | E12: A. Lựa chọn A B. Lựa chọn B C. Lựa chọn C D. Lựa chọn D | G12: =IF(ISBLANK(F12), "⏳ Chờ đáp án", IF(UPPER(TRIM(F12))="A", "✅ Đúng", "❌ Sai")) | I12: =IF(ISBLANK(H12), "", IF(UPPER(TRIM(H12))="A", "✅ Đúng", "❌ Sai")) | K12: =IF(ISBLANK(J12), "", IF(UPPER(TRIM(J12))="A", "✅ Đúng", "❌ Sai")) | L12: =COUNTIF(G12, "❌ Sai") + COUNTIF(I12, "❌ Sai") + COUNTIF(K12, "❌ Sai") | M12: =IF(ISBLANK(F12), "⏳ Chờ làm", IF(G12="✅ Đúng", "✅ Đúng ngay L1", IF(I12="✅ Đúng", "✅ Đúng ở L2", IF(K12="✅ Đúng", "✅ Đúng ở L3", "❌ Chưa đúng sau 3 lần")))) | N12: =IF(G12="✅ Đúng", 1, IF(I12="✅ Đúng", 0.667, IF(K12="✅ Đúng", 0.333, 0))) | O12: =IF(ISBLANK(F12), "💡 Nhập đáp án vào Lần thử 1", IF(OR(G12="✅ Đúng", I12="✅ Đúng", K12="✅ Đúng"), "✨ Xuất sắc! Bạn đã làm đúng.", IF(NOT(ISBLANK(J12)), "💡 Gợi ý Tầng 3 (Chốt phương pháp): " & "Chọn đáp án diễn đạt lại chính xác (paraphrase) điều kiện kích hoạt được nêu trực tiếp trên mặt chữ.", IF(NOT(ISBLANK(H12)), "💡 Gợi ý Tầng 2 (Manh mối cấu trúc & Loại trừ): " & "Đối chiếu trực tiếp chi tiết về điều kiện nhìn thấy được miêu tả ở phần giữa bài đọc.", "💡 Gợi ý Tầng 1 (Định hướng bối cảnh): " & "Xác định từ khóa tên riêng được đề cập trong câu hỏi và định vị câu chứa thông tin.")))) | P12: =IF(OR(G12="✅ Đúng", I12="✅ Đúng", K12="✅ Đúng"), "Literal Comprehension: Paraphrase đúng nguyên văn bài đọc, không suy diễn.", "🔒 Trả lời đúng để mở khóa Strategic Tip!")
A13: Q9 | B13: Quantitative Evidence (Graph) | C13: A student is collecting data about countries with volcanoes that have been active in the time since 1800 and in the time since 1960. The student records that Ethiopia has ______ | D13: Which choice most effectively uses data from the graph to complete the statement? | E13: A. Lựa chọn A B. Lựa chọn B C. Lựa chọn C D. Lựa chọn D | G13: =IF(ISBLANK(F13), "⏳ Chờ đáp án", IF(UPPER(TRIM(F13))="C", "✅ Đúng", "❌ Sai")) | I13: =IF(ISBLANK(H13), "", IF(UPPER(TRIM(H13))="C", "✅ Đúng", "❌ Sai")) | K13: =IF(ISBLANK(J13), "", IF(UPPER(TRIM(J13))="C", "✅ Đúng", "❌ Sai")) | L13: =COUNTIF(G13, "❌ Sai") + COUNTIF(I13, "❌ Sai") + COUNTIF(K13, "❌ Sai") | M13: =IF(ISBLANK(F13), "⏳ Chờ làm", IF(G13="✅ Đúng", "✅ Đúng ngay L1", IF(I13="✅ Đúng", "✅ Đúng ở L2", IF(K13="✅ Đúng", "✅ Đúng ở L3", "❌ Chưa đúng sau 3 lần")))) | N13: =IF(G13="✅ Đúng", 1, IF(I13="✅ Đúng", 0.667, IF(K13="✅ Đúng", 0.333, 0))) | O13: =IF(ISBLANK(F13), "💡 Nhập đáp án vào Lần thử 1", IF(OR(G13="✅ Đúng", I13="✅ Đúng", K13="✅ Đúng"), "✨ Xuất sắc! Bạn đã làm đúng.", IF(NOT(ISBLANK(J13)), "💡 Gợi ý Tầng 3 (Chốt phương pháp): " & "Chọn đáp án phản ánh đúng mối quan hệ lớn hơn/nhỏ hơn giữa hai số liệu trên đồ thị.", IF(NOT(ISBLANK(H13)), "💡 Gợi ý Tầng 2 (Manh mối cấu trúc & Loại trừ): " & "So sánh chiều cao của các cột đại diện cho số lượng núi lửa hoạt động giữa hai vùng.", "💡 Gợi ý Tầng 1 (Định hướng bối cảnh): " & "Quan sát biểu đồ và xác định đúng hai quốc gia cùng mốc thời gian từ năm 1960.")))) | P13: =IF(OR(G13="✅ Đúng", I13="✅ Đúng", K13="✅ Đúng"), "Đọc chính xác cột chú giải và số liệu tương ứng của hai quốc gia.", "🔒 Trả lời đúng để mở khóa Strategic Tip!")
A14: Q10 | B14: Command of Evidence (Quotation) | C14: Editor Jared Shurin’s enormous 2023 anthology The Big Book of Cyberpunk comprises 108 stories. Shurin’s volume is chronologically expansive, featuring such stories as James Tiptree Jr.’s “The Girl Who Was Plugged In” (1973) and Erica Satifka’s “Act of Providence” (2021). In his introduction, Shurin defines cyberpunk as a subgenre of speculative fiction concerning “the influence of technology on the scale, the pace, or the pattern of human affairs”; however, some critics assert that cyberpunk is a literary movement that is in large part aesthetic rather than idea driven. | D14: Which quotation from a literary critic would be the most effective evidence in support of the underlined claim? | E14: A. Lựa chọn A B. Lựa chọn B C. Lựa chọn C D. Lựa chọn D | G14: =IF(ISBLANK(F14), "⏳ Chờ đáp án", IF(UPPER(TRIM(F14))="D", "✅ Đúng", "❌ Sai")) | I14: =IF(ISBLANK(H14), "", IF(UPPER(TRIM(H14))="D", "✅ Đúng", "❌ Sai")) | K14: =IF(ISBLANK(J14), "", IF(UPPER(TRIM(J14))="D", "✅ Đúng", "❌ Sai")) | L14: =COUNTIF(G14, "❌ Sai") + COUNTIF(I14, "❌ Sai") + COUNTIF(K14, "❌ Sai") | M14: =IF(ISBLANK(F14), "⏳ Chờ làm", IF(G14="✅ Đúng", "✅ Đúng ngay L1", IF(I14="✅ Đúng", "✅ Đúng ở L2", IF(K14="✅ Đúng", "✅ Đúng ở L3", "❌ Chưa đúng sau 3 lần")))) | N14: =IF(G14="✅ Đúng", 1, IF(I14="✅ Đúng", 0.667, IF(K14="✅ Đúng", 0.333, 0))) | O14: =IF(ISBLANK(F14), "💡 Nhập đáp án vào Lần thử 1", IF(OR(G14="✅ Đúng", I14="✅ Đúng", K14="✅ Đúng"), "✨ Xuất sắc! Bạn đã làm đúng.", IF(NOT(ISBLANK(J14)), "💡 Gợi ý Tầng 3 (Chốt phương pháp): " & "Loại trừ các trích dẫn chỉ nói về chức năng kỹ thuật; chọn câu nhấn mạnh khía cạnh phong cách/thẩm mỹ.", IF(NOT(ISBLANK(H14)), "💡 Gợi ý Tầng 2 (Manh mối cấu trúc & Loại trừ): " & "Tìm câu trích dẫn chứa các từ miêu tả dáng vẻ bên ngoài, phụ kiện hoặc yếu tố văn hóa đại chúng.", "💡 Gợi ý Tầng 1 (Định hướng bối cảnh): " & "Đọc kỹ yêu cầu câu hỏi về yếu tố thẩm mỹ hoặc biểu tượng phong cách.")))) | P14: =IF(OR(G14="✅ Đúng", I14="✅ Đúng", K14="✅ Đúng"), "Bằng chứng hỗ trợ phải trực tiếp chứng minh tính chất 'aesthetic' (thẩm mỹ).", "🔒 Trả lời đúng để mở khóa Strategic Tip!")
A15: Q11 | B15: Command of Evidence (Table Data) | C15: Employment in Tribal Economies in December 2017 and December 2023 by Sector Economic sector Approximate total number of employees, 2017 Percentage of workforce, 2017 Approximate total number of employees, 2023 Percentage of workforce, 2023 Business sector (all tribal businesses) 220,700 66.0% 232,300 65.4% Leisure and hospitality businesses 185,100 55.3% 192,300 54.2% Education and healthcare businesses 19,100 5.7% 21,600 6.1% Other businesses 16,500 5.0% 18,400 5.1% Public sector (tribal government and public administration) 113,800 34.0% 122,700 34.6% Tribal nations employ a large percentage of their populations in tribally owned businesses as well as in government and public administration. This is especially true in Oklahoma and other states with robust tribal economies and large Native populations. Between end-of-year 2017 and end-of-year 2023, the percentage of tribal employees working in the public sector increased, from 34.0% to 34.6%, while the percentage working in the business sector declined from 66.0% to 65.4%. | D15: Which statement about the decline in the percentage of tribal employees working in the business sector is best supported by information in the table? | E15: A. Lựa chọn A B. Lựa chọn B C. Lựa chọn C D. Lựa chọn D | G15: =IF(ISBLANK(F15), "⏳ Chờ đáp án", IF(UPPER(TRIM(F15))="A", "✅ Đúng", "❌ Sai")) | I15: =IF(ISBLANK(H15), "", IF(UPPER(TRIM(H15))="A", "✅ Đúng", "❌ Sai")) | K15: =IF(ISBLANK(J15), "", IF(UPPER(TRIM(J15))="A", "✅ Đúng", "❌ Sai")) | L15: =COUNTIF(G15, "❌ Sai") + COUNTIF(I15, "❌ Sai") + COUNTIF(K15, "❌ Sai") | M15: =IF(ISBLANK(F15), "⏳ Chờ làm", IF(G15="✅ Đúng", "✅ Đúng ngay L1", IF(I15="✅ Đúng", "✅ Đúng ở L2", IF(K15="✅ Đúng", "✅ Đúng ở L3", "❌ Chưa đúng sau 3 lần")))) | N15: =IF(G15="✅ Đúng", 1, IF(I15="✅ Đúng", 0.667, IF(K15="✅ Đúng", 0.333, 0))) | O15: =IF(ISBLANK(F15), "💡 Nhập đáp án vào Lần thử 1", IF(OR(G15="✅ Đúng", I15="✅ Đúng", K15="✅ Đúng"), "✨ Xuất sắc! Bạn đã làm đúng.", IF(NOT(ISBLANK(J15)), "💡 Gợi ý Tầng 3 (Chốt phương pháp): " & "Chọn đáp án nêu đúng sự thay đổi tăng/giảm dựa trên phép trừ số liệu chính xác trong bảng.", IF(NOT(ISBLANK(H15)), "💡 Gợi ý Tầng 2 (Manh mối cấu trúc & Loại trừ): " & "So sánh giá trị nhân viên thực tế giữa các mốc năm trong ngành kinh doanh.", "💡 Gợi ý Tầng 1 (Định hướng bối cảnh): " & "Định vị ngành nghề và khoảng thời gian được đề cập trong bảng số liệu.")))) | P15: =IF(OR(G15="✅ Đúng", I15="✅ Đúng", K15="✅ Đúng"), "Tỷ lệ % giảm không có nghĩa là số lượng tuyệt đối giảm nếu tổng quy mô tăng.", "🔒 Trả lời đúng để mở khóa Strategic Tip!")
A16: Q12 | B16: Command of Evidence (Chart Interpretation) | C16: While US public charities, like Commonfund, must file Form 990 yearly with the IRS, private foundations, such as Lilly Endowment Inc., must file a different form, 990-PF. In addition, foundations that engage in certain prohibited activities must also file Form 4720 and pay a penalty tax on the money involved. Private foundations are prohibited from holding excess interests in a business enterprise, “self-dealing” (conducting activities that benefit foundation insiders), making taxable expenditures such as grants to noncharitable entities, and failing to cross a required threshold in making charitable distributions from income. Out of the organizations that filed Form 990-PF in the years 2003–2005, ______ | D16: Which choice most effectively uses data from the graph to complete the assertion? | E16: A. Lựa chọn A B. Lựa chọn B C. Lựa chọn C D. Lựa chọn D | G16: =IF(ISBLANK(F16), "⏳ Chờ đáp án", IF(UPPER(TRIM(F16))="C", "✅ Đúng", "❌ Sai")) | I16: =IF(ISBLANK(H16), "", IF(UPPER(TRIM(H16))="C", "✅ Đúng", "❌ Sai")) | K16: =IF(ISBLANK(J16), "", IF(UPPER(TRIM(J16))="C", "✅ Đúng", "❌ Sai")) | L16: =COUNTIF(G16, "❌ Sai") + COUNTIF(I16, "❌ Sai") + COUNTIF(K16, "❌ Sai") | M16: =IF(ISBLANK(F16), "⏳ Chờ làm", IF(G16="✅ Đúng", "✅ Đúng ngay L1", IF(I16="✅ Đúng", "✅ Đúng ở L2", IF(K16="✅ Đúng", "✅ Đúng ở L3", "❌ Chưa đúng sau 3 lần")))) | N16: =IF(G16="✅ Đúng", 1, IF(I16="✅ Đúng", 0.667, IF(K16="✅ Đúng", 0.333, 0))) | O16: =IF(ISBLANK(F16), "💡 Nhập đáp án vào Lần thử 1", IF(OR(G16="✅ Đúng", I16="✅ Đúng", K16="✅ Đúng"), "✨ Xuất sắc! Bạn đã làm đúng.", IF(NOT(ISBLANK(J16)), "💡 Gợi ý Tầng 3 (Chốt phương pháp): " & "Chọn đáp án phản ánh chính xác xu hướng biến động số liệu được thể hiện trên đồ thị.", IF(NOT(ISBLANK(H16)), "💡 Gợi ý Tầng 2 (Manh mối cấu trúc & Loại trừ): " & "So sánh tỉ lệ giữa hai năm được hỏi (2003 và 2005) để xem năm nào cao hơn.", "💡 Gợi ý Tầng 1 (Định hướng bối cảnh): " & "Chú ý chỉ số phần trăm do 'undistributed income' trên biểu đồ qua các mốc năm.")))) | P16: =IF(OR(G16="✅ Đúng", I16="✅ Đúng", K16="✅ Đúng"), "Đọc đúng cột năm (2003 vs 2005) và nhóm lý do bị phạt.", "🔒 Trả lời đúng để mở khóa Strategic Tip!")
A17: Q13 | B17: Command of Evidence (Literary Text) | C17: Philoctetes is a play by Sophocles that was first performed in 409 BCE. In the play, Odysseus and Neoptolemus must retrieve Philoctetes—a master archer who is believed necessary for the Greeks to win the Trojan War—from a cave on a deserted island where Odysseus and others had abandoned him with a debilitating injury earlier in the war. Odysseus suggests that the plan for returning with Philoctetes rests on Neoptolemus not having been part of the group that abandoned him: ______ | D17: Which quotation from Philoctetes most effectively illustrates the claim? | E17: A. Lựa chọn A B. Lựa chọn B C. Lựa chọn C D. Lựa chọn D | G17: =IF(ISBLANK(F17), "⏳ Chờ đáp án", IF(UPPER(TRIM(F17))="C", "✅ Đúng", "❌ Sai")) | I17: =IF(ISBLANK(H17), "", IF(UPPER(TRIM(H17))="C", "✅ Đúng", "❌ Sai")) | K17: =IF(ISBLANK(J17), "", IF(UPPER(TRIM(J17))="C", "✅ Đúng", "❌ Sai")) | L17: =COUNTIF(G17, "❌ Sai") + COUNTIF(I17, "❌ Sai") + COUNTIF(K17, "❌ Sai") | M17: =IF(ISBLANK(F17), "⏳ Chờ làm", IF(G17="✅ Đúng", "✅ Đúng ngay L1", IF(I17="✅ Đúng", "✅ Đúng ở L2", IF(K17="✅ Đúng", "✅ Đúng ở L3", "❌ Chưa đúng sau 3 lần")))) | N17: =IF(G17="✅ Đúng", 1, IF(I17="✅ Đúng", 0.667, IF(K17="✅ Đúng", 0.333, 0))) | O17: =IF(ISBLANK(F17), "💡 Nhập đáp án vào Lần thử 1", IF(OR(G17="✅ Đúng", I17="✅ Đúng", K17="✅ Đúng"), "✨ Xuất sắc! Bạn đã làm đúng.", IF(NOT(ISBLANK(J17)), "💡 Gợi ý Tầng 3 (Chốt phương pháp): " & "Chọn trích dẫn thể hiện rõ việc nhân vật không tham gia vào hành động bỏ rơi trước đó.", IF(NOT(ISBLANK(H17)), "💡 Gợi ý Tầng 2 (Manh mối cấu trúc & Loại trừ): " & "Tìm câu thoại hoặc lời kể giải thích lý do nhân vật không bị coi là người phản bội.", "💡 Gợi ý Tầng 1 (Định hướng bối cảnh): " & "Xác định nguyên nhân dẫn đến sự tin tưởng của nhân vật được hỏi trong tác phẩm.")))) | P17: =IF(OR(G17="✅ Đúng", I17="✅ Đúng", K17="✅ Đúng"), "Chọn câu thoại thể hiện rõ luận điểm Neoptolemus không thuộc nhóm cũ.", "🔒 Trả lời đúng để mở khóa Strategic Tip!")
A18: Q14 | B18: Text Completion / Logical Inference | C18: Louis-Ferdinand Céline’s 1932 novel Journey to the End of the Night is regularly described as autobiographical. That characterization is apt—there are many parallels between the experiences of the novel’s protagonist, Ferdinand Bardamu, and those of Céline—but it should not be taken to mean that every person or event depicted in Journey to the End of the Night has a real-life analogue. Much of the novel is pure invention, and readers who overlook this fact and instead focus excessively on correspondences between the novel and Céline’s life can thus ______ | D18: Which choice most logically completes the text? | E18: A. Lựa chọn A B. Lựa chọn B C. Lựa chọn C D. Lựa chọn D | G18: =IF(ISBLANK(F18), "⏳ Chờ đáp án", IF(UPPER(TRIM(F18))="A", "✅ Đúng", "❌ Sai")) | I18: =IF(ISBLANK(H18), "", IF(UPPER(TRIM(H18))="A", "✅ Đúng", "❌ Sai")) | K18: =IF(ISBLANK(J18), "", IF(UPPER(TRIM(J18))="A", "✅ Đúng", "❌ Sai")) | L18: =COUNTIF(G18, "❌ Sai") + COUNTIF(I18, "❌ Sai") + COUNTIF(K18, "❌ Sai") | M18: =IF(ISBLANK(F18), "⏳ Chờ làm", IF(G18="✅ Đúng", "✅ Đúng ngay L1", IF(I18="✅ Đúng", "✅ Đúng ở L2", IF(K18="✅ Đúng", "✅ Đúng ở L3", "❌ Chưa đúng sau 3 lần")))) | N18: =IF(G18="✅ Đúng", 1, IF(I18="✅ Đúng", 0.667, IF(K18="✅ Đúng", 0.333, 0))) | O18: =IF(ISBLANK(F18), "💡 Nhập đáp án vào Lần thử 1", IF(OR(G18="✅ Đúng", I18="✅ Đúng", K18="✅ Đúng"), "✨ Xuất sắc! Bạn đã làm đúng.", IF(NOT(ISBLANK(J18)), "💡 Gợi ý Tầng 3 (Chốt phương pháp): " & "Chọn câu kết luận chỉ ra sự thiếu sót trong việc đánh giá toàn diện tác phẩm nếu chỉ nhìn một chiều.", IF(NOT(ISBLANK(H18)), "💡 Gợi ý Tầng 2 (Manh mối cấu trúc & Loại trừ): " & "Chú ý từ nối đối lập chỉ ra hậu quả của việc bỏ qua khía cạnh hư cấu trong nghiên cứu.", "💡 Gợi ý Tầng 1 (Định hướng bối cảnh): " & "Xác định mối quan hệ logic giữa việc tập trung vào yếu tố tự thuật và yếu tố sáng tác.")))) | P18: =IF(OR(G18="✅ Đúng", I18="✅ Đúng", K18="✅ Đúng"), "Suy luận logic: Xem nhẹ 'pure invention' -> Bỏ qua tính sáng tạo (creativity).", "🔒 Trả lời đúng để mở khóa Strategic Tip!")
A19: Q15 | B19: Text Completion / Inference | C19: Last-mile delivery, the final stage in the delivery of products to customers, is subject to increasing pressure as consumers place greater emphasis on convenience and immediacy, increasingly expecting next-day delivery. In response to this challenge and others, such as the increasing volume of parcels to be delivered, delivery companies are continually looking for ways to make last-mile delivery more efficient. One advance in last-mile delivery is the use of self-service lockers (containers where consumers can pick up their parcels using a unique code). This approach, while promising, also introduces new obstacles (e.g., convenient placement of self-service lockers is challenging). It is therefore likely that ______ | D19: Which choice most logically completes the text? | E19: A. Lựa chọn A B. Lựa chọn B C. Lựa chọn C D. Lựa chọn D | G19: =IF(ISBLANK(F19), "⏳ Chờ đáp án", IF(UPPER(TRIM(F19))="A", "✅ Đúng", "❌ Sai")) | I19: =IF(ISBLANK(H19), "", IF(UPPER(TRIM(H19))="A", "✅ Đúng", "❌ Sai")) | K19: =IF(ISBLANK(J19), "", IF(UPPER(TRIM(J19))="A", "✅ Đúng", "❌ Sai")) | L19: =COUNTIF(G19, "❌ Sai") + COUNTIF(I19, "❌ Sai") + COUNTIF(K19, "❌ Sai") | M19: =IF(ISBLANK(F19), "⏳ Chờ làm", IF(G19="✅ Đúng", "✅ Đúng ngay L1", IF(I19="✅ Đúng", "✅ Đúng ở L2", IF(K19="✅ Đúng", "✅ Đúng ở L3", "❌ Chưa đúng sau 3 lần")))) | N19: =IF(G19="✅ Đúng", 1, IF(I19="✅ Đúng", 0.667, IF(K19="✅ Đúng", 0.333, 0))) | O19: =IF(ISBLANK(F19), "💡 Nhập đáp án vào Lần thử 1", IF(OR(G19="✅ Đúng", I19="✅ Đúng", K19="✅ Đúng"), "✨ Xuất sắc! Bạn đã làm đúng.", IF(NOT(ISBLANK(J19)), "💡 Gợi ý Tầng 3 (Chốt phương pháp): " & "Chọn kết luận nối tiếp hợp lý, thể hiện sự suy giảm hoặc thay đổi hành vi tương ứng.", IF(NOT(ISBLANK(H19)), "💡 Gợi ý Tầng 2 (Manh mối cấu trúc & Loại trừ): " & "Chú ý các bằng chứng được đưa ra ở câu trước về sự thay đổi nguồn thức ăn.", "💡 Gợi ý Tầng 1 (Định hướng bối cảnh): " & "Phân tích lập luận của tác giả về tác động của biến đổi khí hậu đối với loài động vật.")))) | P19: =IF(OR(G19="✅ Đúng", I19="✅ Đúng", K19="✅ Đúng"), "Kết luận hợp lý: Giải pháp hiện tại gặp thách thức -> Cần tiếp tục thử nghiệm ý tưởng mới.", "🔒 Trả lời đúng để mở khóa Strategic Tip!")
A20: Q16 | B20: Standard English Conventions (Relative Clauses) | C20: With an average summer temperature of 82.5 degrees Fahrenheit, Nicosia is one European ______ many travelers recommend, especially from June to September. | D20: Which choice completes the text so that it conforms to the conventions of Standard English? | E20: A. Lựa chọn A B. Lựa chọn B C. Lựa chọn C D. Lựa chọn D | G20: =IF(ISBLANK(F20), "⏳ Chờ đáp án", IF(UPPER(TRIM(F20))="C", "✅ Đúng", "❌ Sai")) | I20: =IF(ISBLANK(H20), "", IF(UPPER(TRIM(H20))="C", "✅ Đúng", "❌ Sai")) | K20: =IF(ISBLANK(J20), "", IF(UPPER(TRIM(J20))="C", "✅ Đúng", "❌ Sai")) | L20: =COUNTIF(G20, "❌ Sai") + COUNTIF(I20, "❌ Sai") + COUNTIF(K20, "❌ Sai") | M20: =IF(ISBLANK(F20), "⏳ Chờ làm", IF(G20="✅ Đúng", "✅ Đúng ngay L1", IF(I20="✅ Đúng", "✅ Đúng ở L2", IF(K20="✅ Đúng", "✅ Đúng ở L3", "❌ Chưa đúng sau 3 lần")))) | N20: =IF(G20="✅ Đúng", 1, IF(I20="✅ Đúng", 0.667, IF(K20="✅ Đúng", 0.333, 0))) | O20: =IF(ISBLANK(F20), "💡 Nhập đáp án vào Lần thử 1", IF(OR(G20="✅ Đúng", I20="✅ Đúng", K20="✅ Đúng"), "✨ Xuất sắc! Bạn đã làm đúng.", IF(NOT(ISBLANK(J20)), "💡 Gợi ý Tầng 3 (Chốt phương pháp): " & "Loại bỏ các đại từ quan hệ không phù hợp; chọn cấu trúc ngữ pháp chuẩn xác.", IF(NOT(ISBLANK(H20)), "💡 Gợi ý Tầng 2 (Manh mối cấu trúc & Loại trừ): " & "Kiểm tra xem động từ trong mệnh đề quan hệ chia ở số ít hay số nhiều dựa vào danh từ trung tâm.", "💡 Gợi ý Tầng 1 (Định hướng bối cảnh): " & "Xác định mệnh đề quan hệ bổ nghĩa cho danh từ chỉ vật hay chỉ người đứng trước.")))) | P20: =IF(OR(G20="✅ Đúng", I20="✅ Đúng", K20="✅ Đúng"), "Dùng 'that' không dấu phẩy cho mệnh đề quan hệ giới hạn.", "🔒 Trả lời đúng để mở khóa Strategic Tip!")
A21: Q17 | B21: Standard English Conventions (Verb Tense & Progress) | C21: Nanoengineers have developed synthesized mesoporous silica nanoparticles that are used to transport genes and medicines to specific cells in the body. As nanotechnology evolves, medical technology ______ to evolve as well. | D21: Which choice completes the text so that it conforms to the conventions of Standard English? | E21: A. Lựa chọn A B. Lựa chọn B C. Lựa chọn C D. Lựa chọn D | G21: =IF(ISBLANK(F21), "⏳ Chờ đáp án", IF(UPPER(TRIM(F21))="D", "✅ Đúng", "❌ Sai")) | I21: =IF(ISBLANK(H21), "", IF(UPPER(TRIM(H21))="D", "✅ Đúng", "❌ Sai")) | K21: =IF(ISBLANK(J21), "", IF(UPPER(TRIM(J21))="D", "✅ Đúng", "❌ Sai")) | L21: =COUNTIF(G21, "❌ Sai") + COUNTIF(I21, "❌ Sai") + COUNTIF(K21, "❌ Sai") | M21: =IF(ISBLANK(F21), "⏳ Chờ làm", IF(G21="✅ Đúng", "✅ Đúng ngay L1", IF(I21="✅ Đúng", "✅ Đúng ở L2", IF(K21="✅ Đúng", "✅ Đúng ở L3", "❌ Chưa đúng sau 3 lần")))) | N21: =IF(G21="✅ Đúng", 1, IF(I21="✅ Đúng", 0.667, IF(K21="✅ Đúng", 0.333, 0))) | O21: =IF(ISBLANK(F21), "💡 Nhập đáp án vào Lần thử 1", IF(OR(G21="✅ Đúng", I21="✅ Đúng", K21="✅ Đúng"), "✨ Xuất sắc! Bạn đã làm đúng.", IF(NOT(ISBLANK(J21)), "💡 Gợi ý Tầng 3 (Chốt phương pháp): " & "Chọn dạng động từ thể hiện sự tiếp diễn hoặc hoàn thành phù hợp với bối cảnh.", IF(NOT(ISBLANK(H21)), "💡 Gợi ý Tầng 2 (Manh mối cấu trúc & Loại trừ): " & "Đối chiếu thì của các động từ xung quanh để bảo đảm tính nhất quán về thời gian.", "💡 Gợi ý Tầng 1 (Định hướng bối cảnh): " & "Xác định mốc thời gian và tính liên tục của hành động trong bài đọc.")))) | P21: =IF(OR(G21="✅ Đúng", I21="✅ Đúng", K21="✅ Đúng"), "Sự tương thích thì: As [Present], [Future].", "🔒 Trả lời đúng để mở khóa Strategic Tip!")
A22: Q18 | B22: Standard English Conventions (Punctuation / Dashes) | C22: To more easily balance the weight of her body on her toes while performing the demanding pointe work that became increasingly common in early 20th-century ballet, internationally known ballerina Anna Pavlova redesigned her pointe shoes. The modifications she made—adding a stiffened leather sole and hardened toe ______ began the modernization of ballet’s iconic footwear. | D22: Which choice completes the text so that it conforms to the conventions of Standard English? | E22: A. Lựa chọn A B. Lựa chọn B C. Lựa chọn C D. Lựa chọn D | G22: =IF(ISBLANK(F22), "⏳ Chờ đáp án", IF(UPPER(TRIM(F22))="B", "✅ Đúng", "❌ Sai")) | I22: =IF(ISBLANK(H22), "", IF(UPPER(TRIM(H22))="B", "✅ Đúng", "❌ Sai")) | K22: =IF(ISBLANK(J22), "", IF(UPPER(TRIM(J22))="B", "✅ Đúng", "❌ Sai")) | L22: =COUNTIF(G22, "❌ Sai") + COUNTIF(I22, "❌ Sai") + COUNTIF(K22, "❌ Sai") | M22: =IF(ISBLANK(F22), "⏳ Chờ làm", IF(G22="✅ Đúng", "✅ Đúng ngay L1", IF(I22="✅ Đúng", "✅ Đúng ở L2", IF(K22="✅ Đúng", "✅ Đúng ở L3", "❌ Chưa đúng sau 3 lần")))) | N22: =IF(G22="✅ Đúng", 1, IF(I22="✅ Đúng", 0.667, IF(K22="✅ Đúng", 0.333, 0))) | O22: =IF(ISBLANK(F22), "💡 Nhập đáp án vào Lần thử 1", IF(OR(G22="✅ Đúng", I22="✅ Đúng", K22="✅ Đúng"), "✨ Xuất sắc! Bạn đã làm đúng.", IF(NOT(ISBLANK(J22)), "💡 Gợi ý Tầng 3 (Chốt phương pháp): " & "Loại bỏ các phương án dùng hỗn hợp dấu phẩy và gạch ngang không đồng bộ.", IF(NOT(ISBLANK(H22)), "💡 Gợi ý Tầng 2 (Manh mối cấu trúc & Loại trừ): " & "Nhớ quy tắc cặp dấu tương đương: nếu đã mở đầu bằng dấu gạch ngang thì phải đóng bằng dấu gạch ngang.", "💡 Gợi ý Tầng 1 (Định hướng bối cảnh): " & "Xác định thành phần bổ sung không thiết yếu (non-essential clause) trong câu.")))) | P22: =IF(OR(G22="✅ Đúng", I22="✅ Đúng", K22="✅ Đúng"), "Dấu gạch ngang đi theo cặp: — [thông tin bổ sung] —.", "🔒 Trả lời đúng để mở khóa Strategic Tip!")
A23: Q19 | B23: Standard English Conventions (Colons) | C23: Archaeological evidence indicates that board games have existed in human societies for at least five millennia, with examples discovered in the tombs of ancient Egypt and the ruins of Mesopotamia. The purpose of these ancient games was ______ provide entertainment during leisure time, to reflect cultural beliefs, and to develop strategic thinking skills among players. | D23: Which choice completes the text so that it conforms to the conventions of Standard English? | E23: A. Lựa chọn A B. Lựa chọn B C. Lựa chọn C D. Lựa chọn D | G23: =IF(ISBLANK(F23), "⏳ Chờ đáp án", IF(UPPER(TRIM(F23))="B", "✅ Đúng", "❌ Sai")) | I23: =IF(ISBLANK(H23), "", IF(UPPER(TRIM(H23))="B", "✅ Đúng", "❌ Sai")) | K23: =IF(ISBLANK(J23), "", IF(UPPER(TRIM(J23))="B", "✅ Đúng", "❌ Sai")) | L23: =COUNTIF(G23, "❌ Sai") + COUNTIF(I23, "❌ Sai") + COUNTIF(K23, "❌ Sai") | M23: =IF(ISBLANK(F23), "⏳ Chờ làm", IF(G23="✅ Đúng", "✅ Đúng ngay L1", IF(I23="✅ Đúng", "✅ Đúng ở L2", IF(K23="✅ Đúng", "✅ Đúng ở L3", "❌ Chưa đúng sau 3 lần")))) | N23: =IF(G23="✅ Đúng", 1, IF(I23="✅ Đúng", 0.667, IF(K23="✅ Đúng", 0.333, 0))) | O23: =IF(ISBLANK(F23), "💡 Nhập đáp án vào Lần thử 1", IF(OR(G23="✅ Đúng", I23="✅ Đúng", K23="✅ Đúng"), "✨ Xuất sắc! Bạn đã làm đúng.", IF(NOT(ISBLANK(J23)), "💡 Gợi ý Tầng 3 (Chốt phương pháp): " & "Loại bỏ phương án dùng dấu phẩy nối hai mệnh đề độc lập (lỗi comma splice).", IF(NOT(ISBLANK(H23)), "💡 Gợi ý Tầng 2 (Manh mối cấu trúc & Loại trừ): " & "Dấu hai chấm được dùng để giải thích hoặc chi tiết hóa nội dung đã nêu ở mệnh đề độc lập trước đó.", "💡 Gợi ý Tầng 1 (Định hướng bối cảnh): " & "Kiểm tra xem vế trước vị trí cần điền có phải là một mệnh đề độc lập hoàn chỉnh hay không.")))) | P23: =IF(OR(G23="✅ Đúng", I23="✅ Đúng", K23="✅ Đúng"), "Dấu hai chấm (:) báo hiệu danh sách giải thích phía sau.", "🔒 Trả lời đúng để mở khóa Strategic Tip!")
A24: Q20 | B24: Standard English Conventions (Semicolons & Colons) | C24: Extensive radiocarbon dating of reed samples from Caral confirmed Ruth Shady Solís’s hypothesis about the Peruvian site’s ______ nearly 5,000 years ago, the ancient city preceded the Olmec civilization to the north by a full millennium, a revelation that fundamentally altered our understanding of urban development in the Western Hemisphere. | D24: Which choice completes the text so that it conforms to the conventions of Standard English? | E24: A. Lựa chọn A B. Lựa chọn B C. Lựa chọn C D. Lựa chọn D | G24: =IF(ISBLANK(F24), "⏳ Chờ đáp án", IF(UPPER(TRIM(F24))="B", "✅ Đúng", "❌ Sai")) | I24: =IF(ISBLANK(H24), "", IF(UPPER(TRIM(H24))="B", "✅ Đúng", "❌ Sai")) | K24: =IF(ISBLANK(J24), "", IF(UPPER(TRIM(J24))="B", "✅ Đúng", "❌ Sai")) | L24: =COUNTIF(G24, "❌ Sai") + COUNTIF(I24, "❌ Sai") + COUNTIF(K24, "❌ Sai") | M24: =IF(ISBLANK(F24), "⏳ Chờ làm", IF(G24="✅ Đúng", "✅ Đúng ngay L1", IF(I24="✅ Đúng", "✅ Đúng ở L2", IF(K24="✅ Đúng", "✅ Đúng ở L3", "❌ Chưa đúng sau 3 lần")))) | N24: =IF(G24="✅ Đúng", 1, IF(I24="✅ Đúng", 0.667, IF(K24="✅ Đúng", 0.333, 0))) | O24: =IF(ISBLANK(F24), "💡 Nhập đáp án vào Lần thử 1", IF(OR(G24="✅ Đúng", I24="✅ Đúng", K24="✅ Đúng"), "✨ Xuất sắc! Bạn đã làm đúng.", IF(NOT(ISBLANK(J24)), "💡 Gợi ý Tầng 3 (Chốt phương pháp): " & "Loại bỏ phương án chỉ dùng dấu phẩy đơn lẻ giữa hai mệnh đề độc lập.", IF(NOT(ISBLANK(H24)), "💡 Gợi ý Tầng 2 (Manh mối cấu trúc & Loại trừ): " & "Nếu hai mệnh đề độc lập không có liên từ FANBOYS thì phải dùng dấu chấm phẩy hoặc dấu chấm.", "💡 Gợi ý Tầng 1 (Định hướng bối cảnh): " & "Phân tích mối quan hệ giữa hai mệnh đề độc lập đứng trước và sau vị trí khoảng trống.")))) | P24: =IF(OR(G24="✅ Đúng", I24="✅ Đúng", K24="✅ Đúng"), "Dấu hai chấm nối 2 mệnh đề độc lập khi mệnh đề 2 giải thích cho mệnh đề 1.", "🔒 Trả lời đúng để mở khóa Strategic Tip!")
A25: Q21 | B25: Standard English Conventions (Subject-Verb Agreement) | C25: Chemists investigating the properties of coal tar in the mid-nineteenth century discovered compounds that led to the creation of vibrant artificial colorants. Commercial applications of this new synthetic dye technology—beginning with the purple dye called mauve, discovered by William Perkin in 1856—______ responsible for launching what one science historian calls a “manufacturing revolution based on chemistry.” | D25: Which choice completes the text so that it conforms to the conventions of Standard English? | E25: A. Lựa chọn A B. Lựa chọn B C. Lựa chọn C D. Lựa chọn D | G25: =IF(ISBLANK(F25), "⏳ Chờ đáp án", IF(UPPER(TRIM(F25))="C", "✅ Đúng", "❌ Sai")) | I25: =IF(ISBLANK(H25), "", IF(UPPER(TRIM(H25))="C", "✅ Đúng", "❌ Sai")) | K25: =IF(ISBLANK(J25), "", IF(UPPER(TRIM(J25))="C", "✅ Đúng", "❌ Sai")) | L25: =COUNTIF(G25, "❌ Sai") + COUNTIF(I25, "❌ Sai") + COUNTIF(K25, "❌ Sai") | M25: =IF(ISBLANK(F25), "⏳ Chờ làm", IF(G25="✅ Đúng", "✅ Đúng ngay L1", IF(I25="✅ Đúng", "✅ Đúng ở L2", IF(K25="✅ Đúng", "✅ Đúng ở L3", "❌ Chưa đúng sau 3 lần")))) | N25: =IF(G25="✅ Đúng", 1, IF(I25="✅ Đúng", 0.667, IF(K25="✅ Đúng", 0.333, 0))) | O25: =IF(ISBLANK(F25), "💡 Nhập đáp án vào Lần thử 1", IF(OR(G25="✅ Đúng", I25="✅ Đúng", K25="✅ Đúng"), "✨ Xuất sắc! Bạn đã làm đúng.", IF(NOT(ISBLANK(J25)), "💡 Gợi ý Tầng 3 (Chốt phương pháp): " & "Chọn dạng động từ hòa hợp chính xác về số với chủ ngữ trung tâm.", IF(NOT(ISBLANK(H25)), "💡 Gợi ý Tầng 2 (Manh mối cấu trúc & Loại trừ): " & "Kiểm tra xem chủ ngữ chính là danh từ số ít hay số nhiều.", "💡 Gợi ý Tầng 1 (Định hướng bối cảnh): " & "Xác định chủ ngữ chính của câu bằng cách gạch bỏ các cụm giới từ nhiễu đứng giữa.")))) | P25: =IF(OR(G25="✅ Đúng", I25="✅ Đúng", K25="✅ Đúng"), "Gạch bỏ thông tin xen giữa trong hai dấu gạch ngang để xác định chủ ngữ chính.", "🔒 Trả lời đúng để mở khóa Strategic Tip!")
A26: Q22 | B26: Transitions (Sequence & Step) | C26: How does a clear evening become foggy? First, the ground releases heat, which radiates upward. This causes the air near the ground to cool. ______ tiny water droplets begin to form as the cooling air reaches its dew point and can no longer hold its moisture as invisible vapor. Finally, as more droplets accumulate, a visible layer of fog develops close to the ground. | D26: Which choice completes the text with the most logical transition? | E26: A. Lựa chọn A B. Lựa chọn B C. Lựa chọn C D. Lựa chọn D | G26: =IF(ISBLANK(F26), "⏳ Chờ đáp án", IF(UPPER(TRIM(F26))="D", "✅ Đúng", "❌ Sai")) | I26: =IF(ISBLANK(H26), "", IF(UPPER(TRIM(H26))="D", "✅ Đúng", "❌ Sai")) | K26: =IF(ISBLANK(J26), "", IF(UPPER(TRIM(J26))="D", "✅ Đúng", "❌ Sai")) | L26: =COUNTIF(G26, "❌ Sai") + COUNTIF(I26, "❌ Sai") + COUNTIF(K26, "❌ Sai") | M26: =IF(ISBLANK(F26), "⏳ Chờ làm", IF(G26="✅ Đúng", "✅ Đúng ngay L1", IF(I26="✅ Đúng", "✅ Đúng ở L2", IF(K26="✅ Đúng", "✅ Đúng ở L3", "❌ Chưa đúng sau 3 lần")))) | N26: =IF(G26="✅ Đúng", 1, IF(I26="✅ Đúng", 0.667, IF(K26="✅ Đúng", 0.333, 0))) | O26: =IF(ISBLANK(F26), "💡 Nhập đáp án vào Lần thử 1", IF(OR(G26="✅ Đúng", I26="✅ Đúng", K26="✅ Đúng"), "✨ Xuất sắc! Bạn đã làm đúng.", IF(NOT(ISBLANK(J26)), "💡 Gợi ý Tầng 3 (Chốt phương pháp): " & "Chọn từ nối thể hiện chính xác mối quan hệ trình tự/kết quả được thiết lập.", IF(NOT(ISBLANK(H26)), "💡 Gợi ý Tầng 2 (Manh mối cấu trúc & Loại trừ): " & "Xác định xem câu sau đưa ra kết quả, sự đối lập, hay bước tiếp theo trong trình tự.", "💡 Gợi ý Tầng 1 (Định hướng bối cảnh): " & "Phân tích mối quan hệ logic giữa hai câu văn đứng trước và sau từ nối.")))) | P26: =IF(OR(G26="✅ Đúng", I26="✅ Đúng", K26="✅ Đúng"), "Từ nối chỉ thứ tự các bước trong quy trình: Next.", "🔒 Trả lời đúng để mở khóa Strategic Tip!")
A27: Q23 | B27: Transitions (Elaboration & Specifics) | C27: Scientists studying forest restoration have discovered that trees depend on complex partnerships with microscopic organisms for survival. The researchers found that special fungi called endophytes live inside tree leaves and serve as a defense mechanism. ______ these endophytes help by fighting off diseases and boosting the tree’s immune system. | D27: Which choice completes the text with the most logical transition? | E27: A. Lựa chọn A B. Lựa chọn B C. Lựa chọn C D. Lựa chọn D | G27: =IF(ISBLANK(F27), "⏳ Chờ đáp án", IF(UPPER(TRIM(F27))="D", "✅ Đúng", "❌ Sai")) | I27: =IF(ISBLANK(H27), "", IF(UPPER(TRIM(H27))="D", "✅ Đúng", "❌ Sai")) | K27: =IF(ISBLANK(J27), "", IF(UPPER(TRIM(J27))="D", "✅ Đúng", "❌ Sai")) | L27: =COUNTIF(G27, "❌ Sai") + COUNTIF(I27, "❌ Sai") + COUNTIF(K27, "❌ Sai") | M27: =IF(ISBLANK(F27), "⏳ Chờ làm", IF(G27="✅ Đúng", "✅ Đúng ngay L1", IF(I27="✅ Đúng", "✅ Đúng ở L2", IF(K27="✅ Đúng", "✅ Đúng ở L3", "❌ Chưa đúng sau 3 lần")))) | N27: =IF(G27="✅ Đúng", 1, IF(I27="✅ Đúng", 0.667, IF(K27="✅ Đúng", 0.333, 0))) | O27: =IF(ISBLANK(F27), "💡 Nhập đáp án vào Lần thử 1", IF(OR(G27="✅ Đúng", I27="✅ Đúng", K27="✅ Đúng"), "✨ Xuất sắc! Bạn đã làm đúng.", IF(NOT(ISBLANK(J27)), "💡 Gợi ý Tầng 3 (Chốt phương pháp): " & "Chọn từ nối mang nghĩa cụ thể hóa, minh họa hoặc diễn giải thêm.", IF(NOT(ISBLANK(H27)), "💡 Gợi ý Tầng 2 (Manh mối cấu trúc & Loại trừ): " & "Câu sau đưa ra thông tin chi tiết hoặc ví dụ cụ thể để làm rõ hơn cho nhận định trước.", "💡 Gợi ý Tầng 1 (Định hướng bối cảnh): " & "Xác định vai trò của câu sau đối với ý tưởng tổng quát đã phát biểu ở câu trước.")))) | P27: =IF(OR(G27="✅ Đúng", I27="✅ Đúng", K27="✅ Đúng"), "Specifically = đi vào chi tiết minh họa cụ thể.", "🔒 Trả lời đúng để mở khóa Strategic Tip!")
A28: Q24 | B28: Rhetorical Synthesis / Student Notes | C28: While researching a topic, a student has taken the following notes: • Pistol shrimp are small marine crustaceans that hunt using a specialized oversized claw. • When the claw snaps shut rapidly, it pushes water through a narrow groove at extreme speeds. • This high-speed water jet creates a bubble that pops forcefully near the shrimp’s prey. • The popping bubble generates shock waves powerful enough to stun small fish. | D28: The student wants to introduce pistol shrimp to an audience unfamiliar with these crustaceans. Which choice most effectively uses relevant information from the notes to accomplish this goal? | E28: A. Lựa chọn A B. Lựa chọn B C. Lựa chọn C D. Lựa chọn D | G28: =IF(ISBLANK(F28), "⏳ Chờ đáp án", IF(UPPER(TRIM(F28))="B", "✅ Đúng", "❌ Sai")) | I28: =IF(ISBLANK(H28), "", IF(UPPER(TRIM(H28))="B", "✅ Đúng", "❌ Sai")) | K28: =IF(ISBLANK(J28), "", IF(UPPER(TRIM(J28))="B", "✅ Đúng", "❌ Sai")) | L28: =COUNTIF(G28, "❌ Sai") + COUNTIF(I28, "❌ Sai") + COUNTIF(K28, "❌ Sai") | M28: =IF(ISBLANK(F28), "⏳ Chờ làm", IF(G28="✅ Đúng", "✅ Đúng ngay L1", IF(I28="✅ Đúng", "✅ Đúng ở L2", IF(K28="✅ Đúng", "✅ Đúng ở L3", "❌ Chưa đúng sau 3 lần")))) | N28: =IF(G28="✅ Đúng", 1, IF(I28="✅ Đúng", 0.667, IF(K28="✅ Đúng", 0.333, 0))) | O28: =IF(ISBLANK(F28), "💡 Nhập đáp án vào Lần thử 1", IF(OR(G28="✅ Đúng", I28="✅ Đúng", K28="✅ Đúng"), "✨ Xuất sắc! Bạn đã làm đúng.", IF(NOT(ISBLANK(J28)), "💡 Gợi ý Tầng 3 (Chốt phương pháp): " & "Chọn câu tổng hợp trực tiếp đáp ứng đúng mục tiêu đề bài mà không thừa thông tin ngoài.", IF(NOT(ISBLANK(H28)), "💡 Gợi ý Tầng 2 (Manh mối cấu trúc & Loại trừ): " & "So sánh các ghi chú với mục tiêu được chỉ định trong yêu cầu.", "💡 Gợi ý Tầng 1 (Định hướng bối cảnh): " & "Đọc kỹ yêu cầu đề bài (Goal) để biết thông tin nào cần được ưu tiên làm nổi bật.")))) | P28: =IF(OR(G28="✅ Đúng", I28="✅ Đúng", K28="✅ Đúng"), "Giới thiệu đối tượng mới = Nêu tên đối tượng + Định nghĩa/Đặc điểm nhận diện chính.", "🔒 Trả lời đúng để mở khóa Strategic Tip!")
A29: Q25 | B29: Rhetorical Synthesis / Student Notes | C29: While researching a topic, a student has taken the following notes: • Elizabeth Catlett (1915–2012) was a celebrated African American artist. • She is best known for creating sculptures and prints that explore the Black experience. • Standing Mother and Child is a 1980 sculpture by Catlett. • New Generation is a 1992 print by Catlett. | D29: The student wants to provide an example of one of Catlett’s sculptures. Which choice most effectively uses relevant information from the notes to accomplish this goal? | E29: A. Lựa chọn A B. Lựa chọn B C. Lựa chọn C D. Lựa chọn D | G29: =IF(ISBLANK(F29), "⏳ Chờ đáp án", IF(UPPER(TRIM(F29))="B", "✅ Đúng", "❌ Sai")) | I29: =IF(ISBLANK(H29), "", IF(UPPER(TRIM(H29))="B", "✅ Đúng", "❌ Sai")) | K29: =IF(ISBLANK(J29), "", IF(UPPER(TRIM(J29))="B", "✅ Đúng", "❌ Sai")) | L29: =COUNTIF(G29, "❌ Sai") + COUNTIF(I29, "❌ Sai") + COUNTIF(K29, "❌ Sai") | M29: =IF(ISBLANK(F29), "⏳ Chờ làm", IF(G29="✅ Đúng", "✅ Đúng ngay L1", IF(I29="✅ Đúng", "✅ Đúng ở L2", IF(K29="✅ Đúng", "✅ Đúng ở L3", "❌ Chưa đúng sau 3 lần")))) | N29: =IF(G29="✅ Đúng", 1, IF(I29="✅ Đúng", 0.667, IF(K29="✅ Đúng", 0.333, 0))) | O29: =IF(ISBLANK(F29), "💡 Nhập đáp án vào Lần thử 1", IF(OR(G29="✅ Đúng", I29="✅ Đúng", K29="✅ Đúng"), "✨ Xuất sắc! Bạn đã làm đúng.", IF(NOT(ISBLANK(J29)), "💡 Gợi ý Tầng 3 (Chốt phương pháp): " & "Chọn câu diễn đạt ngắn gọn, tập trung vào điểm nhấn được đề bài yêu cầu.", IF(NOT(ISBLANK(H29)), "💡 Gợi ý Tầng 2 (Manh mối cấu trúc & Loại trừ): " & "Lọc các ghi chú liên quan đến đối tượng hoặc sự kiện được chỉ định.", "💡 Gợi ý Tầng 1 (Định hướng bối cảnh): " & "Xác định khía cạnh cụ thể mà đề bài yêu cầu người học phải nhấn mạnh từ ghi chú.")))) | P29: =IF(OR(G29="✅ Đúng", I29="✅ Đúng", K29="✅ Đúng"), "Đọc kĩ yêu cầu cụ thể của đề bài: 'example of one of Catlett's sculptures'.", "🔒 Trả lời đúng để mở khóa Strategic Tip!")
A30: Q26 | B30: Rhetorical Synthesis / Student Notes | C30: While researching a topic, a student has taken the following notes: • Chapantongo is a municipality in the state of Hidalgo, Mexico. • Municipalities are governmental regions responsible for providing many public services to their residents. • One service they provide is traffic control. • Chapantongo’s population was 12,967 in 2020. • Its population was 12,271 in 2010. • Hidalgo is divided into 84 municipalities. | D30: The student wants to emphasize the 2020 population of Chapantongo. Which choice most effectively uses relevant information from the notes to accomplish this goal? | E30: A. Lựa chọn A B. Lựa chọn B C. Lựa chọn C D. Lựa chọn D | G30: =IF(ISBLANK(F30), "⏳ Chờ đáp án", IF(UPPER(TRIM(F30))="B", "✅ Đúng", "❌ Sai")) | I30: =IF(ISBLANK(H30), "", IF(UPPER(TRIM(H30))="B", "✅ Đúng", "❌ Sai")) | K30: =IF(ISBLANK(J30), "", IF(UPPER(TRIM(J30))="B", "✅ Đúng", "❌ Sai")) | L30: =COUNTIF(G30, "❌ Sai") + COUNTIF(I30, "❌ Sai") + COUNTIF(K30, "❌ Sai") | M30: =IF(ISBLANK(F30), "⏳ Chờ làm", IF(G30="✅ Đúng", "✅ Đúng ngay L1", IF(I30="✅ Đúng", "✅ Đúng ở L2", IF(K30="✅ Đúng", "✅ Đúng ở L3", "❌ Chưa đúng sau 3 lần")))) | N30: =IF(G30="✅ Đúng", 1, IF(I30="✅ Đúng", 0.667, IF(K30="✅ Đúng", 0.333, 0))) | O30: =IF(ISBLANK(F30), "💡 Nhập đáp án vào Lần thử 1", IF(OR(G30="✅ Đúng", I30="✅ Đúng", K30="✅ Đúng"), "✨ Xuất sắc! Bạn đã làm đúng.", IF(NOT(ISBLANK(J30)), "💡 Gợi ý Tầng 3 (Chốt phương pháp): " & "Chọn đáp án có cấu trúc song song, truyền tải chính xác mối quan hệ giữa các dữ kiện.", IF(NOT(ISBLANK(H30)), "💡 Gợi ý Tầng 2 (Manh mối cấu trúc & Loại trừ): " & "Đối chiếu thông tin trong các ghi chú để tìm câu kết hợp đầy đủ hai vế cần so sánh.", "💡 Gợi ý Tầng 1 (Định hướng bối cảnh): " & "Xem xét mục tiêu bài viết (ví dụ: so sánh hai nghiên cứu hay giới thiệu một phát minh).")))) | P30: =IF(OR(G30="✅ Đúng", I30="✅ Đúng", K30="✅ Đúng"), "Đáp án phải chứa thông tin được yêu cầu làm trọng tâm: 2020 population = 12,967.", "🔒 Trả lời đúng để mở khóa Strategic Tip!")
A31: Q27 | B31: Rhetorical Synthesis / Student Notes | C31: While researching a topic, a student has taken the following notes: • The Future of Nostalgia is a scholarly book by literary theorist Svetlana Boym. • The book explores the concept of nostalgia from various angles. • Chapter 8 explores nostalgia and Europe’s largest shopping mall. • Chapter 17 discusses various skeptics’ takes on the concept of nostalgia. • In chapter 17, Boym writes, “The poethics of nostalgia combines estrangement and human solidarity, affect and reflection.” | D31: The student wants to explain what Svetlana Boym writes about in chapter 8. Which choice most effectively uses relevant information from the notes to accomplish this goal? | E31: A. Lựa chọn A B. Lựa chọn B C. Lựa chọn C D. Lựa chọn D | G31: =IF(ISBLANK(F31), "⏳ Chờ đáp án", IF(UPPER(TRIM(F31))="C", "✅ Đúng", "❌ Sai")) | I31: =IF(ISBLANK(H31), "", IF(UPPER(TRIM(H31))="C", "✅ Đúng", "❌ Sai")) | K31: =IF(ISBLANK(J31), "", IF(UPPER(TRIM(J31))="C", "✅ Đúng", "❌ Sai")) | L31: =COUNTIF(G31, "❌ Sai") + COUNTIF(I31, "❌ Sai") + COUNTIF(K31, "❌ Sai") | M31: =IF(ISBLANK(F31), "⏳ Chờ làm", IF(G31="✅ Đúng", "✅ Đúng ngay L1", IF(I31="✅ Đúng", "✅ Đúng ở L2", IF(K31="✅ Đúng", "✅ Đúng ở L3", "❌ Chưa đúng sau 3 lần")))) | N31: =IF(G31="✅ Đúng", 1, IF(I31="✅ Đúng", 0.667, IF(K31="✅ Đúng", 0.333, 0))) | O31: =IF(ISBLANK(F31), "💡 Nhập đáp án vào Lần thử 1", IF(OR(G31="✅ Đúng", I31="✅ Đúng", K31="✅ Đúng"), "✨ Xuất sắc! Bạn đã làm đúng.", IF(NOT(ISBLANK(J31)), "💡 Gợi ý Tầng 3 (Chốt phương pháp): " & "Chọn câu liên kết các ghi chú một cách mượt mà và đúng trọng tâm đề bài.", IF(NOT(ISBLANK(H31)), "💡 Gợi ý Tầng 2 (Manh mối cấu trúc & Loại trừ): " & "Lựa chọn thông tin trong danh sách ghi chú trực tiếp phục vụ cho mục đích đó.", "💡 Gợi ý Tầng 1 (Định hướng bối cảnh): " & "Đọc yêu cầu để xác định đối tượng khán giả hoặc mục đích của câu văn cần viết.")))) | P31: =IF(OR(G31="✅ Đúng", I31="✅ Đúng", K31="✅ Đúng"), "Chỉ chọn phương án trả lời đúng mục tiêu 'explain what Boym writes in chapter 8'.", "🔒 Trả lời đúng để mở khóa Strategic Tip!")

Sheet RW_Module2
A1: Digital SAT Practice Test - October 2026: Reading & Writing Module 2
A2: Chiến thuật: Tự thử sức ở Lần 1 (Cột F) -> Nhận phản hồi tự động & Gợi ý định hướng logic mà không làm lộ đáp án.
A4: Q# | B4: Topic / Skill Focus | C4: Passage & Context | D4: Question Prompt / Calculator | E4: Options / Choices (No Answer) | F4: Lần thử 1 | G4: Kết quả L1 | H4: Lần thử 2 | I4: Kết quả L2 | J4: Lần thử 3 | K4: Kết quả L3 | L4: Tổng số cột Sai | M4: Trạng thái Hoàn thành | N4: Hiệu suất (%) | O4: Hint / Gợi ý Đa tầng (Không đáp án) | P4: Strategic Tip / Formula
A5: Q1 | B5: Vocabulary in Context (Interplay) | C5: Weather patterns, market trends, input costs, labor availability, equipment maintenance, and biological cycles are all variables that farmers must consider separately and in terms of how they may affect each other, and it is this ______ of factors in particular that makes successful farm management so challenging. | D5: Which choice completes the text with the most logical and precise word or phrase? | E5: A. Lựa chọn A B. Lựa chọn B C. Lựa chọn C D. Lựa chọn D | G5: =IF(ISBLANK(F5), "⏳ Chờ đáp án", IF(UPPER(TRIM(F5))="D", "✅ Đúng", "❌ Sai")) | I5: =IF(ISBLANK(H5), "", IF(UPPER(TRIM(H5))="D", "✅ Đúng", "❌ Sai")) | K5: =IF(ISBLANK(J5), "", IF(UPPER(TRIM(J5))="D", "✅ Đúng", "❌ Sai")) | L5: =COUNTIF(G5, "❌ Sai") + COUNTIF(I5, "❌ Sai") + COUNTIF(K5, "❌ Sai") | M5: =IF(ISBLANK(F5), "⏳ Chờ làm", IF(G5="✅ Đúng", "✅ Đúng ngay L1", IF(I5="✅ Đúng", "✅ Đúng ở L2", IF(K5="✅ Đúng", "✅ Đúng ở L3", "❌ Chưa đúng sau 3 lần")))) | N5: =IF(G5="✅ Đúng", 1, IF(I5="✅ Đúng", 0.667, IF(K5="✅ Đúng", 0.333, 0))) | O5: =IF(ISBLANK(F5), "💡 Nhập đáp án vào Lần thử 1", IF(OR(G5="✅ Đúng", I5="✅ Đúng", K5="✅ Đúng"), "✨ Xuất sắc! Bạn đã làm đúng.", IF(NOT(ISBLANK(J5)), "💡 Gợi ý Tầng 3 (Chốt phương pháp): " & "Loại các từ chỉ sự tách biệt hay xung đột; chọn từ thể hiện mối quan hệ tương tác.", IF(NOT(ISBLANK(H5)), "💡 Gợi ý Tầng 2 (Manh mối cấu trúc & Loại trừ): " & "Cần một danh từ miêu tả sự tương tác hoặc ảnh hưởng lẫn nhau giữa các thành phần.", "💡 Gợi ý Tầng 1 (Định hướng bối cảnh): " & "Xem xét sự tác động qua lại giữa hai yếu tố sinh học/môi trường được đề cập.")))) | P5: =IF(OR(G5="✅ Đúng", I5="✅ Đúng", K5="✅ Đúng"), "Interplay = the way in which two or more things have an effect on each other.", "🔒 Trả lời đúng để mở khóa Strategic Tip!")
A6: Q2 | B6: Vocabulary in Context (Efficiency & Output) | C6: To maximize ______, package distribution centers employ advanced scheduling systems and strategic staging areas that allow for goods received from warehouses to be immediately transferred to trucks for delivery to their final destinations. Some centers are so efficient that even the largest delivery trucks can be filled in a matter of minutes. | D6: Which choice completes the text with the most logical and precise word or phrase? | E6: A. Lựa chọn A B. Lựa chọn B C. Lựa chọn C D. Lựa chọn D | G6: =IF(ISBLANK(F6), "⏳ Chờ đáp án", IF(UPPER(TRIM(F6))="A", "✅ Đúng", "❌ Sai")) | I6: =IF(ISBLANK(H6), "", IF(UPPER(TRIM(H6))="A", "✅ Đúng", "❌ Sai")) | K6: =IF(ISBLANK(J6), "", IF(UPPER(TRIM(J6))="A", "✅ Đúng", "❌ Sai")) | L6: =COUNTIF(G6, "❌ Sai") + COUNTIF(I6, "❌ Sai") + COUNTIF(K6, "❌ Sai") | M6: =IF(ISBLANK(F6), "⏳ Chờ làm", IF(G6="✅ Đúng", "✅ Đúng ngay L1", IF(I6="✅ Đúng", "✅ Đúng ở L2", IF(K6="✅ Đúng", "✅ Đúng ở L3", "❌ Chưa đúng sau 3 lần")))) | N6: =IF(G6="✅ Đúng", 1, IF(I6="✅ Đúng", 0.667, IF(K6="✅ Đúng", 0.333, 0))) | O6: =IF(ISBLANK(F6), "💡 Nhập đáp án vào Lần thử 1", IF(OR(G6="✅ Đúng", I6="✅ Đúng", K6="✅ Đúng"), "✨ Xuất sắc! Bạn đã làm đúng.", IF(NOT(ISBLANK(J6)), "💡 Gợi ý Tầng 3 (Chốt phương pháp): " & "Loại bỏ từ chỉ khoảng cách hay chi phí; chọn từ miêu tả lưu lượng/năng suất thông qua.", IF(NOT(ISBLANK(H6)), "💡 Gợi ý Tầng 2 (Manh mối cấu trúc & Loại trừ): " & "Cần một danh từ chỉ khối lượng hoặc năng suất hàng hóa được xử lý trong một đơn vị thời gian.", "💡 Gợi ý Tầng 1 (Định hướng bối cảnh): " & "Chú ý bối cảnh vận chuyển và xử lý hàng hóa qua hệ thống cảng/tuyến đường.")))) | P6: =IF(OR(G6="✅ Đúng", I6="✅ Đúng", K6="✅ Đúng"), "Throughput = the amount of material or items passing through a system or process.", "🔒 Trả lời đúng để mở khóa Strategic Tip!")
A7: Q3 | B7: Vocabulary in Context (Parameters) | C7: Researchers have developed algorithms that take into account how various ______ influence production schedules, allowing rapid solution generation for manufacturing planning problems. The algorithms help identify efficient production schedules by processing those quantifiable inputs (e.g., demand patterns and capacity constraints) without exhaustively testing all possible scenarios. | D7: Which choice completes the text with the most logical and precise word or phrase? | E7: A. Lựa chọn A B. Lựa chọn B C. Lựa chọn C D. Lựa chọn D | G7: =IF(ISBLANK(F7), "⏳ Chờ đáp án", IF(UPPER(TRIM(F7))="C", "✅ Đúng", "❌ Sai")) | I7: =IF(ISBLANK(H7), "", IF(UPPER(TRIM(H7))="C", "✅ Đúng", "❌ Sai")) | K7: =IF(ISBLANK(J7), "", IF(UPPER(TRIM(J7))="C", "✅ Đúng", "❌ Sai")) | L7: =COUNTIF(G7, "❌ Sai") + COUNTIF(I7, "❌ Sai") + COUNTIF(K7, "❌ Sai") | M7: =IF(ISBLANK(F7), "⏳ Chờ làm", IF(G7="✅ Đúng", "✅ Đúng ngay L1", IF(I7="✅ Đúng", "✅ Đúng ở L2", IF(K7="✅ Đúng", "✅ Đúng ở L3", "❌ Chưa đúng sau 3 lần")))) | N7: =IF(G7="✅ Đúng", 1, IF(I7="✅ Đúng", 0.667, IF(K7="✅ Đúng", 0.333, 0))) | O7: =IF(ISBLANK(F7), "💡 Nhập đáp án vào Lần thử 1", IF(OR(G7="✅ Đúng", I7="✅ Đúng", K7="✅ Đúng"), "✨ Xuất sắc! Bạn đã làm đúng.", IF(NOT(ISBLANK(J7)), "💡 Gợi ý Tầng 3 (Chốt phương pháp): " & "Chọn từ chỉ các giới hạn/thông số định lượng; loại từ chỉ cảm xúc hay lý thuyết mơ hồ.", IF(NOT(ISBLANK(H7)), "💡 Gợi ý Tầng 2 (Manh mối cấu trúc & Loại trừ): " & "Các yếu tố này được đo lường bằng số liệu cụ thể chứ không phải nhận định cảm quan.", "💡 Gợi ý Tầng 1 (Định hướng bối cảnh): " & "Xác định bản chất của các yếu tố đầu vào được sử dụng trong mô hình nghiên cứu.")))) | P7: =IF(OR(G7="✅ Đúng", I7="✅ Đúng", K7="✅ Đúng"), "Parameters = numerical or other measurable factors forming sets that define a system.", "🔒 Trả lời đúng để mở khóa Strategic Tip!")
A8: Q4 | B8: Vocabulary in Context (Cautions & Warnings) | C8: Marvel Girl’s ability to lift modest loads with her mind is illustrative of the lamentably lackluster powers bestowed on many female superheroes, but even those with more formidable powers have been subject to unflattering portrayals that often serve as ______: as the Phoenix, Jean Grey loses control of a cosmic force and destroys an entire planet, showing the corrupting influence of power. | D8: Which choice completes the text with the most logical and precise word or phrase? | E8: A. Lựa chọn A B. Lựa chọn B C. Lựa chọn C D. Lựa chọn D | G8: =IF(ISBLANK(F8), "⏳ Chờ đáp án", IF(UPPER(TRIM(F8))="B", "✅ Đúng", "❌ Sai")) | I8: =IF(ISBLANK(H8), "", IF(UPPER(TRIM(H8))="B", "✅ Đúng", "❌ Sai")) | K8: =IF(ISBLANK(J8), "", IF(UPPER(TRIM(J8))="B", "✅ Đúng", "❌ Sai")) | L8: =COUNTIF(G8, "❌ Sai") + COUNTIF(I8, "❌ Sai") + COUNTIF(K8, "❌ Sai") | M8: =IF(ISBLANK(F8), "⏳ Chờ làm", IF(G8="✅ Đúng", "✅ Đúng ngay L1", IF(I8="✅ Đúng", "✅ Đúng ở L2", IF(K8="✅ Đúng", "✅ Đúng ở L3", "❌ Chưa đúng sau 3 lần")))) | N8: =IF(G8="✅ Đúng", 1, IF(I8="✅ Đúng", 0.667, IF(K8="✅ Đúng", 0.333, 0))) | O8: =IF(ISBLANK(F8), "💡 Nhập đáp án vào Lần thử 1", IF(OR(G8="✅ Đúng", I8="✅ Đúng", K8="✅ Đúng"), "✨ Xuất sắc! Bạn đã làm đúng.", IF(NOT(ISBLANK(J8)), "💡 Gợi ý Tầng 3 (Chốt phương pháp): " & "Chọn từ thể hiện sự thận trọng/cảnh báo; loại các từ mang nghĩa khen ngợi hay khuyến khích.", IF(NOT(ISBLANK(H8)), "💡 Gợi ý Tầng 2 (Manh mối cấu trúc & Loại trừ): " & "Cần một danh từ mang nghĩa lời cảnh báo, nhắc nhở hoặc lưu ý trước rủi ro.", "💡 Gợi ý Tầng 1 (Định hướng bối cảnh): " & "Đọc kỹ sắc thái câu văn khi bàn về sự nguy hiểm hoặc hậu quả của việc lạm dụng quyền lực.")))) | P8: =IF(OR(G8="✅ Đúng", I8="✅ Đúng", K8="✅ Đúng"), "Admonitions = firm warnings or reprimands.", "🔒 Trả lời đúng để mở khóa Strategic Tip!")
A9: Q5 | B9: Sentence Function & Text Structure | C9: Research on minor solar eruptions in magnetically quiet regions revealed an interesting pattern. Material expelled during these events follows a narrow arc trajectory back to the Sun’s surface. High-resolution images show these eruptions produce thin streams of hot gas moving at speeds between 55 and 200 kilometers per second. Although these are impressive speeds, they are not sufficient to overcome the confining forces of the Sun’s gravity and magnetic field, so the material is pulled back down. | D9: Which choice best describes the function of the underlined sentence in the text as a whole? | E9: A. Lựa chọn A B. Lựa chọn B C. Lựa chọn C D. Lựa chọn D | G9: =IF(ISBLANK(F9), "⏳ Chờ đáp án", IF(UPPER(TRIM(F9))="A", "✅ Đúng", "❌ Sai")) | I9: =IF(ISBLANK(H9), "", IF(UPPER(TRIM(H9))="A", "✅ Đúng", "❌ Sai")) | K9: =IF(ISBLANK(J9), "", IF(UPPER(TRIM(J9))="A", "✅ Đúng", "❌ Sai")) | L9: =COUNTIF(G9, "❌ Sai") + COUNTIF(I9, "❌ Sai") + COUNTIF(K9, "❌ Sai") | M9: =IF(ISBLANK(F9), "⏳ Chờ làm", IF(G9="✅ Đúng", "✅ Đúng ngay L1", IF(I9="✅ Đúng", "✅ Đúng ở L2", IF(K9="✅ Đúng", "✅ Đúng ở L3", "❌ Chưa đúng sau 3 lần")))) | N9: =IF(G9="✅ Đúng", 1, IF(I9="✅ Đúng", 0.667, IF(K9="✅ Đúng", 0.333, 0))) | O9: =IF(ISBLANK(F9), "💡 Nhập đáp án vào Lần thử 1", IF(OR(G9="✅ Đúng", I9="✅ Đúng", K9="✅ Đúng"), "✨ Xuất sắc! Bạn đã làm đúng.", IF(NOT(ISBLANK(J9)), "💡 Gợi ý Tầng 3 (Chốt phương pháp): " & "Chọn đáp án miêu tả đúng vai trò liên kết logic giữa các phần của đoạn văn.", IF(NOT(ISBLANK(H9)), "💡 Gợi ý Tầng 2 (Manh mối cấu trúc & Loại trừ): " & "Phân tích xem câu gạch chân cung cấp bằng chứng, đặt ra giả thuyết hay đưa ra phản biện.", "💡 Gợi ý Tầng 1 (Định hướng bối cảnh): " & "Xác định chức năng của câu gạch chân đối với lập luận toàn bài.")))) | P9: =IF(OR(G9="✅ Đúng", I9="✅ Đúng", K9="✅ Đúng"), "Xác định vai trò tu từ: Trình bày hiện tượng dẫn tới kết quả theo sau.", "🔒 Trả lời đúng để mở khóa Strategic Tip!")
A10: Q6 | B10: Text Structure & Overall Purpose | C10: With examples ranging from Dean’s Blue Hole in the Bahamas to Watling’s Blue Hole near San Salvador Island, blue holes are large underwater sinkholes: pits filled with dark blue water that contrasts with lighter blue shallower waters surrounding them. The formation of blue holes typically involves several natural processes, including the dissolution of limestone or other carbonate rocks. Currently, the deepest blue hole on record is the Taam Ja’ Blue Hole in Chetumal Bay, Mexico, which is reported by Laura Carrillo and colleagues as extending at least 420 meters below sea level. | D10: Which choice best describes the overall structure of the text? | E10: A. Lựa chọn A B. Lựa chọn B C. Lựa chọn C D. Lựa chọn D | G10: =IF(ISBLANK(F10), "⏳ Chờ đáp án", IF(UPPER(TRIM(F10))="D", "✅ Đúng", "❌ Sai")) | I10: =IF(ISBLANK(H10), "", IF(UPPER(TRIM(H10))="D", "✅ Đúng", "❌ Sai")) | K10: =IF(ISBLANK(J10), "", IF(UPPER(TRIM(J10))="D", "✅ Đúng", "❌ Sai")) | L10: =COUNTIF(G10, "❌ Sai") + COUNTIF(I10, "❌ Sai") + COUNTIF(K10, "❌ Sai") | M10: =IF(ISBLANK(F10), "⏳ Chờ làm", IF(G10="✅ Đúng", "✅ Đúng ngay L1", IF(I10="✅ Đúng", "✅ Đúng ở L2", IF(K10="✅ Đúng", "✅ Đúng ở L3", "❌ Chưa đúng sau 3 lần")))) | N10: =IF(G10="✅ Đúng", 1, IF(I10="✅ Đúng", 0.667, IF(K10="✅ Đúng", 0.333, 0))) | O10: =IF(ISBLANK(F10), "💡 Nhập đáp án vào Lần thử 1", IF(OR(G10="✅ Đúng", I10="✅ Đúng", K10="✅ Đúng"), "✨ Xuất sắc! Bạn đã làm đúng.", IF(NOT(ISBLANK(J10)), "💡 Gợi ý Tầng 3 (Chốt phương pháp): " & "Mục đích chính là trình bày một phát hiện mới làm thay đổi hiểu biết trước đây.", IF(NOT(ISBLANK(H10)), "💡 Gợi ý Tầng 2 (Manh mối cấu trúc & Loại trừ): " & "Chú ý sự chuyển ý giữa quan điểm phổ biến và phát hiện mới của nghiên cứu.", "💡 Gợi ý Tầng 1 (Định hướng bối cảnh): " & "Phân tích bố cục bài đọc từ việc nêu hiện tượng đến việc đưa ra lời giải thích.")))) | P10: =IF(OR(G10="✅ Đúng", I10="✅ Đúng", K10="✅ Đúng"), "Mô hình cấu trúc: Define -> Describe Formation -> Provide Specific Landmark Example.", "🔒 Trả lời đúng để mở khóa Strategic Tip!")
A11: Q7 | B11: Cross-Text Comparison (Paired Passages) | C11: Text 1 is from George Eliot’s 1860 novel The Mill on the Floss. Text 2 is from Rabindranath Tagore’s 1921 nonfiction book Glimpses of Bengal. Text 1 The wood I walk in on this mild May day, with the young yellow-brown foliage of the oaks between me and the blue sky, the white star-flowers and the blue-eyed speedwell and the ground ivy at my feet, what grove of tropic palms, what strange ferns or splendid broad-petalled blossoms, could ever thrill such deep and delicate fibres within me as this home scene? Text 2 My feelings seem to be those of our ancient earth in the daily ecstasy of its sun-kissed life; my own consciousness seems to stream through each blade of grass, each sucking root, to rise with the sap through the trees, to break out with joyous thrills in the waving fields of corn, in the rustling palm leaves. | D11: Which choice best describes a notable difference in how the references to palm trees function in Text 1 and Text 2? | E11: A. Lựa chọn A B. Lựa chọn B C. Lựa chọn C D. Lựa chọn D | G11: =IF(ISBLANK(F11), "⏳ Chờ đáp án", IF(UPPER(TRIM(F11))="D", "✅ Đúng", "❌ Sai")) | I11: =IF(ISBLANK(H11), "", IF(UPPER(TRIM(H11))="D", "✅ Đúng", "❌ Sai")) | K11: =IF(ISBLANK(J11), "", IF(UPPER(TRIM(J11))="D", "✅ Đúng", "❌ Sai")) | L11: =COUNTIF(G11, "❌ Sai") + COUNTIF(I11, "❌ Sai") + COUNTIF(K11, "❌ Sai") | M11: =IF(ISBLANK(F11), "⏳ Chờ làm", IF(G11="✅ Đúng", "✅ Đúng ngay L1", IF(I11="✅ Đúng", "✅ Đúng ở L2", IF(K11="✅ Đúng", "✅ Đúng ở L3", "❌ Chưa đúng sau 3 lần")))) | N11: =IF(G11="✅ Đúng", 1, IF(I11="✅ Đúng", 0.667, IF(K11="✅ Đúng", 0.333, 0))) | O11: =IF(ISBLANK(F11), "💡 Nhập đáp án vào Lần thử 1", IF(OR(G11="✅ Đúng", I11="✅ Đúng", K11="✅ Đúng"), "✨ Xuất sắc! Bạn đã làm đúng.", IF(NOT(ISBLANK(J11)), "💡 Gợi ý Tầng 3 (Chốt phương pháp): " & "Chọn câu thể hiện chính xác thái độ phản biện hoặc bổ sung của Tác giả 2 đối với Tác giả 1.", IF(NOT(ISBLANK(H11)), "💡 Gợi ý Tầng 2 (Manh mối cấu trúc & Loại trừ): " & "Xác định điểm đồng thuận hoặc bất đồng cốt lõi giữa hai bài đọc.", "💡 Gợi ý Tầng 1 (Định hướng bối cảnh): " & "So sánh góc nhìn của tác giả Đoạn 1 và tác giả Đoạn 2 về cùng một chủ đề.")))) | P11: =IF(OR(G11="✅ Đúng", I11="✅ Đúng", K11="✅ Đúng"), "So sánh hai thái độ/góc nhìn của hai tác giả đối với cùng một hình ảnh.", "🔒 Trả lời đúng để mở khóa Strategic Tip!")
A12: Q8 | B12: Main Idea (Vernacular Riddles) | C12: Primarily encountered by modern readers as inert written texts, the vernacular riddles of early medieval England contain “implicit vestiges” of an interactive performance context, scholar Jill Frederick argues. Locative phrases (e.g., “here” and “now”) scattered throughout the riddles indicate the space shared by their speakers and audiences; the common refrain “say what I am called” invites a verbalized response; and the conflation of many of the riddles’ speakers with their solutions (typically animals, objects, or natural phenomena) suggests a form of dramatic impersonation perhaps meant to entertain during public gatherings. | D12: Which choice best states the main idea of the text? | E12: A. Lựa chọn A B. Lựa chọn B C. Lựa chọn C D. Lựa chọn D | G12: =IF(ISBLANK(F12), "⏳ Chờ đáp án", IF(UPPER(TRIM(F12))="B", "✅ Đúng", "❌ Sai")) | I12: =IF(ISBLANK(H12), "", IF(UPPER(TRIM(H12))="B", "✅ Đúng", "❌ Sai")) | K12: =IF(ISBLANK(J12), "", IF(UPPER(TRIM(J12))="B", "✅ Đúng", "❌ Sai")) | L12: =COUNTIF(G12, "❌ Sai") + COUNTIF(I12, "❌ Sai") + COUNTIF(K12, "❌ Sai") | M12: =IF(ISBLANK(F12), "⏳ Chờ làm", IF(G12="✅ Đúng", "✅ Đúng ngay L1", IF(I12="✅ Đúng", "✅ Đúng ở L2", IF(K12="✅ Đúng", "✅ Đúng ở L3", "❌ Chưa đúng sau 3 lần")))) | N12: =IF(G12="✅ Đúng", 1, IF(I12="✅ Đúng", 0.667, IF(K12="✅ Đúng", 0.333, 0))) | O12: =IF(ISBLANK(F12), "💡 Nhập đáp án vào Lần thử 1", IF(OR(G12="✅ Đúng", I12="✅ Đúng", K12="✅ Đúng"), "✨ Xuất sắc! Bạn đã làm đúng.", IF(NOT(ISBLANK(J12)), "💡 Gợi ý Tầng 3 (Chốt phương pháp): " & "Loại bỏ các đáp án quá hẹp hoặc quá rộng; chọn câu tóm tắt chính xác luận điểm cốt lõi.", IF(NOT(ISBLANK(H12)), "💡 Gợi ý Tầng 2 (Manh mối cấu trúc & Loại trừ): " & "Xác định chủ đề trung tâm và thông điệp mà tác giả muốn gửi gắm.", "💡 Gợi ý Tầng 1 (Định hướng bối cảnh): " & "Tập trung vào ý tưởng chủ đạo xuyên suốt các câu thơ/đoạn văn thay vì các chi tiết phụ.")))) | P12: =IF(OR(G12="✅ Đúng", I12="✅ Đúng", K12="✅ Đúng"), "Main Point = Evidence of performance context vs. Modern passive reading.", "🔒 Trả lời đúng để mở khóa Strategic Tip!")
A13: Q9 | B13: Inference / Textual Evidence | C13: In the Mexican dialect of Spanish, the consonant s is pronounced with greater tension in the tongue than it is in Castilian, the dominant dialect in Spain, resulting in a sharper sound. Margarita Hidalgo, a linguist at San Diego State University, argues that Mexican Spanish acquired this pronunciation from Nahuatl, the language of the Nahua people in central Mexico: as the Spanish colonizers of Mexico incorporated Nahuatl words into their speech, and as more and more Nahuas spoke Spanish as a second language, the Nahuatl pronunciation of the s consonant replaced the Castilian pronunciation. | D13: Information in the text best supports which statement about the consonant s? | E13: A. Lựa chọn A B. Lựa chọn B C. Lựa chọn C D. Lựa chọn D | G13: =IF(ISBLANK(F13), "⏳ Chờ đáp án", IF(UPPER(TRIM(F13))="D", "✅ Đúng", "❌ Sai")) | I13: =IF(ISBLANK(H13), "", IF(UPPER(TRIM(H13))="D", "✅ Đúng", "❌ Sai")) | K13: =IF(ISBLANK(J13), "", IF(UPPER(TRIM(J13))="D", "✅ Đúng", "❌ Sai")) | L13: =COUNTIF(G13, "❌ Sai") + COUNTIF(I13, "❌ Sai") + COUNTIF(K13, "❌ Sai") | M13: =IF(ISBLANK(F13), "⏳ Chờ làm", IF(G13="✅ Đúng", "✅ Đúng ngay L1", IF(I13="✅ Đúng", "✅ Đúng ở L2", IF(K13="✅ Đúng", "✅ Đúng ở L3", "❌ Chưa đúng sau 3 lần")))) | N13: =IF(G13="✅ Đúng", 1, IF(I13="✅ Đúng", 0.667, IF(K13="✅ Đúng", 0.333, 0))) | O13: =IF(ISBLANK(F13), "💡 Nhập đáp án vào Lần thử 1", IF(OR(G13="✅ Đúng", I13="✅ Đúng", K13="✅ Đúng"), "✨ Xuất sắc! Bạn đã làm đúng.", IF(NOT(ISBLANK(J13)), "💡 Gợi ý Tầng 3 (Chốt phương pháp): " & "Chọn đáp án dựa trên mối liên hệ logic trực tiếp từ các câu văn trong bài.", IF(NOT(ISBLANK(H13)), "💡 Gợi ý Tầng 2 (Manh mối cấu trúc & Loại trừ): " & "Loại bỏ các lựa chọn đưa ra giả định vượt quá thông tin được cung cấp.", "💡 Gợi ý Tầng 1 (Định hướng bối cảnh): " & "Đối chiếu các dữ kiện trong bài đọc để tìm suy luận có căn cứ trực tiếp.")))) | P13: =IF(OR(G13="✅ Đúng", I13="✅ Đúng", K13="✅ Đúng"), "Suy luận trực tiếp từ giả thuyết ảnh hưởng ngôn ngữ Nahuatl.", "🔒 Trả lời đúng để mở khóa Strategic Tip!")
A14: Q10 | B14: Command of Evidence (Cover Crops) | C14: Cover crops, such as teff, are planted by many farmers between main growing seasons. While these crops are known for increasing biodiversity, Axel Don and his coauthor argued in a 2015 study that cover crops’ role in supporting soil carbon sequestration deserves more attention. Cover crops remove carbon dioxide (CO2) from the air and convert it to organic compounds; some of these compounds are stored in the soil as soil organic carbon (SOC), which contributes to the buildup of SOC stocks over time. Based on data from numerous farm fields, Don and his coauthor concluded that cover crops contribute meaningfully to soil carbon sequestration and, if widely adopted, could help offset agricultural emissions of atmospheric CO2 and other greenhouse gases. | D14: Which finding, if true, would be most consistent with Don and his coauthor’s conclusion? | E14: A. Lựa chọn A B. Lựa chọn B C. Lựa chọn C D. Lựa chọn D | G14: =IF(ISBLANK(F14), "⏳ Chờ đáp án", IF(UPPER(TRIM(F14))="D", "✅ Đúng", "❌ Sai")) | I14: =IF(ISBLANK(H14), "", IF(UPPER(TRIM(H14))="D", "✅ Đúng", "❌ Sai")) | K14: =IF(ISBLANK(J14), "", IF(UPPER(TRIM(J14))="D", "✅ Đúng", "❌ Sai")) | L14: =COUNTIF(G14, "❌ Sai") + COUNTIF(I14, "❌ Sai") + COUNTIF(K14, "❌ Sai") | M14: =IF(ISBLANK(F14), "⏳ Chờ làm", IF(G14="✅ Đúng", "✅ Đúng ngay L1", IF(I14="✅ Đúng", "✅ Đúng ở L2", IF(K14="✅ Đúng", "✅ Đúng ở L3", "❌ Chưa đúng sau 3 lần")))) | N14: =IF(G14="✅ Đúng", 1, IF(I14="✅ Đúng", 0.667, IF(K14="✅ Đúng", 0.333, 0))) | O14: =IF(ISBLANK(F14), "💡 Nhập đáp án vào Lần thử 1", IF(OR(G14="✅ Đúng", I14="✅ Đúng", K14="✅ Đúng"), "✨ Xuất sắc! Bạn đã làm đúng.", IF(NOT(ISBLANK(J14)), "💡 Gợi ý Tầng 3 (Chốt phương pháp): " & "Chọn đáp án mô tả đúng sự gia tăng hoặc giảm thiểu chỉ số được nêu.", IF(NOT(ISBLANK(H14)), "💡 Gợi ý Tầng 2 (Manh mối cấu trúc & Loại trừ): " & "Tìm sự kết hợp giữa thông tin trong bài đọc và xu hướng thể hiện trên biểu đồ/bảng.", "💡 Gợi ý Tầng 1 (Định hướng bối cảnh): " & "Phân tích dữ liệu được trình bày về tác dụng của cây che phủ (cover crops).")))) | P14: =IF(OR(G14="✅ Đúng", I14="✅ Đúng", K14="✅ Đúng"), "Consistent with conclusion = Dữ liệu thực tế chứng minh vai trò tăng SOC của cover crops.", "🔒 Trả lời đúng để mở khóa Strategic Tip!")
A15: Q11 | B15: Text Completion / Logical Inference | C15: While the brain regions most strongly associated with language tasks have some modularity in that different language tasks activate these areas to varying degrees, comprehension also invokes other areas of the brain more strongly associated with nonlinguistic functions. For example, understanding a description of a person performing physical actions might call on parts of the listener’s brain associated with sensory- motor functions, whereas a highly emotive account will likely activate areas associated with affective processing. Thus, beyond the areas most strongly associated with linguistic functions, ______ | D15: Which choice most logically completes the text? | E15: A. Lựa chọn A B. Lựa chọn B C. Lựa chọn C D. Lựa chọn D | G15: =IF(ISBLANK(F15), "⏳ Chờ đáp án", IF(UPPER(TRIM(F15))="A", "✅ Đúng", "❌ Sai")) | I15: =IF(ISBLANK(H15), "", IF(UPPER(TRIM(H15))="A", "✅ Đúng", "❌ Sai")) | K15: =IF(ISBLANK(J15), "", IF(UPPER(TRIM(J15))="A", "✅ Đúng", "❌ Sai")) | L15: =COUNTIF(G15, "❌ Sai") + COUNTIF(I15, "❌ Sai") + COUNTIF(K15, "❌ Sai") | M15: =IF(ISBLANK(F15), "⏳ Chờ làm", IF(G15="✅ Đúng", "✅ Đúng ngay L1", IF(I15="✅ Đúng", "✅ Đúng ở L2", IF(K15="✅ Đúng", "✅ Đúng ở L3", "❌ Chưa đúng sau 3 lần")))) | N15: =IF(G15="✅ Đúng", 1, IF(I15="✅ Đúng", 0.667, IF(K15="✅ Đúng", 0.333, 0))) | O15: =IF(ISBLANK(F15), "💡 Nhập đáp án vào Lần thử 1", IF(OR(G15="✅ Đúng", I15="✅ Đúng", K15="✅ Đúng"), "✨ Xuất sắc! Bạn đã làm đúng.", IF(NOT(ISBLANK(J15)), "💡 Gợi ý Tầng 3 (Chốt phương pháp): " & "Chọn vế kết luận nối tiếp hợp lý với hướng lập luận của tác giả.", IF(NOT(ISBLANK(H15)), "💡 Gợi ý Tầng 2 (Manh mối cấu trúc & Loại trừ): " & "Chú ý từ nối chỉ sự tương phản hoặc nguyên nhân - kết quả ở vế trước.", "💡 Gợi ý Tầng 1 (Định hướng bối cảnh): " & "Phân tích mối quan hệ logic giữa hai vế của câu cần hoàn thành.")))) | P15: =IF(OR(G15="✅ Đúng", I15="✅ Đúng", K15="✅ Đúng"), "Kết luận hợp logic: Loại hình nội dung khác nhau -> Kích hoạt các vùng não phi ngôn ngữ khác nhau.", "🔒 Trả lời đúng để mở khóa Strategic Tip!")
A16: Q12 | B16: Text Completion / Logic Comparison | C16: The Clarion-Clipperton Zone (CCZ) is an expanse of abyssal plain and seamounts (underwater mountains) between Hawai‘i and Mexico in which mining is permitted, but the area’s biodiversity is poorly understood. The vast majority of invertebrate species found in a recent survey of the CCZ were hitherto unknown to scientists, and sampling for animal life has been highly concentrated in the eastern part of the zone. Some species like Psychropotes dyscrita were identified both morphologically and molecularly (using DNA analysis), whereas Discantenna metallica and other species for which molecular sampling was impracticable were identified solely based on physical morphology. Since molecular analysis does not require distinguishing subtle physiological differences, it is ______ | D16: Which choice most logically completes the text? | E16: A. Lựa chọn A B. Lựa chọn B C. Lựa chọn C D. Lựa chọn D | G16: =IF(ISBLANK(F16), "⏳ Chờ đáp án", IF(UPPER(TRIM(F16))="D", "✅ Đúng", "❌ Sai")) | I16: =IF(ISBLANK(H16), "", IF(UPPER(TRIM(H16))="D", "✅ Đúng", "❌ Sai")) | K16: =IF(ISBLANK(J16), "", IF(UPPER(TRIM(J16))="D", "✅ Đúng", "❌ Sai")) | L16: =COUNTIF(G16, "❌ Sai") + COUNTIF(I16, "❌ Sai") + COUNTIF(K16, "❌ Sai") | M16: =IF(ISBLANK(F16), "⏳ Chờ làm", IF(G16="✅ Đúng", "✅ Đúng ngay L1", IF(I16="✅ Đúng", "✅ Đúng ở L2", IF(K16="✅ Đúng", "✅ Đúng ở L3", "❌ Chưa đúng sau 3 lần")))) | N16: =IF(G16="✅ Đúng", 1, IF(I16="✅ Đúng", 0.667, IF(K16="✅ Đúng", 0.333, 0))) | O16: =IF(ISBLANK(F16), "💡 Nhập đáp án vào Lần thử 1", IF(OR(G16="✅ Đúng", I16="✅ Đúng", K16="✅ Đúng"), "✨ Xuất sắc! Bạn đã làm đúng.", IF(NOT(ISBLANK(J16)), "💡 Gợi ý Tầng 3 (Chốt phương pháp): " & "Chọn câu hoàn thành thể hiện chính xác kết quả so sánh được suy ra từ bài.", IF(NOT(ISBLANK(H16)), "💡 Gợi ý Tầng 2 (Manh mối cấu trúc & Loại trừ): " & "Chú ý đến các từ chỉ mức độ hoặc tỉ lệ tương quan giữa hai đối tượng.", "💡 Gợi ý Tầng 1 (Định hướng bối cảnh): " & "Xác định sự so sánh giữa hai nhóm hoặc hai phương pháp được đề cập.")))) | P16: =IF(OR(G16="✅ Đúng", I16="✅ Đúng", K16="✅ Đúng"), "Ưu điểm của phân tích phân tử: Phân biệt chính xác các loài có hình thái bên ngoài tương đồng.", "🔒 Trả lời đúng để mở khóa Strategic Tip!")
A17: Q13 | B17: Text Completion / Complex Inference | C17: Rare species advantage (RSA) describes the situation in which there are few conspecifics (other members of the same species) in an organism’s immediate surroundings, enabling the organism to avoid competition with conspecifics for the same resources; RSA is widely believed to play a crucial role in maintaining ecological stability. Among tree species in the Barro Colorado Island plot (latitude 9.15∘ N) and other tropical forest sites, there is little correlation between conspecific aggregation and the abundance of a given species in the wider local area, so RSA is expected, but in the Fenglin Nature Reserve (latitude 48.08∘ N) and other temperate forest sites, the aggregation-abundance correlation for tree species is strongly negative. Mathematical modeling suggests, however, that ecological niche distinction may mitigate the apparent risk to temperate ecological stability engendered by this pattern: ______ | D17: Which choice most logically completes the text? | E17: A. Lựa chọn A B. Lựa chọn B C. Lựa chọn C D. Lựa chọn D | G17: =IF(ISBLANK(F17), "⏳ Chờ đáp án", IF(UPPER(TRIM(F17))="C", "✅ Đúng", "❌ Sai")) | I17: =IF(ISBLANK(H17), "", IF(UPPER(TRIM(H17))="C", "✅ Đúng", "❌ Sai")) | K17: =IF(ISBLANK(J17), "", IF(UPPER(TRIM(J17))="C", "✅ Đúng", "❌ Sai")) | L17: =COUNTIF(G17, "❌ Sai") + COUNTIF(I17, "❌ Sai") + COUNTIF(K17, "❌ Sai") | M17: =IF(ISBLANK(F17), "⏳ Chờ làm", IF(G17="✅ Đúng", "✅ Đúng ngay L1", IF(I17="✅ Đúng", "✅ Đúng ở L2", IF(K17="✅ Đúng", "✅ Đúng ở L3", "❌ Chưa đúng sau 3 lần")))) | N17: =IF(G17="✅ Đúng", 1, IF(I17="✅ Đúng", 0.667, IF(K17="✅ Đúng", 0.333, 0))) | O17: =IF(ISBLANK(F17), "💡 Nhập đáp án vào Lần thử 1", IF(OR(G17="✅ Đúng", I17="✅ Đúng", K17="✅ Đúng"), "✨ Xuất sắc! Bạn đã làm đúng.", IF(NOT(ISBLANK(J17)), "💡 Gợi ý Tầng 3 (Chốt phương pháp): " & "Chọn câu kết luận phản ánh đúng tác động của kết quả thực nghiệm lên giả thuyết.", IF(NOT(ISBLANK(H17)), "💡 Gợi ý Tầng 2 (Manh mối cấu trúc & Loại trừ): " & "Xác định kết quả thử nghiệm nào sẽ củng cố hoặc làm suy yếu giả thuyết đó.", "💡 Gợi ý Tầng 1 (Định hướng bối cảnh): " & "Đọc kỹ các câu tiền đề để nắm vững giả thuyết nghiên cứu được đưa ra.")))) | P17: =IF(OR(G17="✅ Đúng", I17="✅ Đúng", K17="✅ Đúng"), "Giải thích cơ chế Niche Distinction giúp duy trì sự ổn định sinh thái.", "🔒 Trả lời đúng để mở khóa Strategic Tip!")
A18: Q14 | B18: Standard English Conventions (Modifiers) | C18: A premortem is an exercise in which teams imagine their project has already failed, then brainstorm possible reasons for that failure. Despite its apparent pessimism, ______ prompting teams to proactively develop mitigation strategies during the planning stage. As a result, the project is more likely to succeed. | D18: Which choice completes the text so that it conforms to the conventions of Standard English? | E18: A. Lựa chọn A B. Lựa chọn B C. Lựa chọn C D. Lựa chọn D | G18: =IF(ISBLANK(F18), "⏳ Chờ đáp án", IF(UPPER(TRIM(F18))="B", "✅ Đúng", "❌ Sai")) | I18: =IF(ISBLANK(H18), "", IF(UPPER(TRIM(H18))="B", "✅ Đúng", "❌ Sai")) | K18: =IF(ISBLANK(J18), "", IF(UPPER(TRIM(J18))="B", "✅ Đúng", "❌ Sai")) | L18: =COUNTIF(G18, "❌ Sai") + COUNTIF(I18, "❌ Sai") + COUNTIF(K18, "❌ Sai") | M18: =IF(ISBLANK(F18), "⏳ Chờ làm", IF(G18="✅ Đúng", "✅ Đúng ngay L1", IF(I18="✅ Đúng", "✅ Đúng ở L2", IF(K18="✅ Đúng", "✅ Đúng ở L3", "❌ Chưa đúng sau 3 lần")))) | N18: =IF(G18="✅ Đúng", 1, IF(I18="✅ Đúng", 0.667, IF(K18="✅ Đúng", 0.333, 0))) | O18: =IF(ISBLANK(F18), "💡 Nhập đáp án vào Lần thử 1", IF(OR(G18="✅ Đúng", I18="✅ Đúng", K18="✅ Đúng"), "✨ Xuất sắc! Bạn đã làm đúng.", IF(NOT(ISBLANK(J18)), "💡 Gợi ý Tầng 3 (Chốt phương pháp): " & "Loại bỏ các phương án bị lỗi bổ ngữ lủng lẳng (dangling modifier).", IF(NOT(ISBLANK(H18)), "💡 Gợi ý Tầng 2 (Manh mối cấu trúc & Loại trừ): " & "Quy tắc bổ ngữ: Danh từ đứng ngay sau dấu phẩy phải là chủ thể thực hiện hành động phân từ.", "💡 Gợi ý Tầng 1 (Định hướng bối cảnh): " & "Xác định vị trí của cụm phân từ đầu câu và đối tượng mà nó bổ nghĩa.")))) | P18: =IF(OR(G18="✅ Đúng", I18="✅ Đúng", K18="✅ Đúng"), "Bổ ngữ phân từ đầu câu: [Participle Modifier], [Subject + Verb].", "🔒 Trả lời đúng để mở khóa Strategic Tip!")
A19: Q15 | B19: Standard English Conventions (Parallel Lists) | C19: As one of aviation’s earliest female stunt performers, Gladys Ingle developed a versatile repertoire of acrobatic feats. Her specialized skills included standing on the wing of a flying aircraft and shooting a bow and arrow at a ______ perfect balance during aerial maneuvers, such as vertical loops; and even walking across the wing as an aircraft flew at full speed beneath a bridge. | D19: Which choice completes the text so that it conforms to the conventions of Standard English? | E19: A. Lựa chọn A B. Lựa chọn B C. Lựa chọn C D. Lựa chọn D | G19: =IF(ISBLANK(F19), "⏳ Chờ đáp án", IF(UPPER(TRIM(F19))="A", "✅ Đúng", "❌ Sai")) | I19: =IF(ISBLANK(H19), "", IF(UPPER(TRIM(H19))="A", "✅ Đúng", "❌ Sai")) | K19: =IF(ISBLANK(J19), "", IF(UPPER(TRIM(J19))="A", "✅ Đúng", "❌ Sai")) | L19: =COUNTIF(G19, "❌ Sai") + COUNTIF(I19, "❌ Sai") + COUNTIF(K19, "❌ Sai") | M19: =IF(ISBLANK(F19), "⏳ Chờ làm", IF(G19="✅ Đúng", "✅ Đúng ngay L1", IF(I19="✅ Đúng", "✅ Đúng ở L2", IF(K19="✅ Đúng", "✅ Đúng ở L3", "❌ Chưa đúng sau 3 lần")))) | N19: =IF(G19="✅ Đúng", 1, IF(I19="✅ Đúng", 0.667, IF(K19="✅ Đúng", 0.333, 0))) | O19: =IF(ISBLANK(F19), "💡 Nhập đáp án vào Lần thử 1", IF(OR(G19="✅ Đúng", I19="✅ Đúng", K19="✅ Đúng"), "✨ Xuất sắc! Bạn đã làm đúng.", IF(NOT(ISBLANK(J19)), "💡 Gợi ý Tầng 3 (Chốt phương pháp): " & "Chọn phương án duy trì đúng hình thái ngữ pháp đồng bộ với các phần tử trước.", IF(NOT(ISBLANK(H19)), "💡 Gợi ý Tầng 2 (Manh mối cấu trúc & Loại trừ): " & "Các phần tử được nối bằng liên từ phải có cùng dạng từ (động từ, danh từ hoặc cụm từ).", "💡 Gợi ý Tầng 1 (Định hướng bối cảnh): " & "Kiểm tra cấu trúc song song (parallelism) trong danh sách các phần tử.")))) | P19: =IF(OR(G19="✅ Đúng", I19="✅ Đúng", K19="✅ Đúng"), "Dùng dấu chấm phẩy (;) phân tách các mục lớn trong danh sách phức tạp.", "🔒 Trả lời đúng để mở khóa Strategic Tip!")
A20: Q16 | B20: Standard English Conventions (Participles) | C20: During a recent investigation, archaeologists ______ an explanation for the consistent and seemingly deliberate placement of petroglyphs (rock carvings) near water analyzed several sites on Caribbean islands. They discovered that many of the pools near petroglyphs had consistent water levels year-round, creating perfect reflecting surfaces for the carved symbols on the rocks. | D20: Which choice completes the text so that it conforms to the conventions of Standard English? | E20: A. Lựa chọn A B. Lựa chọn B C. Lựa chọn C D. Lựa chọn D | G20: =IF(ISBLANK(F20), "⏳ Chờ đáp án", IF(UPPER(TRIM(F20))="C", "✅ Đúng", "❌ Sai")) | I20: =IF(ISBLANK(H20), "", IF(UPPER(TRIM(H20))="C", "✅ Đúng", "❌ Sai")) | K20: =IF(ISBLANK(J20), "", IF(UPPER(TRIM(J20))="C", "✅ Đúng", "❌ Sai")) | L20: =COUNTIF(G20, "❌ Sai") + COUNTIF(I20, "❌ Sai") + COUNTIF(K20, "❌ Sai") | M20: =IF(ISBLANK(F20), "⏳ Chờ làm", IF(G20="✅ Đúng", "✅ Đúng ngay L1", IF(I20="✅ Đúng", "✅ Đúng ở L2", IF(K20="✅ Đúng", "✅ Đúng ở L3", "❌ Chưa đúng sau 3 lần")))) | N20: =IF(G20="✅ Đúng", 1, IF(I20="✅ Đúng", 0.667, IF(K20="✅ Đúng", 0.333, 0))) | O20: =IF(ISBLANK(F20), "💡 Nhập đáp án vào Lần thử 1", IF(OR(G20="✅ Đúng", I20="✅ Đúng", K20="✅ Đúng"), "✨ Xuất sắc! Bạn đã làm đúng.", IF(NOT(ISBLANK(J20)), "💡 Gợi ý Tầng 3 (Chốt phương pháp): " & "Chọn dạng phân từ phù hợp với cấu trúc ngữ pháp của câu.", IF(NOT(ISBLANK(H20)), "💡 Gợi ý Tầng 2 (Manh mối cấu trúc & Loại trừ): " & "Phân biệt giữa dạng phân từ làm tính từ bổ nghĩa và động từ chia thì chính.", "💡 Gợi ý Tầng 1 (Định hướng bối cảnh): " & "Phân tích vai trò ngữ pháp của từ cần điền trong mệnh đề chính.")))) | P20: =IF(OR(G20="✅ Đúng", I20="✅ Đúng", K20="✅ Đúng"), "Rút gọn mệnh đề quan hệ chủ động: archaeologists who were seeking -> archaeologists seeking.", "🔒 Trả lời đúng để mở khóa Strategic Tip!")
A21: Q17 | B21: Standard English Conventions (Punctuation Dashes) | C21: For his mash-up “Smells Like Rockin’ Robin,” DJ Mark Vidler layered Kurt Cobain’s minor-key vocals from “Smells Like Teen Spirit” over the Jackson 5’s major-key blues progression from “Rockin’ ______ by inserting the grunge singer’s vocal melody as pitch-shifted “blue notes” within the pop-soul group’s harmonic framework, creates an intensified “bluesy” sound and subverts the expectations of listeners familiar with either musical source. | D21: Which choice completes the text so that it conforms to the conventions of Standard English? | E21: A. Lựa chọn A B. Lựa chọn B C. Lựa chọn C D. Lựa chọn D | G21: =IF(ISBLANK(F21), "⏳ Chờ đáp án", IF(UPPER(TRIM(F21))="D", "✅ Đúng", "❌ Sai")) | I21: =IF(ISBLANK(H21), "", IF(UPPER(TRIM(H21))="D", "✅ Đúng", "❌ Sai")) | K21: =IF(ISBLANK(J21), "", IF(UPPER(TRIM(J21))="D", "✅ Đúng", "❌ Sai")) | L21: =COUNTIF(G21, "❌ Sai") + COUNTIF(I21, "❌ Sai") + COUNTIF(K21, "❌ Sai") | M21: =IF(ISBLANK(F21), "⏳ Chờ làm", IF(G21="✅ Đúng", "✅ Đúng ngay L1", IF(I21="✅ Đúng", "✅ Đúng ở L2", IF(K21="✅ Đúng", "✅ Đúng ở L3", "❌ Chưa đúng sau 3 lần")))) | N21: =IF(G21="✅ Đúng", 1, IF(I21="✅ Đúng", 0.667, IF(K21="✅ Đúng", 0.333, 0))) | O21: =IF(ISBLANK(F21), "💡 Nhập đáp án vào Lần thử 1", IF(OR(G21="✅ Đúng", I21="✅ Đúng", K21="✅ Đúng"), "✨ Xuất sắc! Bạn đã làm đúng.", IF(NOT(ISBLANK(J21)), "💡 Gợi ý Tầng 3 (Chốt phương pháp): " & "Loại bỏ phương án thiếu dấu ngắt hoặc dùng sai kết hợp dấu.", IF(NOT(ISBLANK(H21)), "💡 Gợi ý Tầng 2 (Manh mối cấu trúc & Loại trừ): " & "Sử dụng cặp dấu gạch ngang đồng bộ để ngắt mở và ngắt kết thúc cụm bổ nghĩa.", "💡 Gợi ý Tầng 1 (Định hướng bối cảnh): " & "Xác định cụm từ bổ sung thông tin không thiết yếu trong câu.")))) | P21: =IF(OR(G21="✅ Đúng", I21="✅ Đúng", K21="✅ Đúng"), "Dấu gạch ngang đơn dùng để nhấn mạnh cụm từ bổ nghĩa ở cuối câu.", "🔒 Trả lời đúng để mở khóa Strategic Tip!")
A22: Q18 | B22: Standard English Conventions (Punctuation & Prepositional Phrases) | C22: During the late nineteenth century, agricultural chemist George Washington Carver revolutionized farming practices in the American ______ promoting systematic crop rotation techniques that replenished essential nitrogen in depleted soils. | D22: Which choice completes the text so that it conforms to the conventions of Standard English? | E22: A. South, by B. South by C. South; by D. South: by | G22: =IF(ISBLANK(F22), "⏳ Chờ đáp án", IF(UPPER(TRIM(F22))="B", "✅ Đúng", "❌ Sai")) | I22: =IF(ISBLANK(H22), "", IF(UPPER(TRIM(H22))="B", "✅ Đúng", "❌ Sai")) | K22: =IF(ISBLANK(J22), "", IF(UPPER(TRIM(J22))="B", "✅ Đúng", "❌ Sai")) | L22: =COUNTIF(G22, "❌ Sai") + COUNTIF(I22, "❌ Sai") + COUNTIF(K22, "❌ Sai") | M22: =IF(ISBLANK(F22), "⏳ Chờ làm", IF(G22="✅ Đúng", "✅ Đúng ngay L1", IF(I22="✅ Đúng", "✅ Đúng ở L2", IF(K22="✅ Đúng", "✅ Đúng ở L3", "❌ Chưa đúng sau 3 lần")))) | N22: =IF(G22="✅ Đúng", 1, IF(I22="✅ Đúng", 0.667, IF(K22="✅ Đúng", 0.333, 0))) | O22: =IF(ISBLANK(F22), "💡 Nhập đáp án vào Lần thử 1", IF(OR(G22="✅ Đúng", I22="✅ Đúng", K22="✅ Đúng"), "✨ Xuất sắc! Bạn đã làm đúng.", IF(NOT(ISBLANK(J22)), "💡 Gợi ý Tầng 3 (Chốt phương pháp): " & "Chọn giới từ đúng theo quy tắc kết hợp từ chuẩn tiếng Anh.", IF(NOT(ISBLANK(H22)), "💡 Gợi ý Tầng 2 (Manh mối cấu trúc & Loại trừ): " & "Thói quen sử dụng từ (collocation) quy định giới từ chuẩn xác trong ngữ cảnh này.", "💡 Gợi ý Tầng 1 (Định hướng bối cảnh): " & "Xác định giới từ đi kèm cố định với danh từ hoặc động từ đứng trước.")))) | P22: =IF(OR(G22="✅ Đúng", I22="✅ Đúng", K22="✅ Đúng"), "Không đặt dấu phẩy ngăn cách trực tiếp trước giới từ chỉ phương thức.", "🔒 Trả lời đúng để mở khóa Strategic Tip!")
A23: Q19 | B23: Standard English Conventions (Boundaries & Sentence Structure) | C23: Named for the year in which it was detected by English astronomers, SN 2016aps was a supernova (the explosion of a massive ______ in the constellation Draco, 3.6 billion light-years from Earth, the transient yet powerful blast propelled particles and debris into space at extremely high speeds. | D23: Which choice completes the text so that it conforms to the conventions of Standard English? | E23: A. star). Occurring B. star) occurring C. star) and occurring D. star), occurring | G23: =IF(ISBLANK(F23), "⏳ Chờ đáp án", IF(UPPER(TRIM(F23))="A", "✅ Đúng", "❌ Sai")) | I23: =IF(ISBLANK(H23), "", IF(UPPER(TRIM(H23))="A", "✅ Đúng", "❌ Sai")) | K23: =IF(ISBLANK(J23), "", IF(UPPER(TRIM(J23))="A", "✅ Đúng", "❌ Sai")) | L23: =COUNTIF(G23, "❌ Sai") + COUNTIF(I23, "❌ Sai") + COUNTIF(K23, "❌ Sai") | M23: =IF(ISBLANK(F23), "⏳ Chờ làm", IF(G23="✅ Đúng", "✅ Đúng ngay L1", IF(I23="✅ Đúng", "✅ Đúng ở L2", IF(K23="✅ Đúng", "✅ Đúng ở L3", "❌ Chưa đúng sau 3 lần")))) | N23: =IF(G23="✅ Đúng", 1, IF(I23="✅ Đúng", 0.667, IF(K23="✅ Đúng", 0.333, 0))) | O23: =IF(ISBLANK(F23), "💡 Nhập đáp án vào Lần thử 1", IF(OR(G23="✅ Đúng", I23="✅ Đúng", K23="✅ Đúng"), "✨ Xuất sắc! Bạn đã làm đúng.", IF(NOT(ISBLANK(J23)), "💡 Gợi ý Tầng 3 (Chốt phương pháp): " & "Chọn dạng từ đảm bảo câu có đủ chủ ngữ và vị ngữ hoàn chỉnh.", IF(NOT(ISBLANK(H23)), "💡 Gợi ý Tầng 2 (Manh mối cấu trúc & Loại trừ): " & "Tránh lỗi câu thiếu vị ngữ (fragment) hoặc thừa vị ngữ nối sai quy tắc.", "💡 Gợi ý Tầng 1 (Định hướng bối cảnh): " & "Phân tích cấu trúc câu để xác định xem đã có động từ chính chia thì chưa.")))) | P23: =IF(OR(G23="✅ Đúng", I23="✅ Đúng", K23="✅ Đúng"), "Tránh lỗi Comma Splice bằng cách kết thúc câu bằng dấu chấm.", "🔒 Trả lời đúng để mở khóa Strategic Tip!")
A24: Q20 | B24: Standard English Conventions (Dangling & Misplaced Modifiers) | C24: Originating during the Cretaceous period, ______ | D24: Which choice completes the text so that it conforms to the conventions of Standard English? | E24: A. entomologists have extensively examined fossilized resin deposits excavated in northern Myanmar. B. the fossilized amber specimens excavated in northern Myanmar preserve unprecedented anatomical details of early arthropods. C. paleontological excavation in northern Myanmar has uncovered numerous ancient arthropods. D. arthropods were trapped and entombed within sticky conifer secretions. | G24: =IF(ISBLANK(F24), "⏳ Chờ đáp án", IF(UPPER(TRIM(F24))="B", "✅ Đúng", "❌ Sai")) | I24: =IF(ISBLANK(H24), "", IF(UPPER(TRIM(H24))="B", "✅ Đúng", "❌ Sai")) | K24: =IF(ISBLANK(J24), "", IF(UPPER(TRIM(J24))="B", "✅ Đúng", "❌ Sai")) | L24: =COUNTIF(G24, "❌ Sai") + COUNTIF(I24, "❌ Sai") + COUNTIF(K24, "❌ Sai") | M24: =IF(ISBLANK(F24), "⏳ Chờ làm", IF(G24="✅ Đúng", "✅ Đúng ngay L1", IF(I24="✅ Đúng", "✅ Đúng ở L2", IF(K24="✅ Đúng", "✅ Đúng ở L3", "❌ Chưa đúng sau 3 lần")))) | N24: =IF(G24="✅ Đúng", 1, IF(I24="✅ Đúng", 0.667, IF(K24="✅ Đúng", 0.333, 0))) | O24: =IF(ISBLANK(F24), "💡 Nhập đáp án vào Lần thử 1", IF(OR(G24="✅ Đúng", I24="✅ Đúng", K24="✅ Đúng"), "✨ Xuất sắc! Bạn đã làm đúng.", IF(NOT(ISBLANK(J24)), "💡 Gợi ý Tầng 3 (Chốt phương pháp): " & "Chọn phương án đặt đúng chủ thể thực hiện hành động vào vị trí ngay sau dấu phẩy.", IF(NOT(ISBLANK(H24)), "💡 Gợi ý Tầng 2 (Manh mối cấu trúc & Loại trừ): " & "Chủ ngữ đứng ngay sau dấu phẩy bắt buộc phải là đối tượng thực hiện trực tiếp hành động đó.", "💡 Gợi ý Tầng 1 (Định hướng bối cảnh): " & "Kiểm tra cụm mở đầu câu dạng `-ing` hoặc `-ed` đứng trước dấu phẩy.")))) | P24: =IF(OR(G24="✅ Đúng", I24="✅ Đúng", K24="✅ Đúng"), "Bổ ngữ chỉ thời đại/nguồn gốc phải đi liền với danh từ hổ phách/hóa thạch.", "🔒 Trả lời đúng để mở khóa Strategic Tip!")
A25: Q21 | B25: Transitions & Discourse Connectors (Contrast) | C25: In a 1993 study by Vales and Peek, the researchers used microhistological fecal analysis to determine the ratio of three plant subtypes (graminoids, forbs, and browse) within the diets of North American ungulates. The researchers did not perform this analysis on all such ungulates, ______ they focused exclusively on elk in Wyoming. | D25: Which choice completes the text with the most logical transition? | E25: A. for instance; B. in other words; C. regardless; D. however; | G25: =IF(ISBLANK(F25), "⏳ Chờ đáp án", IF(UPPER(TRIM(F25))="D", "✅ Đúng", "❌ Sai")) | I25: =IF(ISBLANK(H25), "", IF(UPPER(TRIM(H25))="D", "✅ Đúng", "❌ Sai")) | K25: =IF(ISBLANK(J25), "", IF(UPPER(TRIM(J25))="D", "✅ Đúng", "❌ Sai")) | L25: =COUNTIF(G25, "❌ Sai") + COUNTIF(I25, "❌ Sai") + COUNTIF(K25, "❌ Sai") | M25: =IF(ISBLANK(F25), "⏳ Chờ làm", IF(G25="✅ Đúng", "✅ Đúng ngay L1", IF(I25="✅ Đúng", "✅ Đúng ở L2", IF(K25="✅ Đúng", "✅ Đúng ở L3", "❌ Chưa đúng sau 3 lần")))) | N25: =IF(G25="✅ Đúng", 1, IF(I25="✅ Đúng", 0.667, IF(K25="✅ Đúng", 0.333, 0))) | O25: =IF(ISBLANK(F25), "💡 Nhập đáp án vào Lần thử 1", IF(OR(G25="✅ Đúng", I25="✅ Đúng", K25="✅ Đúng"), "✨ Xuất sắc! Bạn đã làm đúng.", IF(NOT(ISBLANK(J25)), "💡 Gợi ý Tầng 3 (Chốt phương pháp): " & "Chọn từ nối chỉ sự tương phản hoặc nhượng bộ phù hợp.", IF(NOT(ISBLANK(H25)), "💡 Gợi ý Tầng 2 (Manh mối cấu trúc & Loại trừ): " & "Xác định xem câu sau có xu hướng đối lập hay làm trái ngược ý của câu trước hay không.", "💡 Gợi ý Tầng 1 (Định hướng bối cảnh): " & "Phân tích mối quan hệ logic giữa hai câu văn về mặt ý nghĩa.")))) | P25: =IF(OR(G25="✅ Đúng", I25="✅ Đúng", K25="✅ Đúng"), "However = dùng để đối lập giữa giả định chung và phạm vi hẹp thực tế.", "🔒 Trả lời đúng để mở khóa Strategic Tip!")
A26: Q22 | B26: Transitions & Discourse Connectors (Cause & Effect / Conclusion) | C26: The Hornbostel-Sachs system classifies musical instruments by how they produce sound. For example, an instrument that is popular in India called the saraswati veena produces sound primarily through the vibration of its strings. ______ under the Hornbostel-Sachs system, the saraswati veena is a chordophone. | D26: Which choice completes the text with the most logical transition? | E26: A. Furthermore, B. Thus, C. Similarly, D. Instead, | G26: =IF(ISBLANK(F26), "⏳ Chờ đáp án", IF(UPPER(TRIM(F26))="B", "✅ Đúng", "❌ Sai")) | I26: =IF(ISBLANK(H26), "", IF(UPPER(TRIM(H26))="B", "✅ Đúng", "❌ Sai")) | K26: =IF(ISBLANK(J26), "", IF(UPPER(TRIM(J26))="B", "✅ Đúng", "❌ Sai")) | L26: =COUNTIF(G26, "❌ Sai") + COUNTIF(I26, "❌ Sai") + COUNTIF(K26, "❌ Sai") | M26: =IF(ISBLANK(F26), "⏳ Chờ làm", IF(G26="✅ Đúng", "✅ Đúng ngay L1", IF(I26="✅ Đúng", "✅ Đúng ở L2", IF(K26="✅ Đúng", "✅ Đúng ở L3", "❌ Chưa đúng sau 3 lần")))) | N26: =IF(G26="✅ Đúng", 1, IF(I26="✅ Đúng", 0.667, IF(K26="✅ Đúng", 0.333, 0))) | O26: =IF(ISBLANK(F26), "💡 Nhập đáp án vào Lần thử 1", IF(OR(G26="✅ Đúng", I26="✅ Đúng", K26="✅ Đúng"), "✨ Xuất sắc! Bạn đã làm đúng.", IF(NOT(ISBLANK(J26)), "💡 Gợi ý Tầng 3 (Chốt phương pháp): " & "Chọn từ nối chỉ ví dụ hoặc sự minh họa cụ thể.", IF(NOT(ISBLANK(H26)), "💡 Gợi ý Tầng 2 (Manh mối cấu trúc & Loại trừ): " & "Nếu câu thứ hai đưa ra một trường hợp cụ thể để minh họa, cần dùng từ nối minh họa.", "💡 Gợi ý Tầng 1 (Định hướng bối cảnh): " & "Xác định vai trò của câu thứ hai đối với câu thứ nhất.")))) | P26: =IF(OR(G26="✅ Đúng", I26="✅ Đúng", K26="✅ Đúng"), "Thus = kết luận logic rút ra từ định nghĩa trước đó.", "🔒 Trả lời đúng để mở khóa Strategic Tip!")
A27: Q23 | B27: Transitions & Discourse Connectors (Exemplification) | C27: Generally, sleek vehicles are more aerodynamic than bulkier ones. The streamlined nose of the Airbus A350 XWB jet, ______ helps it glide through wind with relative ease, while a boxy pickup truck encounters more wind resistance, making it less aerodynamic. | D27: Which choice completes the text with the most logical transition? | E27: A. additionally, B. however, C. for example, D. meanwhile, | G27: =IF(ISBLANK(F27), "⏳ Chờ đáp án", IF(UPPER(TRIM(F27))="C", "✅ Đúng", "❌ Sai")) | I27: =IF(ISBLANK(H27), "", IF(UPPER(TRIM(H27))="C", "✅ Đúng", "❌ Sai")) | K27: =IF(ISBLANK(J27), "", IF(UPPER(TRIM(J27))="C", "✅ Đúng", "❌ Sai")) | L27: =COUNTIF(G27, "❌ Sai") + COUNTIF(I27, "❌ Sai") + COUNTIF(K27, "❌ Sai") | M27: =IF(ISBLANK(F27), "⏳ Chờ làm", IF(G27="✅ Đúng", "✅ Đúng ngay L1", IF(I27="✅ Đúng", "✅ Đúng ở L2", IF(K27="✅ Đúng", "✅ Đúng ở L3", "❌ Chưa đúng sau 3 lần")))) | N27: =IF(G27="✅ Đúng", 1, IF(I27="✅ Đúng", 0.667, IF(K27="✅ Đúng", 0.333, 0))) | O27: =IF(ISBLANK(F27), "💡 Nhập đáp án vào Lần thử 1", IF(OR(G27="✅ Đúng", I27="✅ Đúng", K27="✅ Đúng"), "✨ Xuất sắc! Bạn đã làm đúng.", IF(NOT(ISBLANK(J27)), "💡 Gợi ý Tầng 3 (Chốt phương pháp): " & "Chọn từ nối phản ánh chính xác sự so sánh hoặc tương phản logic.", IF(NOT(ISBLANK(H27)), "💡 Gợi ý Tầng 2 (Manh mối cấu trúc & Loại trừ): " & "Xác định mối quan hệ tương đồng hay đối lập giữa hai phát biểu.", "💡 Gợi ý Tầng 1 (Định hướng bối cảnh): " & "So sánh ý nghĩa giữa hai mệnh đề được nối với nhau.")))) | P27: =IF(OR(G27="✅ Đúng", I27="✅ Đúng", K27="✅ Đúng"), "Meanwhile / whereas = nối hai vế đối lập song song.", "🔒 Trả lời đúng để mở khóa Strategic Tip!")
A28: Q24 | B28: Transitions & Discourse Connectors (Emphasis / Reinforcement) | C28: On June 13, 1927, aviator Charles Lindbergh received a ticker-tape parade in New York City in recognition of his transatlantic flight. Of the 206 ticker-tape parades held between 1886 and 2022, a number were for achievements in aviation. ______ Lindbergh’s parade was just one of 16 honoring pilots. | D28: Which choice completes the text with the most logical transition? | E28: A. Therefore, B. Indeed, C. In addition, D. Nevertheless, | G28: =IF(ISBLANK(F28), "⏳ Chờ đáp án", IF(UPPER(TRIM(F28))="B", "✅ Đúng", "❌ Sai")) | I28: =IF(ISBLANK(H28), "", IF(UPPER(TRIM(H28))="B", "✅ Đúng", "❌ Sai")) | K28: =IF(ISBLANK(J28), "", IF(UPPER(TRIM(J28))="B", "✅ Đúng", "❌ Sai")) | L28: =COUNTIF(G28, "❌ Sai") + COUNTIF(I28, "❌ Sai") + COUNTIF(K28, "❌ Sai") | M28: =IF(ISBLANK(F28), "⏳ Chờ làm", IF(G28="✅ Đúng", "✅ Đúng ngay L1", IF(I28="✅ Đúng", "✅ Đúng ở L2", IF(K28="✅ Đúng", "✅ Đúng ở L3", "❌ Chưa đúng sau 3 lần")))) | N28: =IF(G28="✅ Đúng", 1, IF(I28="✅ Đúng", 0.667, IF(K28="✅ Đúng", 0.333, 0))) | O28: =IF(ISBLANK(F28), "💡 Nhập đáp án vào Lần thử 1", IF(OR(G28="✅ Đúng", I28="✅ Đúng", K28="✅ Đúng"), "✨ Xuất sắc! Bạn đã làm đúng.", IF(NOT(ISBLANK(J28)), "💡 Gợi ý Tầng 3 (Chốt phương pháp): " & "Chọn từ nối mang nghĩa 'thật vậy' hoặc 'trên thực tế'.", IF(NOT(ISBLANK(H28)), "💡 Gợi ý Tầng 2 (Manh mối cấu trúc & Loại trừ): " & "Nếu câu thứ hai nhằm nhấn mạnh hoặc khẳng định mạnh mẽ hơn ý trước, chọn từ nối nhấn mạnh.", "💡 Gợi ý Tầng 1 (Định hướng bối cảnh): " & "Phân tích sắc thái của phát biểu ở câu thứ hai.")))) | P28: =IF(OR(G28="✅ Đúng", I28="✅ Đúng", K28="✅ Đúng"), "Indeed = dùng để nhấn mạnh/xác nhận thông tin trước.", "🔒 Trả lời đúng để mở khóa Strategic Tip!")
A29: Q25 | B29: Transitions & Clause-Level Logic (Contrast & Concession) | C29: Between February 1876 and September 1876, George Eliot’s novel Daniel Deronda was serialized in eight parts in Blackwood’s Magazine. Scholars typically regard the serial version of Eliot’s novel as less authoritative than the version later published in book form. ______ as scholar Philip Allingham notes, serialized texts were the versions in which the nineteenth-century readership first “saw itself and its world reflected, and to which it responded, often with great emotion.” | D29: Which choice completes the text with the most logical transition? | E29: A. Accordingly, they emphasize the appeal of the serial version for Victorian audiences; B. Still, the serial version is important to an understanding of the novel’s historical context; C. Consequently, the book version of the novel is often favored over the serial version; D. However, others regard the serial version as a more faithful representation of Eliot’s intentions; | G29: =IF(ISBLANK(F29), "⏳ Chờ đáp án", IF(UPPER(TRIM(F29))="B", "✅ Đúng", "❌ Sai")) | I29: =IF(ISBLANK(H29), "", IF(UPPER(TRIM(H29))="B", "✅ Đúng", "❌ Sai")) | K29: =IF(ISBLANK(J29), "", IF(UPPER(TRIM(J29))="B", "✅ Đúng", "❌ Sai")) | L29: =COUNTIF(G29, "❌ Sai") + COUNTIF(I29, "❌ Sai") + COUNTIF(K29, "❌ Sai") | M29: =IF(ISBLANK(F29), "⏳ Chờ làm", IF(G29="✅ Đúng", "✅ Đúng ngay L1", IF(I29="✅ Đúng", "✅ Đúng ở L2", IF(K29="✅ Đúng", "✅ Đúng ở L3", "❌ Chưa đúng sau 3 lần")))) | N29: =IF(G29="✅ Đúng", 1, IF(I29="✅ Đúng", 0.667, IF(K29="✅ Đúng", 0.333, 0))) | O29: =IF(ISBLANK(F29), "💡 Nhập đáp án vào Lần thử 1", IF(OR(G29="✅ Đúng", I29="✅ Đúng", K29="✅ Đúng"), "✨ Xuất sắc! Bạn đã làm đúng.", IF(NOT(ISBLANK(J29)), "💡 Gợi ý Tầng 3 (Chốt phương pháp): " & "Chọn từ nối liên kết mượt mà và đúng sắc thái chuyển ý.", IF(NOT(ISBLANK(H29)), "💡 Gợi ý Tầng 2 (Manh mối cấu trúc & Loại trừ): " & "Xác định mối quan hệ giữa thông tin thực tế và nhận định được đưa ra.", "💡 Gợi ý Tầng 1 (Định hướng bối cảnh): " & "Xem xét bối cảnh và sự chuyển ý giữa hai đoạn văn.")))) | P29: =IF(OR(G29="✅ Đúng", I29="✅ Đúng", K29="✅ Đúng"), "Still = tuy nhiên, chuyển hướng sang khía cạnh tích cực khác.", "🔒 Trả lời đúng để mở khóa Strategic Tip!")
A30: Q26 | B30: Rhetorical Synthesis (Audience Adaptation / Introducing a Concept) | C30: • The Highpointers Club is a hiking club. • One of the main goals among club members is to reach the highest points in all fifty US states. • Those who achieve this are called 50 Completers. • In Suk Han became a 50 Completer on November 15, 2013. • The highest point in Wisconsin is Timms Hill, at 1,951 ft. • The highest point in Wyoming is Gannett Peak, at 13,809 ft. | D30: Which choice most effectively uses information from the given sentences to explain the 50 Completers hiking challenge to a new audience? | E30: A. If you are looking for a new hiking challenge, consider joining the Highpointers Club, as did In Suk Han, a hiker who successfully reached the highest point in every US state. B. Not until after you have reached the highest points in all fifty US states—including Timms Hill in Wisconsin and Gannett Peak in Wyoming—can you include yourself among the 50 Completers of the Highpointers Club. C. On November 15, 2013, In Suk Han finally completed the feat of reaching the highest point in all fifty US states, including Timms Hill in Wisconsin and Gannett Peak in Wyoming. D. Hikers aiming to count themselves among the 50 Completers must reach not only Wisconsin’s Timms Hill but also the even higher peak of Gannett Peak in Wyoming. | G30: =IF(ISBLANK(F30), "⏳ Chờ đáp án", IF(UPPER(TRIM(F30))="B", "✅ Đúng", "❌ Sai")) | I30: =IF(ISBLANK(H30), "", IF(UPPER(TRIM(H30))="B", "✅ Đúng", "❌ Sai")) | K30: =IF(ISBLANK(J30), "", IF(UPPER(TRIM(J30))="B", "✅ Đúng", "❌ Sai")) | L30: =COUNTIF(G30, "❌ Sai") + COUNTIF(I30, "❌ Sai") + COUNTIF(K30, "❌ Sai") | M30: =IF(ISBLANK(F30), "⏳ Chờ làm", IF(G30="✅ Đúng", "✅ Đúng ngay L1", IF(I30="✅ Đúng", "✅ Đúng ở L2", IF(K30="✅ Đúng", "✅ Đúng ở L3", "❌ Chưa đúng sau 3 lần")))) | N30: =IF(G30="✅ Đúng", 1, IF(I30="✅ Đúng", 0.667, IF(K30="✅ Đúng", 0.333, 0))) | O30: =IF(ISBLANK(F30), "💡 Nhập đáp án vào Lần thử 1", IF(OR(G30="✅ Đúng", I30="✅ Đúng", K30="✅ Đúng"), "✨ Xuất sắc! Bạn đã làm đúng.", IF(NOT(ISBLANK(J30)), "💡 Gợi ý Tầng 3 (Chốt phương pháp): " & "Chọn câu tổng hợp đáp ứng chính xác yêu cầu đề bài.", IF(NOT(ISBLANK(H30)), "💡 Gợi ý Tầng 2 (Manh mối cấu trúc & Loại trừ): " & "Lọc danh sách ghi chú để tìm thông tin trực tiếp liên quan đến mục tiêu.", "💡 Gợi ý Tầng 1 (Định hướng bối cảnh): " & "Đọc kỹ yêu cầu đề bài để biết thông tin nào cần được làm nổi bật.")))) | P30: =IF(OR(G30="✅ Đúng", I30="✅ Đúng", K30="✅ Đúng"), "Giải thích thử thách = Nêu điều kiện hoàn thành + Ví dụ các đỉnh núi.", "🔒 Trả lời đúng để mở khóa Strategic Tip!")
A31: Q27 | B31: Rhetorical Synthesis (Achieving a Specific Goal / Superiority Comparison) | C31: While researching a topic, a student has taken the following notes: • Enhanced rock weathering (ERW) is a method of spreading crushed basalt on farmland to capture carbon dioxide (CO2) and improve soil health. • ERW increases crop yields and removes harmful CO2 from the air. • ERW offers a low-cost, low-tech alternative to expensive, energy-intensive carbon capture methods. • The CO2 captured by ERW becomes stable bicarbonate in soil water, which eventually streams into the ocean to remain safely stored for hundreds of years. • ERW can improve rural economies by reducing farmers’ need for fertilizers and increasing their earnings from carbon credits. | D31: The student wants to explain why ERW is a superior method for capturing CO2. Which choice most effectively uses relevant information from the notes to accomplish this goal? | E31: A. ERW improves soil health and helps farmers increase their income from selling carbon credits. B. ERW removes CO2 from the air in a way that is both low-cost and low-tech. C. The CO2 captured by ERW becomes stable bicarbonate, which improves soil health by remaining in the ocean for hundreds of years. D. ERW is a method of spreading crushed basalt on farmland to capture CO2, improving rural economies. | G31: =IF(ISBLANK(F31), "⏳ Chờ đáp án", IF(UPPER(TRIM(F31))="B", "✅ Đúng", "❌ Sai")) | I31: =IF(ISBLANK(H31), "", IF(UPPER(TRIM(H31))="B", "✅ Đúng", "❌ Sai")) | K31: =IF(ISBLANK(J31), "", IF(UPPER(TRIM(J31))="B", "✅ Đúng", "❌ Sai")) | L31: =COUNTIF(G31, "❌ Sai") + COUNTIF(I31, "❌ Sai") + COUNTIF(K31, "❌ Sai") | M31: =IF(ISBLANK(F31), "⏳ Chờ làm", IF(G31="✅ Đúng", "✅ Đúng ngay L1", IF(I31="✅ Đúng", "✅ Đúng ở L2", IF(K31="✅ Đúng", "✅ Đúng ở L3", "❌ Chưa đúng sau 3 lần")))) | N31: =IF(G31="✅ Đúng", 1, IF(I31="✅ Đúng", 0.667, IF(K31="✅ Đúng", 0.333, 0))) | O31: =IF(ISBLANK(F31), "💡 Nhập đáp án vào Lần thử 1", IF(OR(G31="✅ Đúng", I31="✅ Đúng", K31="✅ Đúng"), "✨ Xuất sắc! Bạn đã làm đúng.", IF(NOT(ISBLANK(J31)), "💡 Gợi ý Tầng 3 (Chốt phương pháp): " & "Chọn câu diễn đạt nêu bật sự đối lập hoặc tương đồng theo yêu cầu.", IF(NOT(ISBLANK(H31)), "💡 Gợi ý Tầng 2 (Manh mối cấu trúc & Loại trừ): " & "Chọn các ghi chú cung cấp dữ liệu đối sánh trực tiếp.", "💡 Gợi ý Tầng 1 (Định hướng bối cảnh): " & "Xác định mục tiêu nhấn mạnh sự khác biệt hay điểm chung giữa hai đối tượng.")))) | P31: =IF(OR(G31="✅ Đúng", I31="✅ Đúng", K31="✅ Đúng"), "Chỉ ra điểm vượt trội trực tiếp: 'low-cost and low-tech alternative'.", "🔒 Trả lời đúng để mở khóa Strategic Tip!")

Sheet Math_Module1
A1: Digital SAT Practice Test - October 2026: Math Module 1
A2: Chiến thuật: Tự thử sức ở Lần 1 (Cột F) -> Nhận phản hồi tự động & Gợi ý định hướng logic mà không làm lộ đáp án.
A4: Q# | B4: Topic / Skill Focus | C4: Passage & Context | D4: Question Prompt / Calculator | E4: Options / Choices (No Answer) | F4: Lần thử 1 | G4: Kết quả L1 | H4: Lần thử 2 | I4: Kết quả L2 | J4: Lần thử 3 | K4: Kết quả L3 | L4: Tổng số cột Sai | M4: Trạng thái Hoàn thành | N4: Hiệu suất (%) | O4: Hint / Gợi ý Đa tầng (Không đáp án) | P4: Strategic Tip / Formula
A5: Q1 | B5: Linear Functions & Evaluation | C5: The function h is defined by h(x) = 100x - 50. | D5: Calculator Allowed. What is the value of h(x) when x = 6? | E5: A. Lựa chọn A B. Lựa chọn B C. Lựa chọn C D. Lựa chọn D | G5: =IF(ISBLANK(F5), "⏳ Chờ đáp án", IF(UPPER(TRIM(F5))="C", "✅ Đúng", "❌ Sai")) | I5: =IF(ISBLANK(H5), "", IF(UPPER(TRIM(H5))="C", "✅ Đúng", "❌ Sai")) | K5: =IF(ISBLANK(J5), "", IF(UPPER(TRIM(J5))="C", "✅ Đúng", "❌ Sai")) | L5: =COUNTIF(G5, "❌ Sai") + COUNTIF(I5, "❌ Sai") + COUNTIF(K5, "❌ Sai") | M5: =IF(ISBLANK(F5), "⏳ Chờ làm", IF(G5="✅ Đúng", "✅ Đúng ngay L1", IF(I5="✅ Đúng", "✅ Đúng ở L2", IF(K5="✅ Đúng", "✅ Đúng ở L3", "❌ Chưa đúng sau 3 lần")))) | N5: =IF(G5="✅ Đúng", 1, IF(I5="✅ Đúng", 0.667, IF(K5="✅ Đúng", 0.333, 0))) | O5: =IF(ISBLANK(F5), "💡 Nhập đáp án vào Lần thử 1", IF(OR(G5="✅ Đúng", I5="✅ Đúng", K5="✅ Đúng"), "✨ Xuất sắc! Bạn đã làm đúng.", IF(NOT(ISBLANK(J5)), "💡 Gợi ý Tầng 3 (Chốt phương pháp): " & "Thực hiện phép nhân trước rồi thực hiện phép trừ để tìm giá trị đầu ra.", IF(NOT(ISBLANK(H5)), "💡 Gợi ý Tầng 2 (Manh mối cấu trúc & Loại trừ): " & "Thay giá trị của biến số vào vị trí tương ứng trong công thức hàm số.", "💡 Gợi ý Tầng 1 (Định hướng bối cảnh): " & "Đây là bài toán đánh giá giá trị hàm số tuyến tính h(x) tại một điểm.")))) | P5: =IF(OR(G5="✅ Đúng", I5="✅ Đúng", K5="✅ Đúng"), "Linear Function Evaluation: h(6) = 100(6) - 50 = 550.", "🔒 Trả lời đúng để mở khóa Strategic Tip!")
A6: Q2 | B6: Linear Graph Interpretation (y-intercept) | C6: The graph shown gives the estimated value, in dollars, of a mountain bike as a function of the number of months since it was purchased. The line intersects the y-axis at (0, 275). | D6: Calculator Allowed. What is the best interpretation of the y-intercept of the graph in this context? | E6: A. Lựa chọn A B. Lựa chọn B C. Lựa chọn C D. Lựa chọn D | G6: =IF(ISBLANK(F6), "⏳ Chờ đáp án", IF(UPPER(TRIM(F6))="A", "✅ Đúng", "❌ Sai")) | I6: =IF(ISBLANK(H6), "", IF(UPPER(TRIM(H6))="A", "✅ Đúng", "❌ Sai")) | K6: =IF(ISBLANK(J6), "", IF(UPPER(TRIM(J6))="A", "✅ Đúng", "❌ Sai")) | L6: =COUNTIF(G6, "❌ Sai") + COUNTIF(I6, "❌ Sai") + COUNTIF(K6, "❌ Sai") | M6: =IF(ISBLANK(F6), "⏳ Chờ làm", IF(G6="✅ Đúng", "✅ Đúng ngay L1", IF(I6="✅ Đúng", "✅ Đúng ở L2", IF(K6="✅ Đúng", "✅ Đúng ở L3", "❌ Chưa đúng sau 3 lần")))) | N6: =IF(G6="✅ Đúng", 1, IF(I6="✅ Đúng", 0.667, IF(K6="✅ Đúng", 0.333, 0))) | O6: =IF(ISBLANK(F6), "💡 Nhập đáp án vào Lần thử 1", IF(OR(G6="✅ Đúng", I6="✅ Đúng", K6="✅ Đúng"), "✨ Xuất sắc! Bạn đã làm đúng.", IF(NOT(ISBLANK(J6)), "💡 Gợi ý Tầng 3 (Chốt phương pháp): " & "Trong bối cảnh bài toán, t = 0 đại diện cho thời điểm ban đầu khi bắt đầu theo dõi.", IF(NOT(ISBLANK(H6)), "💡 Gợi ý Tầng 2 (Manh mối cấu trúc & Loại trừ): " & "Tung độ gốc là giá trị của y khi biến độc lập t bằng 0.", "💡 Gợi ý Tầng 1 (Định hướng bối cảnh): " & "Phân tích ý nghĩa của tung độ gốc (y-intercept) trên đồ thị bài toán thực tế.")))) | P6: =IF(OR(G6="✅ Đúng", I6="✅ Đúng", K6="✅ Đúng"), "y-intercept (0, b) represents the initial value at time t = 0.", "🔒 Trả lời đúng để mở khóa Strategic Tip!")
A7: Q3 | B7: Percentages & Basic Calculations | C7: Out of 200 attempts, 55% were successful. | D7: Calculator Allowed. How many of these attempts were successful? | E7: Student-Produced Response (Grid-in) | G7: =IF(ISBLANK(F7), "⏳ Chờ đáp án", IF(UPPER(TRIM(F7))="110", "✅ Đúng", "❌ Sai")) | I7: =IF(ISBLANK(H7), "", IF(UPPER(TRIM(H7))="110", "✅ Đúng", "❌ Sai")) | K7: =IF(ISBLANK(J7), "", IF(UPPER(TRIM(J7))="110", "✅ Đúng", "❌ Sai")) | L7: =COUNTIF(G7, "❌ Sai") + COUNTIF(I7, "❌ Sai") + COUNTIF(K7, "❌ Sai") | M7: =IF(ISBLANK(F7), "⏳ Chờ làm", IF(G7="✅ Đúng", "✅ Đúng ngay L1", IF(I7="✅ Đúng", "✅ Đúng ở L2", IF(K7="✅ Đúng", "✅ Đúng ở L3", "❌ Chưa đúng sau 3 lần")))) | N7: =IF(G7="✅ Đúng", 1, IF(I7="✅ Đúng", 0.667, IF(K7="✅ Đúng", 0.333, 0))) | O7: =IF(ISBLANK(F7), "💡 Nhập đáp án vào Lần thử 1", IF(OR(G7="✅ Đúng", I7="✅ Đúng", K7="✅ Đúng"), "✨ Xuất sắc! Bạn đã làm đúng.", IF(NOT(ISBLANK(J7)), "💡 Gợi ý Tầng 3 (Chốt phương pháp): " & "Nhân số thập phân vừa tìm được với giá trị tổng ban đầu.", IF(NOT(ISBLANK(H7)), "💡 Gợi ý Tầng 2 (Manh mối cấu trúc & Loại trừ): " & "Chuyển đổi tỉ lệ phần trăm thành số thập phân bằng cách chia cho 100.", "💡 Gợi ý Tầng 1 (Định hướng bối cảnh): " & "Bài toán yêu cầu tính giá trị phần trăm của một số nguyên cho trước.")))) | P7: =IF(OR(G7="✅ Đúng", I7="✅ Đúng", K7="✅ Đúng"), "Percent of Total: Number = Percentage * Total = 0.55 * 200 = 110.", "🔒 Trả lời đúng để mở khóa Strategic Tip!")
A8: Q4 | B8: Equivalent Algebraic Expressions | C8: Given the expression: 29x^2 + 29. | D8: Calculator Allowed. Which expression is equivalent to 29x^2 + 29? | E8: A. Lựa chọn A B. Lựa chọn B C. Lựa chọn C D. Lựa chọn D | G8: =IF(ISBLANK(F8), "⏳ Chờ đáp án", IF(UPPER(TRIM(F8))="A", "✅ Đúng", "❌ Sai")) | I8: =IF(ISBLANK(H8), "", IF(UPPER(TRIM(H8))="A", "✅ Đúng", "❌ Sai")) | K8: =IF(ISBLANK(J8), "", IF(UPPER(TRIM(J8))="A", "✅ Đúng", "❌ Sai")) | L8: =COUNTIF(G8, "❌ Sai") + COUNTIF(I8, "❌ Sai") + COUNTIF(K8, "❌ Sai") | M8: =IF(ISBLANK(F8), "⏳ Chờ làm", IF(G8="✅ Đúng", "✅ Đúng ngay L1", IF(I8="✅ Đúng", "✅ Đúng ở L2", IF(K8="✅ Đúng", "✅ Đúng ở L3", "❌ Chưa đúng sau 3 lần")))) | N8: =IF(G8="✅ Đúng", 1, IF(I8="✅ Đúng", 0.667, IF(K8="✅ Đúng", 0.333, 0))) | O8: =IF(ISBLANK(F8), "💡 Nhập đáp án vào Lần thử 1", IF(OR(G8="✅ Đúng", I8="✅ Đúng", K8="✅ Đúng"), "✨ Xuất sắc! Bạn đã làm đúng.", IF(NOT(ISBLANK(J8)), "💡 Gợi ý Tầng 3 (Chốt phương pháp): " & "Đặt nhân tử chung ra ngoài dấu ngoặc và viết lại phần còn lại bên trong.", IF(NOT(ISBLANK(H8)), "💡 Gợi ý Tầng 2 (Manh mối cấu trúc & Loại trừ): " & "Quan sát các hệ số của từng số hạng để tìm nhân tử chung lớn nhất.", "💡 Gợi ý Tầng 1 (Định hướng bối cảnh): " & "Bài toán yêu cầu tìm biểu thức đại số tương đương bằng cách nhóm thừa số chung.")))) | P8: =IF(OR(G8="✅ Đúng", I8="✅ Đúng", K8="✅ Đúng"), "Factoring Out Common Factor: 29x^2 + 29 = 29(x^2 + 1).", "🔒 Trả lời đúng để mở khóa Strategic Tip!")
A9: Q5 | B9: Solving Linear Equations | C9: Given the equation: 2(x - 3) = 2(90). | D9: Calculator Allowed. What is the value of x - 3? | E9: A. Lựa chọn A B. Lựa chọn B C. Lựa chọn C D. Lựa chọn D | G9: =IF(ISBLANK(F9), "⏳ Chờ đáp án", IF(UPPER(TRIM(F9))="C", "✅ Đúng", "❌ Sai")) | I9: =IF(ISBLANK(H9), "", IF(UPPER(TRIM(H9))="C", "✅ Đúng", "❌ Sai")) | K9: =IF(ISBLANK(J9), "", IF(UPPER(TRIM(J9))="C", "✅ Đúng", "❌ Sai")) | L9: =COUNTIF(G9, "❌ Sai") + COUNTIF(I9, "❌ Sai") + COUNTIF(K9, "❌ Sai") | M9: =IF(ISBLANK(F9), "⏳ Chờ làm", IF(G9="✅ Đúng", "✅ Đúng ngay L1", IF(I9="✅ Đúng", "✅ Đúng ở L2", IF(K9="✅ Đúng", "✅ Đúng ở L3", "❌ Chưa đúng sau 3 lần")))) | N9: =IF(G9="✅ Đúng", 1, IF(I9="✅ Đúng", 0.667, IF(K9="✅ Đúng", 0.333, 0))) | O9: =IF(ISBLANK(F9), "💡 Nhập đáp án vào Lần thử 1", IF(OR(G9="✅ Đúng", I9="✅ Đúng", K9="✅ Đúng"), "✨ Xuất sắc! Bạn đã làm đúng.", IF(NOT(ISBLANK(J9)), "💡 Gợi ý Tầng 3 (Chốt phương pháp): " & "Chia cả hai vế cho hệ số của ẩn số để tìm giá trị cần tìm.", IF(NOT(ISBLANK(H9)), "💡 Gợi ý Tầng 2 (Manh mối cấu trúc & Loại trừ): " & "Sử dụng các phép biến đổi tương đương để cô lập biến số về một vế.", "💡 Gợi ý Tầng 1 (Định hướng bối cảnh): " & "Đây là phương trình tuyến tính một ẩn đơn giản.")))) | P9: =IF(OR(G9="✅ Đúng", I9="✅ Đúng", K9="✅ Đúng"), "Divide both sides by 2 directly: x - 3 = 90.", "🔒 Trả lời đúng để mở khóa Strategic Tip!")
A10: Q6 | B10: Rates & Unit Conversion | C10: A commercial water pump drains water from a reservoir at a constant rate of 180 gallons per minute. | D10: Calculator Allowed. At this rate, how many hours will it take to drain 32,400 gallons of water? | E10: A. Lựa chọn A B. Lựa chọn B C. Lựa chọn C D. Lựa chọn D | G10: =IF(ISBLANK(F10), "⏳ Chờ đáp án", IF(UPPER(TRIM(F10))="B", "✅ Đúng", "❌ Sai")) | I10: =IF(ISBLANK(H10), "", IF(UPPER(TRIM(H10))="B", "✅ Đúng", "❌ Sai")) | K10: =IF(ISBLANK(J10), "", IF(UPPER(TRIM(J10))="B", "✅ Đúng", "❌ Sai")) | L10: =COUNTIF(G10, "❌ Sai") + COUNTIF(I10, "❌ Sai") + COUNTIF(K10, "❌ Sai") | M10: =IF(ISBLANK(F10), "⏳ Chờ làm", IF(G10="✅ Đúng", "✅ Đúng ngay L1", IF(I10="✅ Đúng", "✅ Đúng ở L2", IF(K10="✅ Đúng", "✅ Đúng ở L3", "❌ Chưa đúng sau 3 lần")))) | N10: =IF(G10="✅ Đúng", 1, IF(I10="✅ Đúng", 0.667, IF(K10="✅ Đúng", 0.333, 0))) | O10: =IF(ISBLANK(F10), "💡 Nhập đáp án vào Lần thử 1", IF(OR(G10="✅ Đúng", I10="✅ Đúng", K10="✅ Đúng"), "✨ Xuất sắc! Bạn đã làm đúng.", IF(NOT(ISBLANK(J10)), "💡 Gợi ý Tầng 3 (Chốt phương pháp): " & "Triệt tiêu các đơn vị trung gian để thu được đơn vị kết quả mong muốn.", IF(NOT(ISBLANK(H10)), "💡 Gợi ý Tầng 2 (Manh mối cấu trúc & Loại trừ): " & "Thiết lập tỉ lệ chuyển đổi đơn vị theo phương pháp dây chuyền.", "💡 Gợi ý Tầng 1 (Định hướng bối cảnh): " & "Bài toán đổi đơn vị đo lường hoặc tính tốc độ trung bình.")))) | P10: =IF(OR(G10="✅ Đúng", I10="✅ Đúng", K10="✅ Đúng"), "Time (hours) = Total Gallons / (Rate per min * 60 min/hr) = 32,400 / (180 * 60) = 3.", "🔒 Trả lời đúng để mở khóa Strategic Tip!")
A11: Q7 | B11: Linear Equations in Two Variables | C11: The equation 4.57x + 6.08y = 902.07 represents a situation where x is the number of smaller bottles sold and y is the number of larger bottles sold. | D11: Calculator Allowed. According to the equation, what is the price, in dollars, of each smaller bottle? | E11: Student-Produced Response (Grid-in) | G11: =IF(ISBLANK(F11), "⏳ Chờ đáp án", IF(UPPER(TRIM(F11))="4.57", "✅ Đúng", "❌ Sai")) | I11: =IF(ISBLANK(H11), "", IF(UPPER(TRIM(H11))="4.57", "✅ Đúng", "❌ Sai")) | K11: =IF(ISBLANK(J11), "", IF(UPPER(TRIM(J11))="4.57", "✅ Đúng", "❌ Sai")) | L11: =COUNTIF(G11, "❌ Sai") + COUNTIF(I11, "❌ Sai") + COUNTIF(K11, "❌ Sai") | M11: =IF(ISBLANK(F11), "⏳ Chờ làm", IF(G11="✅ Đúng", "✅ Đúng ngay L1", IF(I11="✅ Đúng", "✅ Đúng ở L2", IF(K11="✅ Đúng", "✅ Đúng ở L3", "❌ Chưa đúng sau 3 lần")))) | N11: =IF(G11="✅ Đúng", 1, IF(I11="✅ Đúng", 0.667, IF(K11="✅ Đúng", 0.333, 0))) | O11: =IF(ISBLANK(F11), "💡 Nhập đáp án vào Lần thử 1", IF(OR(G11="✅ Đúng", I11="✅ Đúng", K11="✅ Đúng"), "✨ Xuất sắc! Bạn đã làm đúng.", IF(NOT(ISBLANK(J11)), "💡 Gợi ý Tầng 3 (Chốt phương pháp): " & "Lập phương trình ax + by = C và biến đổi đại số để tìm đại lượng yêu cầu.", IF(NOT(ISBLANK(H11)), "💡 Gợi ý Tầng 2 (Manh mối cấu trúc & Loại trừ): " & "Xác định đơn giá cố định cho mỗi đại lượng và tổng chi phí toàn bộ.", "💡 Gợi ý Tầng 1 (Định hướng bối cảnh): " & "Bài toán thiết lập phương trình tuyến tính hai ẩn dựa trên dữ kiện thực tế.")))) | P11: =IF(OR(G11="✅ Đúng", I11="✅ Đúng", K11="✅ Đúng"), "In Total Cost = a*x + b*y, the coefficient 'a' represents the price per unit x.", "🔒 Trả lời đúng để mở khóa Strategic Tip!")
A12: Q8 | B12: Similar Triangles & Proportions | C12: Triangle ABC is similar to triangle XYZ, where A, B, and C correspond to X, Y, and Z, respectively. In triangle ABC, AB = 180 and BC = 900. In triangle XYZ, YZ = 80. | D12: Calculator Allowed. What is the length of XY? | E12: A. Lựa chọn A B. Lựa chọn B C. Lựa chọn C D. Lựa chọn D | G12: =IF(ISBLANK(F12), "⏳ Chờ đáp án", IF(UPPER(TRIM(F12))="D", "✅ Đúng", "❌ Sai")) | I12: =IF(ISBLANK(H12), "", IF(UPPER(TRIM(H12))="D", "✅ Đúng", "❌ Sai")) | K12: =IF(ISBLANK(J12), "", IF(UPPER(TRIM(J12))="D", "✅ Đúng", "❌ Sai")) | L12: =COUNTIF(G12, "❌ Sai") + COUNTIF(I12, "❌ Sai") + COUNTIF(K12, "❌ Sai") | M12: =IF(ISBLANK(F12), "⏳ Chờ làm", IF(G12="✅ Đúng", "✅ Đúng ngay L1", IF(I12="✅ Đúng", "✅ Đúng ở L2", IF(K12="✅ Đúng", "✅ Đúng ở L3", "❌ Chưa đúng sau 3 lần")))) | N12: =IF(G12="✅ Đúng", 1, IF(I12="✅ Đúng", 0.667, IF(K12="✅ Đúng", 0.333, 0))) | O12: =IF(ISBLANK(F12), "💡 Nhập đáp án vào Lần thử 1", IF(OR(G12="✅ Đúng", I12="✅ Đúng", K12="✅ Đúng"), "✨ Xuất sắc! Bạn đã làm đúng.", IF(NOT(ISBLANK(J12)), "💡 Gợi ý Tầng 3 (Chốt phương pháp): " & "Thay các độ dài đã biết vào tỉ lệ thức và giải phương trình tìm độ dài cạnh còn lại.", IF(NOT(ISBLANK(H12)), "💡 Gợi ý Tầng 2 (Manh mối cấu trúc & Loại trừ): " & "Lập tỉ lệ giữa các cặp cạnh tương ứng của hai tam giác.", "💡 Gợi ý Tầng 1 (Định hướng bối cảnh): " & "Áp dụng tính chất của hai tam giác đồng dạng.")))) | P12: =IF(OR(G12="✅ Đúng", I12="✅ Đúng", K12="✅ Đúng"), "Similar Triangles Ratio: AB / XY = BC / YZ => 180 / XY = 900 / 80 => XY = 16.", "🔒 Trả lời đúng để mở khóa Strategic Tip!")
A13: Q9 | B13: Absolute Value Equations | C13: Given the equation: |x - 43| = 0. | D13: Calculator Allowed. Which value is a solution to the given equation? | E13: A. Lựa chọn A B. Lựa chọn B C. Lựa chọn C D. Lựa chọn D | G13: =IF(ISBLANK(F13), "⏳ Chờ đáp án", IF(UPPER(TRIM(F13))="D", "✅ Đúng", "❌ Sai")) | I13: =IF(ISBLANK(H13), "", IF(UPPER(TRIM(H13))="D", "✅ Đúng", "❌ Sai")) | K13: =IF(ISBLANK(J13), "", IF(UPPER(TRIM(J13))="D", "✅ Đúng", "❌ Sai")) | L13: =COUNTIF(G13, "❌ Sai") + COUNTIF(I13, "❌ Sai") + COUNTIF(K13, "❌ Sai") | M13: =IF(ISBLANK(F13), "⏳ Chờ làm", IF(G13="✅ Đúng", "✅ Đúng ngay L1", IF(I13="✅ Đúng", "✅ Đúng ở L2", IF(K13="✅ Đúng", "✅ Đúng ở L3", "❌ Chưa đúng sau 3 lần")))) | N13: =IF(G13="✅ Đúng", 1, IF(I13="✅ Đúng", 0.667, IF(K13="✅ Đúng", 0.333, 0))) | O13: =IF(ISBLANK(F13), "💡 Nhập đáp án vào Lần thử 1", IF(OR(G13="✅ Đúng", I13="✅ Đúng", K13="✅ Đúng"), "✨ Xuất sắc! Bạn đã làm đúng.", IF(NOT(ISBLANK(J13)), "💡 Gợi ý Tầng 3 (Chốt phương pháp): " & "Giải từng phương trình tuyến tính để tìm tập nghiệm.", IF(NOT(ISBLANK(H13)), "💡 Gợi ý Tầng 2 (Manh mối cấu trúc & Loại trừ): " & "Chia thành hai trường hợp: f(x) = c hoặc f(x) = -c.", "💡 Gợi ý Tầng 1 (Định hướng bối cảnh): " & "Giải phương trình chứa dấu giá trị tuyệt đối |f(x)| = c.")))) | P13: =IF(OR(G13="✅ Đúng", I13="✅ Đúng", K13="✅ Đúng"), "|A| = 0 implies A = 0 => x = 43.", "🔒 Trả lời đúng để mở khóa Strategic Tip!")
A14: Q10 | B14: Finding Line Equation from Points | C14: In the xy-plane, line k passes through the points (0, -8) and (1, -5). | D14: Calculator Allowed. Which equation defines line k? | E14: A. Lựa chọn A B. Lựa chọn B C. Lựa chọn C D. Lựa chọn D | G14: =IF(ISBLANK(F14), "⏳ Chờ đáp án", IF(UPPER(TRIM(F14))="C", "✅ Đúng", "❌ Sai")) | I14: =IF(ISBLANK(H14), "", IF(UPPER(TRIM(H14))="C", "✅ Đúng", "❌ Sai")) | K14: =IF(ISBLANK(J14), "", IF(UPPER(TRIM(J14))="C", "✅ Đúng", "❌ Sai")) | L14: =COUNTIF(G14, "❌ Sai") + COUNTIF(I14, "❌ Sai") + COUNTIF(K14, "❌ Sai") | M14: =IF(ISBLANK(F14), "⏳ Chờ làm", IF(G14="✅ Đúng", "✅ Đúng ngay L1", IF(I14="✅ Đúng", "✅ Đúng ở L2", IF(K14="✅ Đúng", "✅ Đúng ở L3", "❌ Chưa đúng sau 3 lần")))) | N14: =IF(G14="✅ Đúng", 1, IF(I14="✅ Đúng", 0.667, IF(K14="✅ Đúng", 0.333, 0))) | O14: =IF(ISBLANK(F14), "💡 Nhập đáp án vào Lần thử 1", IF(OR(G14="✅ Đúng", I14="✅ Đúng", K14="✅ Đúng"), "✨ Xuất sắc! Bạn đã làm đúng.", IF(NOT(ISBLANK(J14)), "💡 Gợi ý Tầng 3 (Chốt phương pháp): " & "Thay tọa độ một điểm và m vào dạng y = mx + b để tìm tung độ gốc b.", IF(NOT(ISBLANK(H14)), "💡 Gợi ý Tầng 2 (Manh mối cấu trúc & Loại trừ): " & "Tính hệ số góc m bằng công thức (y2 - y1) / (x2 - x1).", "💡 Gợi ý Tầng 1 (Định hướng bối cảnh): " & "Bài toán tìm phương trình đường thẳng đi qua hai điểm cho trước.")))) | P14: =IF(OR(G14="✅ Đúng", I14="✅ Đúng", K14="✅ Đúng"), "Slope m = (y2 - y1)/(x2 - x1) = 3, y-intercept = -8 => y = 3x - 8.", "🔒 Trả lời đúng để mở khóa Strategic Tip!")
A15: Q11 | B15: Scatterplot Best-Fit Line Model | C15: A scatterplot shows data points with a positive slope passing near (0, 0.2) and (4, 9.2). | D15: Calculator Allowed. Which equation is the most appropriate linear model for the data? | E15: A. Lựa chọn A B. Lựa chọn B C. Lựa chọn C D. Lựa chọn D | G15: =IF(ISBLANK(F15), "⏳ Chờ đáp án", IF(UPPER(TRIM(F15))="A", "✅ Đúng", "❌ Sai")) | I15: =IF(ISBLANK(H15), "", IF(UPPER(TRIM(H15))="A", "✅ Đúng", "❌ Sai")) | K15: =IF(ISBLANK(J15), "", IF(UPPER(TRIM(J15))="A", "✅ Đúng", "❌ Sai")) | L15: =COUNTIF(G15, "❌ Sai") + COUNTIF(I15, "❌ Sai") + COUNTIF(K15, "❌ Sai") | M15: =IF(ISBLANK(F15), "⏳ Chờ làm", IF(G15="✅ Đúng", "✅ Đúng ngay L1", IF(I15="✅ Đúng", "✅ Đúng ở L2", IF(K15="✅ Đúng", "✅ Đúng ở L3", "❌ Chưa đúng sau 3 lần")))) | N15: =IF(G15="✅ Đúng", 1, IF(I15="✅ Đúng", 0.667, IF(K15="✅ Đúng", 0.333, 0))) | O15: =IF(ISBLANK(F15), "💡 Nhập đáp án vào Lần thử 1", IF(OR(G15="✅ Đúng", I15="✅ Đúng", K15="✅ Đúng"), "✨ Xuất sắc! Bạn đã làm đúng.", IF(NOT(ISBLANK(J15)), "💡 Gợi ý Tầng 3 (Chốt phương pháp): " & "Đối chiếu hệ số góc và tung độ gốc ước lượng với các phương án.", IF(NOT(ISBLANK(H15)), "💡 Gợi ý Tầng 2 (Manh mối cấu trúc & Loại trừ): " & "Xác định xu hướng tăng/giảm (hệ số góc dương hay âm) và tung độ gốc trên đồ thị.", "💡 Gợi ý Tầng 1 (Định hướng bối cảnh): " & "Phân tích đường tiệm cận/đường xu hướng (best-fit line) trên biểu đồ phân tán.")))) | P15: =IF(OR(G15="✅ Đúng", I15="✅ Đúng", K15="✅ Đúng"), "Linear Model: y = b + m*x where b ≈ 0.2 and m ≈ 2.25.", "🔒 Trả lời đúng để mở khóa Strategic Tip!")
A16: Q12 | B16: Rational Function Intercepts | C16: Given the function y = (21 - x) / (ax + b), where a and b are positive constants. | D16: Calculator Allowed. What is the x-intercept of the graph in the xy-plane? | E16: A. Lựa chọn A B. Lựa chọn B C. Lựa chọn C D. Lựa chọn D | G16: =IF(ISBLANK(F16), "⏳ Chờ đáp án", IF(UPPER(TRIM(F16))="A", "✅ Đúng", "❌ Sai")) | I16: =IF(ISBLANK(H16), "", IF(UPPER(TRIM(H16))="A", "✅ Đúng", "❌ Sai")) | K16: =IF(ISBLANK(J16), "", IF(UPPER(TRIM(J16))="A", "✅ Đúng", "❌ Sai")) | L16: =COUNTIF(G16, "❌ Sai") + COUNTIF(I16, "❌ Sai") + COUNTIF(K16, "❌ Sai") | M16: =IF(ISBLANK(F16), "⏳ Chờ làm", IF(G16="✅ Đúng", "✅ Đúng ngay L1", IF(I16="✅ Đúng", "✅ Đúng ở L2", IF(K16="✅ Đúng", "✅ Đúng ở L3", "❌ Chưa đúng sau 3 lần")))) | N16: =IF(G16="✅ Đúng", 1, IF(I16="✅ Đúng", 0.667, IF(K16="✅ Đúng", 0.333, 0))) | O16: =IF(ISBLANK(F16), "💡 Nhập đáp án vào Lần thử 1", IF(OR(G16="✅ Đúng", I16="✅ Đúng", K16="✅ Đúng"), "✨ Xuất sắc! Bạn đã làm đúng.", IF(NOT(ISBLANK(J16)), "💡 Gợi ý Tầng 3 (Chốt phương pháp): " & "Xác định tọa độ giao điểm tương ứng từ kết quả tính toán.", IF(NOT(ISBLANK(H16)), "💡 Gợi ý Tầng 2 (Manh mối cấu trúc & Loại trừ): " & "Để tìm y-intercept, cho x = 0; để tìm x-intercept, cho tử số bằng 0.", "💡 Gợi ý Tầng 1 (Định hướng bối cảnh): " & "Tìm giao điểm của đồ thị hàm phân thức với các trục tọa độ.")))) | P16: =IF(OR(G16="✅ Đúng", I16="✅ Đúng", K16="✅ Đúng"), "x-intercept occurs when y = 0 => Numerator 21 - x = 0 => x = 21.", "🔒 Trả lời đúng để mở khóa Strategic Tip!")
A17: Q13 | B17: Inequalities & Speed/Distance | C17: A model estimates that a glacier moves between 17 and 24 centimeters per day. | D17: Calculator Allowed. Which inequality represents possible values of x, where x is the total distance, in centimeters, the glacier moves in 2 days? | E17: A. Lựa chọn A B. Lựa chọn B C. Lựa chọn C D. Lựa chọn D | G17: =IF(ISBLANK(F17), "⏳ Chờ đáp án", IF(UPPER(TRIM(F17))="D", "✅ Đúng", "❌ Sai")) | I17: =IF(ISBLANK(H17), "", IF(UPPER(TRIM(H17))="D", "✅ Đúng", "❌ Sai")) | K17: =IF(ISBLANK(J17), "", IF(UPPER(TRIM(J17))="D", "✅ Đúng", "❌ Sai")) | L17: =COUNTIF(G17, "❌ Sai") + COUNTIF(I17, "❌ Sai") + COUNTIF(K17, "❌ Sai") | M17: =IF(ISBLANK(F17), "⏳ Chờ làm", IF(G17="✅ Đúng", "✅ Đúng ngay L1", IF(I17="✅ Đúng", "✅ Đúng ở L2", IF(K17="✅ Đúng", "✅ Đúng ở L3", "❌ Chưa đúng sau 3 lần")))) | N17: =IF(G17="✅ Đúng", 1, IF(I17="✅ Đúng", 0.667, IF(K17="✅ Đúng", 0.333, 0))) | O17: =IF(ISBLANK(F17), "💡 Nhập đáp án vào Lần thử 1", IF(OR(G17="✅ Đúng", I17="✅ Đúng", K17="✅ Đúng"), "✨ Xuất sắc! Bạn đã làm đúng.", IF(NOT(ISBLANK(J17)), "💡 Gợi ý Tầng 3 (Chốt phương pháp): " & "Đặt dấu bất đẳng thức (lớn hơn/nhỏ hơn) đúng theo yêu cầu giới hạn của đề bài.", IF(NOT(ISBLANK(H17)), "💡 Gợi ý Tầng 2 (Manh mối cấu trúc & Loại trừ): " & "Áp dụng công thức Quãng đường = Vận tốc x Thời gian.", "💡 Gợi ý Tầng 1 (Định hướng bối cảnh): " & "Thiết lập bất phương trình liên quan đến quãng đường, vận tốc và thời gian.")))) | P17: =IF(OR(G17="✅ Đúng", I17="✅ Đúng", K17="✅ Đúng"), "Range for 2 days = [Min rate * 2, Max rate * 2] = [(17)(2), (24)(2)].", "🔒 Trả lời đúng để mở khóa Strategic Tip!")
A18: Q14 | B18: Unit Conversion (Ancient Units) | C18: In an ancient Roman measurement system, a leuga was a unit of length equal to 7,500 pedes. | D18: Calculator Allowed. In this measurement system, how many pedes were equivalent to 4.6 leugas? | E18: Student-Produced Response (Grid-in) | G18: =IF(ISBLANK(F18), "⏳ Chờ đáp án", IF(UPPER(TRIM(F18))="34500", "✅ Đúng", "❌ Sai")) | I18: =IF(ISBLANK(H18), "", IF(UPPER(TRIM(H18))="34500", "✅ Đúng", "❌ Sai")) | K18: =IF(ISBLANK(J18), "", IF(UPPER(TRIM(J18))="34500", "✅ Đúng", "❌ Sai")) | L18: =COUNTIF(G18, "❌ Sai") + COUNTIF(I18, "❌ Sai") + COUNTIF(K18, "❌ Sai") | M18: =IF(ISBLANK(F18), "⏳ Chờ làm", IF(G18="✅ Đúng", "✅ Đúng ngay L1", IF(I18="✅ Đúng", "✅ Đúng ở L2", IF(K18="✅ Đúng", "✅ Đúng ở L3", "❌ Chưa đúng sau 3 lần")))) | N18: =IF(G18="✅ Đúng", 1, IF(I18="✅ Đúng", 0.667, IF(K18="✅ Đúng", 0.333, 0))) | O18: =IF(ISBLANK(F18), "💡 Nhập đáp án vào Lần thử 1", IF(OR(G18="✅ Đúng", I18="✅ Đúng", K18="✅ Đúng"), "✨ Xuất sắc! Bạn đã làm đúng.", IF(NOT(ISBLANK(J18)), "💡 Gợi ý Tầng 3 (Chốt phương pháp): " & "Nhân/chia chuỗi tỉ lệ để đổi sang đơn vị mục tiêu.", IF(NOT(ISBLANK(H18)), "💡 Gợi ý Tầng 2 (Manh mối cấu trúc & Loại trừ): " & "Sử dụng tỉ lệ chuyển đổi được cung cấp trong đề bài.", "💡 Gợi ý Tầng 1 (Định hướng bối cảnh): " & "Bài toán chuyển đổi đơn vị đo lường cổ/đặc thù.")))) | P18: =IF(OR(G18="✅ Đúng", I18="✅ Đúng", K18="✅ Đúng"), "Unit Conversion: Pedes = 4.6 * 7,500 = 34,500.", "🔒 Trả lời đúng để mở khóa Strategic Tip!")
A19: Q15 | B19: Geometry (Area & Factoring) | C19: A rectangle has a width of n yards and a length of (n + 7) yards. The area of the rectangle is 198 square yards. | D19: Calculator Allowed. What is the value of n? | E19: Student-Produced Response (Grid-in) | G19: =IF(ISBLANK(F19), "⏳ Chờ đáp án", IF(UPPER(TRIM(F19))="11", "✅ Đúng", "❌ Sai")) | I19: =IF(ISBLANK(H19), "", IF(UPPER(TRIM(H19))="11", "✅ Đúng", "❌ Sai")) | K19: =IF(ISBLANK(J19), "", IF(UPPER(TRIM(J19))="11", "✅ Đúng", "❌ Sai")) | L19: =COUNTIF(G19, "❌ Sai") + COUNTIF(I19, "❌ Sai") + COUNTIF(K19, "❌ Sai") | M19: =IF(ISBLANK(F19), "⏳ Chờ làm", IF(G19="✅ Đúng", "✅ Đúng ngay L1", IF(I19="✅ Đúng", "✅ Đúng ở L2", IF(K19="✅ Đúng", "✅ Đúng ở L3", "❌ Chưa đúng sau 3 lần")))) | N19: =IF(G19="✅ Đúng", 1, IF(I19="✅ Đúng", 0.667, IF(K19="✅ Đúng", 0.333, 0))) | O19: =IF(ISBLANK(F19), "💡 Nhập đáp án vào Lần thử 1", IF(OR(G19="✅ Đúng", I19="✅ Đúng", K19="✅ Đúng"), "✨ Xuất sắc! Bạn đã làm đúng.", IF(NOT(ISBLANK(J19)), "💡 Gợi ý Tầng 3 (Chốt phương pháp): " & "Giải phương trình đại số để tìm độ dài kích thước chưa biết.", IF(NOT(ISBLANK(H19)), "💡 Gợi ý Tầng 2 (Manh mối cấu trúc & Loại trừ): " & "Viết biểu thức diện tích theo chiều dài và chiều rộng.", "💡 Gợi ý Tầng 1 (Định hướng bối cảnh): " & "Áp dụng công thức tính diện tích hình học và phân tích đa thức thành nhân tử.")))) | P19: =IF(OR(G19="✅ Đúng", I19="✅ Đúng", K19="✅ Đúng"), "Area = n(n + 7) = 198 => n = 11 (since 11 * 18 = 198).", "🔒 Trả lời đúng để mở khóa Strategic Tip!")
A20: Q16 | B20: Rearranging Formulas (Kinetic Energy) | C20: For an object with a mass of 55 kg, the given equation 55 = 2K / (v^2) relates kinetic energy K to speed v. | D20: Calculator Allowed. Which equation correctly expresses speed v in terms of K? | E20: A. Lựa chọn A B. Lựa chọn B C. Lựa chọn C D. Lựa chọn D | G20: =IF(ISBLANK(F20), "⏳ Chờ đáp án", IF(UPPER(TRIM(F20))="D", "✅ Đúng", "❌ Sai")) | I20: =IF(ISBLANK(H20), "", IF(UPPER(TRIM(H20))="D", "✅ Đúng", "❌ Sai")) | K20: =IF(ISBLANK(J20), "", IF(UPPER(TRIM(J20))="D", "✅ Đúng", "❌ Sai")) | L20: =COUNTIF(G20, "❌ Sai") + COUNTIF(I20, "❌ Sai") + COUNTIF(K20, "❌ Sai") | M20: =IF(ISBLANK(F20), "⏳ Chờ làm", IF(G20="✅ Đúng", "✅ Đúng ngay L1", IF(I20="✅ Đúng", "✅ Đúng ở L2", IF(K20="✅ Đúng", "✅ Đúng ở L3", "❌ Chưa đúng sau 3 lần")))) | N20: =IF(G20="✅ Đúng", 1, IF(I20="✅ Đúng", 0.667, IF(K20="✅ Đúng", 0.333, 0))) | O20: =IF(ISBLANK(F20), "💡 Nhập đáp án vào Lần thử 1", IF(OR(G20="✅ Đúng", I20="✅ Đúng", K20="✅ Đúng"), "✨ Xuất sắc! Bạn đã làm đúng.", IF(NOT(ISBLANK(J20)), "💡 Gợi ý Tầng 3 (Chốt phương pháp): " & "Rút biến số mục tiêu ra một vế hoàn chỉnh.", IF(NOT(ISBLANK(H20)), "💡 Gợi ý Tầng 2 (Manh mối cấu trúc & Loại trừ): " & "Thực hiện các phép tính ngược (nhân/chia, lấy căn/bình phương) lên cả hai vế.", "💡 Gợi ý Tầng 1 (Định hướng bối cảnh): " & "Biến đổi công thức vật lý/đại số để cô lập một biến số.")))) | P20: =IF(OR(G20="✅ Đúng", I20="✅ Đúng", K20="✅ Đúng"), "Isolate v: v^2 = 2K / 55 => v = sqrt(2K / 55).", "🔒 Trả lời đúng để mở khóa Strategic Tip!")
A21: Q17 | B21: Exponential Growth Model | C21: A company's solar cell production grew by approximately 22% each year for 5 years following 2013, starting at 7,138 peak kilowatts in 2013. | D21: Calculator Allowed. Which function best models the solar cell production C(n) n years after 2013? | E21: A. Lựa chọn A B. Lựa chọn B C. Lựa chọn C D. Lựa chọn D | G21: =IF(ISBLANK(F21), "⏳ Chờ đáp án", IF(UPPER(TRIM(F21))="B", "✅ Đúng", "❌ Sai")) | I21: =IF(ISBLANK(H21), "", IF(UPPER(TRIM(H21))="B", "✅ Đúng", "❌ Sai")) | K21: =IF(ISBLANK(J21), "", IF(UPPER(TRIM(J21))="B", "✅ Đúng", "❌ Sai")) | L21: =COUNTIF(G21, "❌ Sai") + COUNTIF(I21, "❌ Sai") + COUNTIF(K21, "❌ Sai") | M21: =IF(ISBLANK(F21), "⏳ Chờ làm", IF(G21="✅ Đúng", "✅ Đúng ngay L1", IF(I21="✅ Đúng", "✅ Đúng ở L2", IF(K21="✅ Đúng", "✅ Đúng ở L3", "❌ Chưa đúng sau 3 lần")))) | N21: =IF(G21="✅ Đúng", 1, IF(I21="✅ Đúng", 0.667, IF(K21="✅ Đúng", 0.333, 0))) | O21: =IF(ISBLANK(F21), "💡 Nhập đáp án vào Lần thử 1", IF(OR(G21="✅ Đúng", I21="✅ Đúng", K21="✅ Đúng"), "✨ Xuất sắc! Bạn đã làm đúng.", IF(NOT(ISBLANK(J21)), "💡 Gợi ý Tầng 3 (Chốt phương pháp): " & "Thay giá trị biến thời gian x vào mô hình để tính kết quả.", IF(NOT(ISBLANK(H21)), "💡 Gợi ý Tầng 2 (Manh mối cấu trúc & Loại trừ): " & "Xác định giá trị ban đầu 'a' và hệ số tăng trưởng 'b' từ đề bài.", "💡 Gợi ý Tầng 1 (Định hướng bối cảnh): " & "Áp dụng mô hình hàm số mũ y = a(b)^x đại diện cho sự tăng trưởng.")))) | P21: =IF(OR(G21="✅ Đúng", I21="✅ Đúng", K21="✅ Đúng"), "Exponential Growth Model: P(t) = P0 * (1 + r)^t = 7,138 * (1.22)^n.", "🔒 Trả lời đúng để mở khóa Strategic Tip!")
A22: Q18 | B22: Trigonometry (Special Right Triangle 45-45-90) | C22: In right triangle ABC with angle B = 90 deg and angle C = 45 deg, hypotenuse AC has length x = 19. | D22: Calculator Allowed. What is the value of sin A? | E22: A. Lựa chọn A B. Lựa chọn B C. Lựa chọn C D. Lựa chọn D | G22: =IF(ISBLANK(F22), "⏳ Chờ đáp án", IF(UPPER(TRIM(F22))="B", "✅ Đúng", "❌ Sai")) | I22: =IF(ISBLANK(H22), "", IF(UPPER(TRIM(H22))="B", "✅ Đúng", "❌ Sai")) | K22: =IF(ISBLANK(J22), "", IF(UPPER(TRIM(J22))="B", "✅ Đúng", "❌ Sai")) | L22: =COUNTIF(G22, "❌ Sai") + COUNTIF(I22, "❌ Sai") + COUNTIF(K22, "❌ Sai") | M22: =IF(ISBLANK(F22), "⏳ Chờ làm", IF(G22="✅ Đúng", "✅ Đúng ngay L1", IF(I22="✅ Đúng", "✅ Đúng ở L2", IF(K22="✅ Đúng", "✅ Đúng ở L3", "❌ Chưa đúng sau 3 lần")))) | N22: =IF(G22="✅ Đúng", 1, IF(I22="✅ Đúng", 0.667, IF(K22="✅ Đúng", 0.333, 0))) | O22: =IF(ISBLANK(F22), "💡 Nhập đáp án vào Lần thử 1", IF(OR(G22="✅ Đúng", I22="✅ Đúng", K22="✅ Đúng"), "✨ Xuất sắc! Bạn đã làm đúng.", IF(NOT(ISBLANK(J22)), "💡 Gợi ý Tầng 3 (Chốt phương pháp): " & "Sử dụng tỉ lệ cạnh để tính độ dài cạnh cần tìm.", IF(NOT(ISBLANK(H22)), "💡 Gợi ý Tầng 2 (Manh mối cấu trúc & Loại trừ): " & "Nhớ tỉ lệ cạnh trong tam giác vuông cân là 1 : 1 : sqrt(2).", "💡 Gợi ý Tầng 1 (Định hướng bối cảnh): " & "Áp dụng tỉ số lượng giác trong tam giác vuông đặc biệt 45-45-90.")))) | P22: =IF(OR(G22="✅ Đúng", I22="✅ Đúng", K22="✅ Đúng"), "Special Right Triangle 45-45-90: sin(45 deg) = 1/sqrt(2).", "🔒 Trả lời đúng để mở khóa Strategic Tip!")
A23: Q19 | B23: 3D Geometry (Right Square Prism Volume) | C23: A right square prism has a height of 15 units and a volume of 1,815 cubic units. | D23: Calculator Allowed. What is the length, in units, of an edge of the base? | E23: Student-Produced Response (Grid-in) | G23: =IF(ISBLANK(F23), "⏳ Chờ đáp án", IF(UPPER(TRIM(F23))="11", "✅ Đúng", "❌ Sai")) | I23: =IF(ISBLANK(H23), "", IF(UPPER(TRIM(H23))="11", "✅ Đúng", "❌ Sai")) | K23: =IF(ISBLANK(J23), "", IF(UPPER(TRIM(J23))="11", "✅ Đúng", "❌ Sai")) | L23: =COUNTIF(G23, "❌ Sai") + COUNTIF(I23, "❌ Sai") + COUNTIF(K23, "❌ Sai") | M23: =IF(ISBLANK(F23), "⏳ Chờ làm", IF(G23="✅ Đúng", "✅ Đúng ngay L1", IF(I23="✅ Đúng", "✅ Đúng ở L2", IF(K23="✅ Đúng", "✅ Đúng ở L3", "❌ Chưa đúng sau 3 lần")))) | N23: =IF(G23="✅ Đúng", 1, IF(I23="✅ Đúng", 0.667, IF(K23="✅ Đúng", 0.333, 0))) | O23: =IF(ISBLANK(F23), "💡 Nhập đáp án vào Lần thử 1", IF(OR(G23="✅ Đúng", I23="✅ Đúng", K23="✅ Đúng"), "✨ Xuất sắc! Bạn đã làm đúng.", IF(NOT(ISBLANK(J23)), "💡 Gợi ý Tầng 3 (Chốt phương pháp): " & "Thay độ dài cạnh đáy và chiều cao vào công thức để tính thể tích.", IF(NOT(ISBLANK(H23)), "💡 Gợi ý Tầng 2 (Manh mối cấu trúc & Loại trừ): " & "Áp dụng công thức Thể tích = Diện tích đáy x Chiều cao.", "💡 Gợi ý Tầng 1 (Định hướng bối cảnh): " & "Tính thể tích khối lăng trụ đứng đáy là hình vuông.")))) | P23: =IF(OR(G23="✅ Đúng", I23="✅ Đúng", K23="✅ Đúng"), "Volume of Square Prism = s^2 * h => s^2 = 1815 / 15 = 121 => s = 11.", "🔒 Trả lời đúng để mở khóa Strategic Tip!")
A24: Q20 | B24: Systems of Non-linear Equations | C24: System of equations: y = x - 1 and y = 19(x - 1)^2 - 20. | D24: Calculator Allowed. What is one possible value of x - 1? | E24: A. Lựa chọn A B. Lựa chọn B C. Lựa chọn C D. Lựa chọn D | G24: =IF(ISBLANK(F24), "⏳ Chờ đáp án", IF(UPPER(TRIM(F24))="C", "✅ Đúng", "❌ Sai")) | I24: =IF(ISBLANK(H24), "", IF(UPPER(TRIM(H24))="C", "✅ Đúng", "❌ Sai")) | K24: =IF(ISBLANK(J24), "", IF(UPPER(TRIM(J24))="C", "✅ Đúng", "❌ Sai")) | L24: =COUNTIF(G24, "❌ Sai") + COUNTIF(I24, "❌ Sai") + COUNTIF(K24, "❌ Sai") | M24: =IF(ISBLANK(F24), "⏳ Chờ làm", IF(G24="✅ Đúng", "✅ Đúng ngay L1", IF(I24="✅ Đúng", "✅ Đúng ở L2", IF(K24="✅ Đúng", "✅ Đúng ở L3", "❌ Chưa đúng sau 3 lần")))) | N24: =IF(G24="✅ Đúng", 1, IF(I24="✅ Đúng", 0.667, IF(K24="✅ Đúng", 0.333, 0))) | O24: =IF(ISBLANK(F24), "💡 Nhập đáp án vào Lần thử 1", IF(OR(G24="✅ Đúng", I24="✅ Đúng", K24="✅ Đúng"), "✨ Xuất sắc! Bạn đã làm đúng.", IF(NOT(ISBLANK(J24)), "💡 Gợi ý Tầng 3 (Chốt phương pháp): " & "Giải phương trình bậc hai thu được để tìm số nghiệm.", IF(NOT(ISBLANK(H24)), "💡 Gợi ý Tầng 2 (Manh mối cấu trúc & Loại trừ): " & "Rút một biến từ phương trình tuyến tính và thế vào phương trình phi tuyến.", "💡 Gợi ý Tầng 1 (Định hướng bối cảnh): " & "Giải hệ phương trình gồm một phương trình tuyến tính và một phương trình phi tuyến.")))) | P24: =IF(OR(G24="✅ Đúng", I24="✅ Đúng", K24="✅ Đúng"), "Substitute u = x - 1 => 19u^2 - u - 20 = 0 => u = 1 or u = 20/19.", "🔒 Trả lời đúng để mở khóa Strategic Tip!")
A25: Q21 | B25: Systems of Linear Equations (No Solution) | C25: System of equations: 18x + 6y = 8y + 9 and ty = 1/5 + 9x. | D25: Calculator Allowed. In the given system, t is a constant. If the system has no solution, what is the value of t? | E25: Student-Produced Response (Grid-in) | G25: =IF(ISBLANK(F25), "⏳ Chờ đáp án", IF(UPPER(TRIM(F25))="1", "✅ Đúng", "❌ Sai")) | I25: =IF(ISBLANK(H25), "", IF(UPPER(TRIM(H25))="1", "✅ Đúng", "❌ Sai")) | K25: =IF(ISBLANK(J25), "", IF(UPPER(TRIM(J25))="1", "✅ Đúng", "❌ Sai")) | L25: =COUNTIF(G25, "❌ Sai") + COUNTIF(I25, "❌ Sai") + COUNTIF(K25, "❌ Sai") | M25: =IF(ISBLANK(F25), "⏳ Chờ làm", IF(G25="✅ Đúng", "✅ Đúng ngay L1", IF(I25="✅ Đúng", "✅ Đúng ở L2", IF(K25="✅ Đúng", "✅ Đúng ở L3", "❌ Chưa đúng sau 3 lần")))) | N25: =IF(G25="✅ Đúng", 1, IF(I25="✅ Đúng", 0.667, IF(K25="✅ Đúng", 0.333, 0))) | O25: =IF(ISBLANK(F25), "💡 Nhập đáp án vào Lần thử 1", IF(OR(G25="✅ Đúng", I25="✅ Đúng", K25="✅ Đúng"), "✨ Xuất sắc! Bạn đã làm đúng.", IF(NOT(ISBLANK(J25)), "💡 Gợi ý Tầng 3 (Chốt phương pháp): " & "Thiết lập tỉ lệ thức giữa các hệ số và giải tìm hằng số c.", IF(NOT(ISBLANK(H25)), "💡 Gợi ý Tầng 2 (Manh mối cấu trúc & Loại trừ): " & "Hệ vô nghiệm khi hai đường thẳng song song: tỉ số hệ số x và y bằng nhau nhưng khác tỉ số hằng số.", "💡 Gợi ý Tầng 1 (Định hướng bối cảnh): " & "Xác định điều kiện để hệ phương trình tuyến tính vô nghiệm.")))) | P25: =IF(OR(G25="✅ Đúng", I25="✅ Đúng", K25="✅ Đúng"), "Parallel Lines Condition: m1 = m2 => t = 1.", "🔒 Trả lời đúng để mở khóa Strategic Tip!")
A26: Q22 | B26: Circle Geometry (Radius from Intercepts) | C26: A circle in the xy-plane has center (24, 5) and y-intercepts (0, -27) and (0, 37). | D26: Calculator Allowed. What is the radius of this circle? | E26: A. Lựa chọn A B. Lựa chọn B C. Lựa chọn C D. Lựa chọn D | G26: =IF(ISBLANK(F26), "⏳ Chờ đáp án", IF(UPPER(TRIM(F26))="A", "✅ Đúng", "❌ Sai")) | I26: =IF(ISBLANK(H26), "", IF(UPPER(TRIM(H26))="A", "✅ Đúng", "❌ Sai")) | K26: =IF(ISBLANK(J26), "", IF(UPPER(TRIM(J26))="A", "✅ Đúng", "❌ Sai")) | L26: =COUNTIF(G26, "❌ Sai") + COUNTIF(I26, "❌ Sai") + COUNTIF(K26, "❌ Sai") | M26: =IF(ISBLANK(F26), "⏳ Chờ làm", IF(G26="✅ Đúng", "✅ Đúng ngay L1", IF(I26="✅ Đúng", "✅ Đúng ở L2", IF(K26="✅ Đúng", "✅ Đúng ở L3", "❌ Chưa đúng sau 3 lần")))) | N26: =IF(G26="✅ Đúng", 1, IF(I26="✅ Đúng", 0.667, IF(K26="✅ Đúng", 0.333, 0))) | O26: =IF(ISBLANK(F26), "💡 Nhập đáp án vào Lần thử 1", IF(OR(G26="✅ Đúng", I26="✅ Đúng", K26="✅ Đúng"), "✨ Xuất sắc! Bạn đã làm đúng.", IF(NOT(ISBLANK(J26)), "💡 Gợi ý Tầng 3 (Chốt phương pháp): " & "Lấy căn bậc hai của vế phải r^2 để tìm bán kính r.", IF(NOT(ISBLANK(H26)), "💡 Gợi ý Tầng 2 (Manh mối cấu trúc & Loại trừ): " & "Đưa phương trình đường tròn về dạng chuẩn (x - h)^2 + (y - k)^2 = r^2.", "💡 Gợi ý Tầng 1 (Định hướng bối cảnh): " & "Xác định bán kính đường tròn từ phương trình hoặc giao điểm với trục tọa độ.")))) | P26: =IF(OR(G26="✅ Đúng", I26="✅ Đúng", K26="✅ Đúng"), "Distance Formula: r = sqrt((x_center - 0)^2 + (y_center - y_int)^2) = sqrt(24^2 + 32^2) = 40.", "🔒 Trả lời đúng để mở khóa Strategic Tip!")

Sheet Math_Module2
A1: Digital SAT Practice Test - October 2026: Math Module 2
A2: Chiến thuật: Tự thử sức ở Lần 1 (Cột F) -> Nhận phản hồi tự động & Gợi ý định hướng logic mà không làm lộ đáp án.
A4: Q# | B4: Topic / Skill Focus | C4: Passage & Context | D4: Question Prompt / Calculator | E4: Options / Choices (No Answer) | F4: Lần thử 1 | G4: Kết quả L1 | H4: Lần thử 2 | I4: Kết quả L2 | J4: Lần thử 3 | K4: Kết quả L3 | L4: Tổng số cột Sai | M4: Trạng thái Hoàn thành | N4: Hiệu suất (%) | O4: Hint / Gợi ý Đa tầng (Không đáp án) | P4: Strategic Tip / Formula
A5: Q1 | B5: Circle Equations (Radius) | C5: A circle in the xy-plane has equation (x - 4)^2 + (y + 1)^2 = 49. | D5: Calculator Allowed. What is the radius of the circle? | E5: A. Lựa chọn A B. Lựa chọn B C. Lựa chọn C D. Lựa chọn D | G5: =IF(ISBLANK(F5), "⏳ Chờ đáp án", IF(UPPER(TRIM(F5))="A", "✅ Đúng", "❌ Sai")) | I5: =IF(ISBLANK(H5), "", IF(UPPER(TRIM(H5))="A", "✅ Đúng", "❌ Sai")) | K5: =IF(ISBLANK(J5), "", IF(UPPER(TRIM(J5))="A", "✅ Đúng", "❌ Sai")) | L5: =COUNTIF(G5, "❌ Sai") + COUNTIF(I5, "❌ Sai") + COUNTIF(K5, "❌ Sai") | M5: =IF(ISBLANK(F5), "⏳ Chờ làm", IF(G5="✅ Đúng", "✅ Đúng ngay L1", IF(I5="✅ Đúng", "✅ Đúng ở L2", IF(K5="✅ Đúng", "✅ Đúng ở L3", "❌ Chưa đúng sau 3 lần")))) | N5: =IF(G5="✅ Đúng", 1, IF(I5="✅ Đúng", 0.667, IF(K5="✅ Đúng", 0.333, 0))) | O5: =IF(ISBLANK(F5), "💡 Nhập đáp án vào Lần thử 1", IF(OR(G5="✅ Đúng", I5="✅ Đúng", K5="✅ Đúng"), "✨ Xuất sắc! Bạn đã làm đúng.", IF(NOT(ISBLANK(J5)), "💡 Gợi ý Tầng 3 (Chốt phương pháp): " & "Tính căn bậc hai của r^2 để tìm độ dài bán kính r.", IF(NOT(ISBLANK(H5)), "💡 Gợi ý Tầng 2 (Manh mối cấu trúc & Loại trừ): " & "Xác định giá trị r^2 ở vế phải của phương trình.", "💡 Gợi ý Tầng 1 (Định hướng bối cảnh): " & "So sánh phương trình đường tròn đã cho với dạng chuẩn (x - h)^2 + (y - k)^2 = r^2.")))) | P5: =IF(OR(G5="✅ Đúng", I5="✅ Đúng", K5="✅ Đúng"), "Circle Equation: (x - h)^2 + (y - k)^2 = r^2 => r = sqrt(49) = 7.", "🔒 Trả lời đúng để mở khóa Strategic Tip!")
A6: Q2 | B6: Linear Functions & Table Data | C6: A table shows area x (sq ft) and water f(x) (gallons): (2400, 4320), (3600, 6480), (4800, 8640). | D6: Calculator Allowed. Which equation defines f(x)? | E6: A. Lựa chọn A B. Lựa chọn B C. Lựa chọn C D. Lựa chọn D | G6: =IF(ISBLANK(F6), "⏳ Chờ đáp án", IF(UPPER(TRIM(F6))="B", "✅ Đúng", "❌ Sai")) | I6: =IF(ISBLANK(H6), "", IF(UPPER(TRIM(H6))="B", "✅ Đúng", "❌ Sai")) | K6: =IF(ISBLANK(J6), "", IF(UPPER(TRIM(J6))="B", "✅ Đúng", "❌ Sai")) | L6: =COUNTIF(G6, "❌ Sai") + COUNTIF(I6, "❌ Sai") + COUNTIF(K6, "❌ Sai") | M6: =IF(ISBLANK(F6), "⏳ Chờ làm", IF(G6="✅ Đúng", "✅ Đúng ngay L1", IF(I6="✅ Đúng", "✅ Đúng ở L2", IF(K6="✅ Đúng", "✅ Đúng ở L3", "❌ Chưa đúng sau 3 lần")))) | N6: =IF(G6="✅ Đúng", 1, IF(I6="✅ Đúng", 0.667, IF(K6="✅ Đúng", 0.333, 0))) | O6: =IF(ISBLANK(F6), "💡 Nhập đáp án vào Lần thử 1", IF(OR(G6="✅ Đúng", I6="✅ Đúng", K6="✅ Đúng"), "✨ Xuất sắc! Bạn đã làm đúng.", IF(NOT(ISBLANK(J6)), "💡 Gợi ý Tầng 3 (Chốt phương pháp): " & "Lập công thức hàm số dựa trên hệ số góc và tung độ gốc tìm được.", IF(NOT(ISBLANK(H6)), "💡 Gợi ý Tầng 2 (Manh mối cấu trúc & Loại trừ): " & "Tính tỉ số thay đổi Delta y / Delta x giữa các điểm dữ liệu.", "💡 Gợi ý Tầng 1 (Định hướng bối cảnh): " & "Phân tích bảng giá trị để xác định dạng hàm số (tuyến tính hay hàm mũ).")))) | P6: =IF(OR(G6="✅ Đúng", I6="✅ Đúng", K6="✅ Đúng"), "Direct Variation Ratio: k = y / x = 4320 / 2400 = 1.8.", "🔒 Trả lời đúng để mở khóa Strategic Tip!")
A7: Q3 | B7: Linear Equations (Infinitely Many Solutions) | C7: Given the equation: 15x + 435 = a(x + 29). | D7: Calculator Allowed. If the equation has infinitely many solutions, what is the value of a? | E7: Student-Produced Response (Grid-in) | G7: =IF(ISBLANK(F7), "⏳ Chờ đáp án", IF(UPPER(TRIM(F7))="15", "✅ Đúng", "❌ Sai")) | I7: =IF(ISBLANK(H7), "", IF(UPPER(TRIM(H7))="15", "✅ Đúng", "❌ Sai")) | K7: =IF(ISBLANK(J7), "", IF(UPPER(TRIM(J7))="15", "✅ Đúng", "❌ Sai")) | L7: =COUNTIF(G7, "❌ Sai") + COUNTIF(I7, "❌ Sai") + COUNTIF(K7, "❌ Sai") | M7: =IF(ISBLANK(F7), "⏳ Chờ làm", IF(G7="✅ Đúng", "✅ Đúng ngay L1", IF(I7="✅ Đúng", "✅ Đúng ở L2", IF(K7="✅ Đúng", "✅ Đúng ở L3", "❌ Chưa đúng sau 3 lần")))) | N7: =IF(G7="✅ Đúng", 1, IF(I7="✅ Đúng", 0.667, IF(K7="✅ Đúng", 0.333, 0))) | O7: =IF(ISBLANK(F7), "💡 Nhập đáp án vào Lần thử 1", IF(OR(G7="✅ Đúng", I7="✅ Đúng", K7="✅ Đúng"), "✨ Xuất sắc! Bạn đã làm đúng.", IF(NOT(ISBLANK(J7)), "💡 Gợi ý Tầng 3 (Chốt phương pháp): " & "Thiết lập tỉ lệ giữa các hệ số x, y và hằng số tự do để giải tìm ẩn số.", IF(NOT(ISBLANK(H7)), "💡 Gợi ý Tầng 2 (Manh mối cấu trúc & Loại trừ): " & "Hệ có vô số nghiệm khi hai phương trình trùng nhau hoàn toàn (mọi hệ số tương ứng tỉ lệ).", "💡 Gợi ý Tầng 1 (Định hướng bối cảnh): " & "Xác định điều kiện để hệ phương trình tuyến tính có vô số nghiệm.")))) | P7: =IF(OR(G7="✅ Đúng", I7="✅ Đúng", K7="✅ Đúng"), "Infinitely Many Solutions: Identical coefficients on both sides => a = 15.", "🔒 Trả lời đúng để mở khóa Strategic Tip!")
A8: Q4 | B8: Linear Modeling (Pricing Structure) | C8: A plumbing company charges 116 dollars for the first hour and 70 dollars for each additional hour, plus parts cost z dollars (x >= 1). | D8: Calculator Allowed. Which equation represents total cost y? | E8: A. Lựa chọn A B. Lựa chọn B C. Lựa chọn C D. Lựa chọn D | G8: =IF(ISBLANK(F8), "⏳ Chờ đáp án", IF(UPPER(TRIM(F8))="B", "✅ Đúng", "❌ Sai")) | I8: =IF(ISBLANK(H8), "", IF(UPPER(TRIM(H8))="B", "✅ Đúng", "❌ Sai")) | K8: =IF(ISBLANK(J8), "", IF(UPPER(TRIM(J8))="B", "✅ Đúng", "❌ Sai")) | L8: =COUNTIF(G8, "❌ Sai") + COUNTIF(I8, "❌ Sai") + COUNTIF(K8, "❌ Sai") | M8: =IF(ISBLANK(F8), "⏳ Chờ làm", IF(G8="✅ Đúng", "✅ Đúng ngay L1", IF(I8="✅ Đúng", "✅ Đúng ở L2", IF(K8="✅ Đúng", "✅ Đúng ở L3", "❌ Chưa đúng sau 3 lần")))) | N8: =IF(G8="✅ Đúng", 1, IF(I8="✅ Đúng", 0.667, IF(K8="✅ Đúng", 0.333, 0))) | O8: =IF(ISBLANK(F8), "💡 Nhập đáp án vào Lần thử 1", IF(OR(G8="✅ Đúng", I8="✅ Đúng", K8="✅ Đúng"), "✨ Xuất sắc! Bạn đã làm đúng.", IF(NOT(ISBLANK(J8)), "💡 Gợi ý Tầng 3 (Chốt phương pháp): " & "Thiết lập biểu thức đại số biểu diễn tổng chi phí.", IF(NOT(ISBLANK(H8)), "💡 Gợi ý Tầng 2 (Manh mối cấu trúc & Loại trừ): " & "Xác định chi phí cố định (b) và chi phí biến đổi theo đơn vị (m).", "💡 Gợi ý Tầng 1 (Định hướng bối cảnh): " & "Mô hình hóa chi phí bằng hàm tuyến tính y = mx + b.")))) | P8: =IF(OR(G8="✅ Đúng", I8="✅ Đúng", K8="✅ Đúng"), "Cost Model: y = First Hour + Additional Hours*(x - 1) + Parts = 116 + 70(x - 1) + z = 70x + z + 46.", "🔒 Trả lời đúng để mở khóa Strategic Tip!")
A9: Q5 | B9: Absolute Value Functions | C9: Function h(x) = |x - 8| - |6 - x| + a. Given h(-4) = 1. | D9: Calculator Allowed. What is the value of a? | E9: Student-Produced Response (Grid-in) | G9: =IF(ISBLANK(F9), "⏳ Chờ đáp án", IF(UPPER(TRIM(F9))="-1", "✅ Đúng", "❌ Sai")) | I9: =IF(ISBLANK(H9), "", IF(UPPER(TRIM(H9))="-1", "✅ Đúng", "❌ Sai")) | K9: =IF(ISBLANK(J9), "", IF(UPPER(TRIM(J9))="-1", "✅ Đúng", "❌ Sai")) | L9: =COUNTIF(G9, "❌ Sai") + COUNTIF(I9, "❌ Sai") + COUNTIF(K9, "❌ Sai") | M9: =IF(ISBLANK(F9), "⏳ Chờ làm", IF(G9="✅ Đúng", "✅ Đúng ngay L1", IF(I9="✅ Đúng", "✅ Đúng ở L2", IF(K9="✅ Đúng", "✅ Đúng ở L3", "❌ Chưa đúng sau 3 lần")))) | N9: =IF(G9="✅ Đúng", 1, IF(I9="✅ Đúng", 0.667, IF(K9="✅ Đúng", 0.333, 0))) | O9: =IF(ISBLANK(F9), "💡 Nhập đáp án vào Lần thử 1", IF(OR(G9="✅ Đúng", I9="✅ Đúng", K9="✅ Đúng"), "✨ Xuất sắc! Bạn đã làm đúng.", IF(NOT(ISBLANK(J9)), "💡 Gợi ý Tầng 3 (Chốt phương pháp): " & "Thay giá trị x đề bài yêu cầu vào biểu thức để tính giá trị hàm số.", IF(NOT(ISBLANK(H9)), "💡 Gợi ý Tầng 2 (Manh mối cấu trúc & Loại trừ): " & "Xác định tọa độ đỉnh cực trị (h, k) của hàm số.", "💡 Gợi ý Tầng 1 (Định hướng bối cảnh): " & "Phân tích đồ thị hoặc tập giá trị của hàm giá trị tuyệt đối dạng y = |x - h| + k.")))) | P9: =IF(OR(G9="✅ Đúng", I9="✅ Đúng", K9="✅ Đúng"), "Evaluate h(-4): 12 - 10 + a = 1 => 2 + a = 1 => a = -1.", "🔒 Trả lời đúng để mở khóa Strategic Tip!")
A10: Q6 | B10: Perpendicular Lines Slope | C10: Line h is defined by 2x + 3y - 30 = 0. Line j is perpendicular to line h in the xy-plane. | D10: Calculator Allowed. What is the slope of line j? | E10: A. Lựa chọn A B. Lựa chọn B C. Lựa chọn C D. Lựa chọn D | G10: =IF(ISBLANK(F10), "⏳ Chờ đáp án", IF(UPPER(TRIM(F10))="D", "✅ Đúng", "❌ Sai")) | I10: =IF(ISBLANK(H10), "", IF(UPPER(TRIM(H10))="D", "✅ Đúng", "❌ Sai")) | K10: =IF(ISBLANK(J10), "", IF(UPPER(TRIM(J10))="D", "✅ Đúng", "❌ Sai")) | L10: =COUNTIF(G10, "❌ Sai") + COUNTIF(I10, "❌ Sai") + COUNTIF(K10, "❌ Sai") | M10: =IF(ISBLANK(F10), "⏳ Chờ làm", IF(G10="✅ Đúng", "✅ Đúng ngay L1", IF(I10="✅ Đúng", "✅ Đúng ở L2", IF(K10="✅ Đúng", "✅ Đúng ở L3", "❌ Chưa đúng sau 3 lần")))) | N10: =IF(G10="✅ Đúng", 1, IF(I10="✅ Đúng", 0.667, IF(K10="✅ Đúng", 0.333, 0))) | O10: =IF(ISBLANK(F10), "💡 Nhập đáp án vào Lần thử 1", IF(OR(G10="✅ Đúng", I10="✅ Đúng", K10="✅ Đúng"), "✨ Xuất sắc! Bạn đã làm đúng.", IF(NOT(ISBLANK(J10)), "💡 Gợi ý Tầng 3 (Chốt phương pháp): " & "Lấy nghịch đảo và đổi dấu hệ số góc của đường thẳng ban đầu.", IF(NOT(ISBLANK(H10)), "💡 Gợi ý Tầng 2 (Manh mối cấu trúc & Loại trừ): " & "Hai đường thẳng vuông góc có tích hai hệ số góc bằng -1 (m1 * m2 = -1).", "💡 Gợi ý Tầng 1 (Định hướng bối cảnh): " & "Áp dụng tính chất hệ số góc của hai đường thẳng vuông góc.")))) | P10: =IF(OR(G10="✅ Đúng", I10="✅ Đúng", K10="✅ Đúng"), "Perpendicular Slope Condition: m1 * m2 = -1 => m_j = 3/2.", "🔒 Trả lời đúng để mở khóa Strategic Tip!")
A11: Q7 | B11: Exponential Population Growth Rate | C11: Model P(t) = 250(1.08)^t gives the population after t hours. | D11: Calculator Allowed. By what percentage does the population increase each hour? | E11: A. 0.08% B. 8% C. 25% D. 108% | G11: =IF(ISBLANK(F11), "⏳ Chờ đáp án", IF(UPPER(TRIM(F11))="B", "✅ Đúng", "❌ Sai")) | I11: =IF(ISBLANK(H11), "", IF(UPPER(TRIM(H11))="B", "✅ Đúng", "❌ Sai")) | K11: =IF(ISBLANK(J11), "", IF(UPPER(TRIM(J11))="B", "✅ Đúng", "❌ Sai")) | L11: =COUNTIF(G11, "❌ Sai") + COUNTIF(I11, "❌ Sai") + COUNTIF(K11, "❌ Sai") | M11: =IF(ISBLANK(F11), "⏳ Chờ làm", IF(G11="✅ Đúng", "✅ Đúng ngay L1", IF(I11="✅ Đúng", "✅ Đúng ở L2", IF(K11="✅ Đúng", "✅ Đúng ở L3", "❌ Chưa đúng sau 3 lần")))) | N11: =IF(G11="✅ Đúng", 1, IF(I11="✅ Đúng", 0.667, IF(K11="✅ Đúng", 0.333, 0))) | O11: =IF(ISBLANK(F11), "💡 Nhập đáp án vào Lần thử 1", IF(OR(G11="✅ Đúng", I11="✅ Đúng", K11="✅ Đúng"), "✨ Xuất sắc! Bạn đã làm đúng.", IF(NOT(ISBLANK(J11)), "💡 Gợi ý Tầng 3 (Chốt phương pháp): " & "Chuyển đổi r sang dạng phần trăm %.", IF(NOT(ISBLANK(H11)), "💡 Gợi ý Tầng 2 (Manh mối cấu trúc & Loại trừ): " & "So sánh thừa số cơ số trong ngoặc với dạng (1 + r).", "💡 Gợi ý Tầng 1 (Định hướng bối cảnh): " & "Xác định tỉ lệ tăng trưởng trong mô hình suy giảm/tăng trưởng mũ y = a(1 + r)^t.")))) | P11: =IF(OR(G11="✅ Đúng", I11="✅ Đúng", K11="✅ Đúng"), "Growth Factor = 1 + r => 1.08 = 1 + 0.08 => r = 8%.", "🔒 Trả lời đúng để mở khóa Strategic Tip!")
A12: Q8 | B12: Exponential Cooling Evaluation | C12: Temperature function g(t) = 296 + (362 - 296)(2.72)^(-0.104t). | D12: Calculator Allowed. What was the approximate temperature, in kelvins, when the liquid was placed on the table (t = 0)? | E12: Student-Produced Response (Grid-in) | G12: =IF(ISBLANK(F12), "⏳ Chờ đáp án", IF(UPPER(TRIM(F12))="362", "✅ Đúng", "❌ Sai")) | I12: =IF(ISBLANK(H12), "", IF(UPPER(TRIM(H12))="362", "✅ Đúng", "❌ Sai")) | K12: =IF(ISBLANK(J12), "", IF(UPPER(TRIM(J12))="362", "✅ Đúng", "❌ Sai")) | L12: =COUNTIF(G12, "❌ Sai") + COUNTIF(I12, "❌ Sai") + COUNTIF(K12, "❌ Sai") | M12: =IF(ISBLANK(F12), "⏳ Chờ làm", IF(G12="✅ Đúng", "✅ Đúng ngay L1", IF(I12="✅ Đúng", "✅ Đúng ở L2", IF(K12="✅ Đúng", "✅ Đúng ở L3", "❌ Chưa đúng sau 3 lần")))) | N12: =IF(G12="✅ Đúng", 1, IF(I12="✅ Đúng", 0.667, IF(K12="✅ Đúng", 0.333, 0))) | O12: =IF(ISBLANK(F12), "💡 Nhập đáp án vào Lần thử 1", IF(OR(G12="✅ Đúng", I12="✅ Đúng", K12="✅ Đúng"), "✨ Xuất sắc! Bạn đã làm đúng.", IF(NOT(ISBLANK(J12)), "💡 Gợi ý Tầng 3 (Chốt phương pháp): " & "Thực hiện phép tính lũy thừa rồi nhân với hệ số ban đầu.", IF(NOT(ISBLANK(H12)), "💡 Gợi ý Tầng 2 (Manh mối cấu trúc & Loại trừ): " & "Thay giá trị thời gian t đề bài cho vào công thức.", "💡 Gợi ý Tầng 1 (Định hướng bối cảnh): " & "Đánh giá giá trị hàm suy giảm mũ theo thời gian t.")))) | P12: =IF(OR(G12="✅ Đúng", I12="✅ Đúng", K12="✅ Đúng"), "Evaluate at t = 0: g(0) = 296 + (362 - 296) * 1 = 362.", "🔒 Trả lời đúng để mở khóa Strategic Tip!")
A13: Q9 | B13: Linear Inequalities (Graphing) | C13: A shaded region lies below the line passing through (0, 4) with slope -3. | D13: Calculator Allowed. Which inequality represents the shaded region? | E13: A. Lựa chọn A B. Lựa chọn B C. Lựa chọn C D. Lựa chọn D | G13: =IF(ISBLANK(F13), "⏳ Chờ đáp án", IF(UPPER(TRIM(F13))="C", "✅ Đúng", "❌ Sai")) | I13: =IF(ISBLANK(H13), "", IF(UPPER(TRIM(H13))="C", "✅ Đúng", "❌ Sai")) | K13: =IF(ISBLANK(J13), "", IF(UPPER(TRIM(J13))="C", "✅ Đúng", "❌ Sai")) | L13: =COUNTIF(G13, "❌ Sai") + COUNTIF(I13, "❌ Sai") + COUNTIF(K13, "❌ Sai") | M13: =IF(ISBLANK(F13), "⏳ Chờ làm", IF(G13="✅ Đúng", "✅ Đúng ngay L1", IF(I13="✅ Đúng", "✅ Đúng ở L2", IF(K13="✅ Đúng", "✅ Đúng ở L3", "❌ Chưa đúng sau 3 lần")))) | N13: =IF(G13="✅ Đúng", 1, IF(I13="✅ Đúng", 0.667, IF(K13="✅ Đúng", 0.333, 0))) | O13: =IF(ISBLANK(F13), "💡 Nhập đáp án vào Lần thử 1", IF(OR(G13="✅ Đúng", I13="✅ Đúng", K13="✅ Đúng"), "✨ Xuất sắc! Bạn đã làm đúng.", IF(NOT(ISBLANK(J13)), "💡 Gợi ý Tầng 3 (Chốt phương pháp): " & "Miền nghiệm nằm bên dưới đường biên nếu là dấu '<' hoặc bên trên nếu là dấu '>'.", IF(NOT(ISBLANK(H13)), "💡 Gợi ý Tầng 2 (Manh mối cấu trúc & Loại trừ): " & "Đưa bất phương trình về dạng y < mx + b hoặc y > mx + b.", "💡 Gợi ý Tầng 1 (Định hướng bối cảnh): " & "Xác định miền nghiệm của bất phương trình tuyến tính trên mặt phẳng tọa độ.")))) | P13: =IF(OR(G13="✅ Đúng", I13="✅ Đúng", K13="✅ Đúng"), "Linear Inequality: Region below solid line y = -3x + 4 is y < -3x + 4.", "🔒 Trả lời đúng để mở khóa Strategic Tip!")
A14: Q10 | B14: Systems of Linear Equations (Substitution) | C14: System of equations: 3(2x) + 8(9y) = 534 and 3(2x) - 8(9y) = -618. | D14: Calculator Allowed. What is the value of 2x + 9y? | E14: A. Lựa chọn A B. Lựa chọn B C. Lựa chọn C D. Lựa chọn D | G14: =IF(ISBLANK(F14), "⏳ Chờ đáp án", IF(UPPER(TRIM(F14))="C", "✅ Đúng", "❌ Sai")) | I14: =IF(ISBLANK(H14), "", IF(UPPER(TRIM(H14))="C", "✅ Đúng", "❌ Sai")) | K14: =IF(ISBLANK(J14), "", IF(UPPER(TRIM(J14))="C", "✅ Đúng", "❌ Sai")) | L14: =COUNTIF(G14, "❌ Sai") + COUNTIF(I14, "❌ Sai") + COUNTIF(K14, "❌ Sai") | M14: =IF(ISBLANK(F14), "⏳ Chờ làm", IF(G14="✅ Đúng", "✅ Đúng ngay L1", IF(I14="✅ Đúng", "✅ Đúng ở L2", IF(K14="✅ Đúng", "✅ Đúng ở L3", "❌ Chưa đúng sau 3 lần")))) | N14: =IF(G14="✅ Đúng", 1, IF(I14="✅ Đúng", 0.667, IF(K14="✅ Đúng", 0.333, 0))) | O14: =IF(ISBLANK(F14), "💡 Nhập đáp án vào Lần thử 1", IF(OR(G14="✅ Đúng", I14="✅ Đúng", K14="✅ Đúng"), "✨ Xuất sắc! Bạn đã làm đúng.", IF(NOT(ISBLANK(J14)), "💡 Gợi ý Tầng 3 (Chốt phương pháp): " & "Giải tìm biến thứ nhất rồi thế ngược lại để tìm biến thứ hai.", IF(NOT(ISBLANK(H14)), "💡 Gợi ý Tầng 2 (Manh mối cấu trúc & Loại trừ): " & "Nhân các phương trình với hệ số thích hợp để triệt tiêu một biến.", "💡 Gợi ý Tầng 1 (Định hướng bối cảnh): " & "Giải hệ phương trình tuyến tính hai ẩn bằng phương pháp thế hoặc cộng đại số.")))) | P14: =IF(OR(G14="✅ Đúng", I14="✅ Đúng", K14="✅ Đúng"), "Add equations: 12x = -84 => x = -7 => 2x = -14; 144y = 1152 => 9y = 72 => -14 + 72 = 58.", "🔒 Trả lời đúng để mở khóa Strategic Tip!")
A15: Q11 | B15: Quadratic Vertex & Maximum | C15: Given the function f(x) = -2(x - 3)^2 + 8. | D15: Calculator Allowed. What is the maximum value of f(x)? | E15: A. Lựa chọn A B. Lựa chọn B C. Lựa chọn C D. Lựa chọn D | G15: =IF(ISBLANK(F15), "⏳ Chờ đáp án", IF(UPPER(TRIM(F15))="D", "✅ Đúng", "❌ Sai")) | I15: =IF(ISBLANK(H15), "", IF(UPPER(TRIM(H15))="D", "✅ Đúng", "❌ Sai")) | K15: =IF(ISBLANK(J15), "", IF(UPPER(TRIM(J15))="D", "✅ Đúng", "❌ Sai")) | L15: =COUNTIF(G15, "❌ Sai") + COUNTIF(I15, "❌ Sai") + COUNTIF(K15, "❌ Sai") | M15: =IF(ISBLANK(F15), "⏳ Chờ làm", IF(G15="✅ Đúng", "✅ Đúng ngay L1", IF(I15="✅ Đúng", "✅ Đúng ở L2", IF(K15="✅ Đúng", "✅ Đúng ở L3", "❌ Chưa đúng sau 3 lần")))) | N15: =IF(G15="✅ Đúng", 1, IF(I15="✅ Đúng", 0.667, IF(K15="✅ Đúng", 0.333, 0))) | O15: =IF(ISBLANK(F15), "💡 Nhập đáp án vào Lần thử 1", IF(OR(G15="✅ Đúng", I15="✅ Đúng", K15="✅ Đúng"), "✨ Xuất sắc! Bạn đã làm đúng.", IF(NOT(ISBLANK(J15)), "💡 Gợi ý Tầng 3 (Chốt phương pháp): " & "Giá trị cực đại/cực tiểu chính là tung độ đỉnh k.", IF(NOT(ISBLANK(H15)), "💡 Gợi ý Tầng 2 (Manh mối cấu trúc & Loại trừ): " & "Xác định hoành độ đỉnh x = -b / (2a) hoặc đưa về dạng đỉnh a(x - h)^2 + k.", "💡 Gợi ý Tầng 1 (Định hướng bối cảnh): " & "Tìm giá trị lớn nhất/nhỏ nhất của hàm số bậc hai y = ax^2 + bx + c.")))) | P15: =IF(OR(G15="✅ Đúng", I15="✅ Đúng", K15="✅ Đúng"), "Parabola Vertex (h, k) with a < 0 has maximum value = k = 8.", "🔒 Trả lời đúng để mở khóa Strategic Tip!")
A16: Q12 | B16: Statistics (Effect of Adding Outlier on Mean & Median) | C16: A frequency table summarizes ages of 50 coins (mean = 72.5, median = 70). Vivek adds a 51st coin aged 90 years. | D16: Calculator Allowed. Which statement correctly compares the mean and median ages of the original and new collections? | E16: A. Lựa chọn A B. Lựa chọn B C. Lựa chọn C D. Lựa chọn D | G16: =IF(ISBLANK(F16), "⏳ Chờ đáp án", IF(UPPER(TRIM(F16))="B", "✅ Đúng", "❌ Sai")) | I16: =IF(ISBLANK(H16), "", IF(UPPER(TRIM(H16))="B", "✅ Đúng", "❌ Sai")) | K16: =IF(ISBLANK(J16), "", IF(UPPER(TRIM(J16))="B", "✅ Đúng", "❌ Sai")) | L16: =COUNTIF(G16, "❌ Sai") + COUNTIF(I16, "❌ Sai") + COUNTIF(K16, "❌ Sai") | M16: =IF(ISBLANK(F16), "⏳ Chờ làm", IF(G16="✅ Đúng", "✅ Đúng ngay L1", IF(I16="✅ Đúng", "✅ Đúng ở L2", IF(K16="✅ Đúng", "✅ Đúng ở L3", "❌ Chưa đúng sau 3 lần")))) | N16: =IF(G16="✅ Đúng", 1, IF(I16="✅ Đúng", 0.667, IF(K16="✅ Đúng", 0.333, 0))) | O16: =IF(ISBLANK(F16), "💡 Nhập đáp án vào Lần thử 1", IF(OR(G16="✅ Đúng", I16="✅ Đúng", K16="✅ Đúng"), "✨ Xuất sắc! Bạn đã làm đúng.", IF(NOT(ISBLANK(J16)), "💡 Gợi ý Tầng 3 (Chốt phương pháp): " & "Số trung bình Mean sẽ dịch chuyển về phía outlier, trong khi Median ít bị ảnh hưởng.", IF(NOT(ISBLANK(H16)), "💡 Gợi ý Tầng 2 (Manh mối cấu trúc & Loại trừ): " & "So sánh giá trị ngoại lai với số trung bình (Mean) hiện tại.", "💡 Gợi ý Tầng 1 (Định hướng bối cảnh): " & "Đánh giá tác động của việc thêm một giá trị ngoại lai (outlier) vào tập dữ liệu.")))) | P16: =IF(OR(G16="✅ Đúng", I16="✅ Đúng", K16="✅ Đúng"), "Adding a high value increases Mean; Median position remains in the same frequency bin.", "🔒 Trả lời đúng để mở khóa Strategic Tip!")
A17: Q13 | B17: Non-linear Systems (Circle & Line) | C17: System of equations: x^2 + y^2 = 64 and y = mx + b/2. Intersect at (-7, y) with y < 0. | D17: Calculator Allowed. Which expression represents the value of b? | E17: A. Lựa chọn A B. Lựa chọn B C. Lựa chọn C D. Lựa chọn D | G17: =IF(ISBLANK(F17), "⏳ Chờ đáp án", IF(UPPER(TRIM(F17))="A", "✅ Đúng", "❌ Sai")) | I17: =IF(ISBLANK(H17), "", IF(UPPER(TRIM(H17))="A", "✅ Đúng", "❌ Sai")) | K17: =IF(ISBLANK(J17), "", IF(UPPER(TRIM(J17))="A", "✅ Đúng", "❌ Sai")) | L17: =COUNTIF(G17, "❌ Sai") + COUNTIF(I17, "❌ Sai") + COUNTIF(K17, "❌ Sai") | M17: =IF(ISBLANK(F17), "⏳ Chờ làm", IF(G17="✅ Đúng", "✅ Đúng ngay L1", IF(I17="✅ Đúng", "✅ Đúng ở L2", IF(K17="✅ Đúng", "✅ Đúng ở L3", "❌ Chưa đúng sau 3 lần")))) | N17: =IF(G17="✅ Đúng", 1, IF(I17="✅ Đúng", 0.667, IF(K17="✅ Đúng", 0.333, 0))) | O17: =IF(ISBLANK(F17), "💡 Nhập đáp án vào Lần thử 1", IF(OR(G17="✅ Đúng", I17="✅ Đúng", K17="✅ Đúng"), "✨ Xuất sắc! Bạn đã làm đúng.", IF(NOT(ISBLANK(J17)), "💡 Gợi ý Tầng 3 (Chốt phương pháp): " & "Giải phương trình bậc hai một ẩn thu được để tìm tọa độ giao điểm.", IF(NOT(ISBLANK(H17)), "💡 Gợi ý Tầng 2 (Manh mối cấu trúc & Loại trừ): " & "Thế biểu thức y (hoặc x) từ phương trình đường thẳng vào phương trình đường tròn.", "💡 Gợi ý Tầng 1 (Định hướng bối cảnh): " & "Giải hệ phương trình gồm đường thẳng và đường tròn.")))) | P17: =IF(OR(G17="✅ Đúng", I17="✅ Đúng", K17="✅ Đúng"), "Substitute (-7, -sqrt(15)) into line equation => -sqrt(15) = -7m + b/2 => b = 14m - 2*sqrt(15).", "🔒 Trả lời đúng để mở khóa Strategic Tip!")
A18: Q14 | B18: Geometry (Similar Triangles) | C18: In triangle ABC, DE is parallel to AC, BD = AD, BE = 9, and AC = 8. | D18: Calculator Allowed. What is the length of BC? | E18: A. Lựa chọn A B. Lựa chọn B C. Lựa chọn C D. Lựa chọn D | G18: =IF(ISBLANK(F18), "⏳ Chờ đáp án", IF(UPPER(TRIM(F18))="B", "✅ Đúng", "❌ Sai")) | I18: =IF(ISBLANK(H18), "", IF(UPPER(TRIM(H18))="B", "✅ Đúng", "❌ Sai")) | K18: =IF(ISBLANK(J18), "", IF(UPPER(TRIM(J18))="B", "✅ Đúng", "❌ Sai")) | L18: =COUNTIF(G18, "❌ Sai") + COUNTIF(I18, "❌ Sai") + COUNTIF(K18, "❌ Sai") | M18: =IF(ISBLANK(F18), "⏳ Chờ làm", IF(G18="✅ Đúng", "✅ Đúng ngay L1", IF(I18="✅ Đúng", "✅ Đúng ở L2", IF(K18="✅ Đúng", "✅ Đúng ở L3", "❌ Chưa đúng sau 3 lần")))) | N18: =IF(G18="✅ Đúng", 1, IF(I18="✅ Đúng", 0.667, IF(K18="✅ Đúng", 0.333, 0))) | O18: =IF(ISBLANK(F18), "💡 Nhập đáp án vào Lần thử 1", IF(OR(G18="✅ Đúng", I18="✅ Đúng", K18="✅ Đúng"), "✨ Xuất sắc! Bạn đã làm đúng.", IF(NOT(ISBLANK(J18)), "💡 Gợi ý Tầng 3 (Chốt phương pháp): " & "Giải phương trình tỉ lệ để tính độ dài đoạn thẳng chưa biết.", IF(NOT(ISBLANK(H18)), "💡 Gợi ý Tầng 2 (Manh mối cấu trúc & Loại trừ): " & "Thiết lập tỉ lệ giữa các đoạn thẳng tương ứng.", "💡 Gợi ý Tầng 1 (Định hướng bối cảnh): " & "Áp dụng định lý đường trung bình hoặc tính chất tam giác đồng dạng.")))) | P18: =IF(OR(G18="✅ Đúng", I18="✅ Đúng", K18="✅ Đúng"), "Midpoint Segment Theorem: BC = 2 * BE = 18.", "🔒 Trả lời đúng để mở khóa Strategic Tip!")
A19: Q15 | B19: Systems of Equations Evaluation | C19: System of equations: 2x + 3y = 19 and 2x - y = 3. | D19: Calculator Allowed. What is the value of x + y? | E19: A. Lựa chọn A B. Lựa chọn B C. Lựa chọn C D. Lựa chọn D | G19: =IF(ISBLANK(F19), "⏳ Chờ đáp án", IF(UPPER(TRIM(F19))="C", "✅ Đúng", "❌ Sai")) | I19: =IF(ISBLANK(H19), "", IF(UPPER(TRIM(H19))="C", "✅ Đúng", "❌ Sai")) | K19: =IF(ISBLANK(J19), "", IF(UPPER(TRIM(J19))="C", "✅ Đúng", "❌ Sai")) | L19: =COUNTIF(G19, "❌ Sai") + COUNTIF(I19, "❌ Sai") + COUNTIF(K19, "❌ Sai") | M19: =IF(ISBLANK(F19), "⏳ Chờ làm", IF(G19="✅ Đúng", "✅ Đúng ngay L1", IF(I19="✅ Đúng", "✅ Đúng ở L2", IF(K19="✅ Đúng", "✅ Đúng ở L3", "❌ Chưa đúng sau 3 lần")))) | N19: =IF(G19="✅ Đúng", 1, IF(I19="✅ Đúng", 0.667, IF(K19="✅ Đúng", 0.333, 0))) | O19: =IF(ISBLANK(F19), "💡 Nhập đáp án vào Lần thử 1", IF(OR(G19="✅ Đúng", I19="✅ Đúng", K19="✅ Đúng"), "✨ Xuất sắc! Bạn đã làm đúng.", IF(NOT(ISBLANK(J19)), "💡 Gợi ý Tầng 3 (Chốt phương pháp): " & "Thực hiện phép cộng/trừ hai phương trình theo vế.", IF(NOT(ISBLANK(H19)), "💡 Gợi ý Tầng 2 (Manh mối cấu trúc & Loại trừ): " & "Sử dụng phương pháp cộng đại số để tìm trực tiếp biểu thức đề bài yêu cầu.", "💡 Gợi ý Tầng 1 (Định hướng bối cảnh): " & "Giải hệ phương trình tuyến tính hai ẩn.")))) | P19: =IF(OR(G19="✅ Đúng", I19="✅ Đúng", K19="✅ Đúng"), "Solve system: y = 4, x = 3 => x + y = 7.", "🔒 Trả lời đúng để mở khóa Strategic Tip!")
A20: Q16 | B20: Statistics (Sampling Bias) | C20: A study on melatonin levels sampled 125 gamers from 3 countries (Sweden 25, South Korea 49, US 51). | D20: Calculator Allowed. Which aspect prevents the results from being generalized to ALL gamers globally? | E20: A. Lựa chọn A B. Lựa chọn B C. Lựa chọn C D. Lựa chọn D | G20: =IF(ISBLANK(F20), "⏳ Chờ đáp án", IF(UPPER(TRIM(F20))="A", "✅ Đúng", "❌ Sai")) | I20: =IF(ISBLANK(H20), "", IF(UPPER(TRIM(H20))="A", "✅ Đúng", "❌ Sai")) | K20: =IF(ISBLANK(J20), "", IF(UPPER(TRIM(J20))="A", "✅ Đúng", "❌ Sai")) | L20: =COUNTIF(G20, "❌ Sai") + COUNTIF(I20, "❌ Sai") + COUNTIF(K20, "❌ Sai") | M20: =IF(ISBLANK(F20), "⏳ Chờ làm", IF(G20="✅ Đúng", "✅ Đúng ngay L1", IF(I20="✅ Đúng", "✅ Đúng ở L2", IF(K20="✅ Đúng", "✅ Đúng ở L3", "❌ Chưa đúng sau 3 lần")))) | N20: =IF(G20="✅ Đúng", 1, IF(I20="✅ Đúng", 0.667, IF(K20="✅ Đúng", 0.333, 0))) | O20: =IF(ISBLANK(F20), "💡 Nhập đáp án vào Lần thử 1", IF(OR(G20="✅ Đúng", I20="✅ Đúng", K20="✅ Đúng"), "✨ Xuất sắc! Bạn đã làm đúng.", IF(NOT(ISBLANK(J20)), "💡 Gợi ý Tầng 3 (Chốt phương pháp): " & "Mẫu bị giới hạn phạm vi sẽ gây ra sai số chọn mẫu (sampling bias) và không thể suy rộng.", IF(NOT(ISBLANK(H20)), "💡 Gợi ý Tầng 2 (Manh mối cấu trúc & Loại trừ): " & "Kiểm tra xem mẫu khảo sát có được chọn ngẫu nhiên từ toàn bộ quần thể hay không.", "💡 Gợi ý Tầng 1 (Định hướng bối cảnh): " & "Phân tích tính đại diện của mẫu khảo sát thống kê.")))) | P20: =IF(OR(G20="✅ Đúng", I20="✅ Đúng", K20="✅ Đúng"), "Generalizability requires random sampling from the target population.", "🔒 Trả lời đúng để mở khóa Strategic Tip!")
A21: Q17 | B21: Trigonometry (Right Triangle Ratios) | C21: In right triangle ABC with right angle C = 90 deg, cos A = 5/13. | D21: Calculator Allowed. What is the value of tan A? | E21: A. Lựa chọn A B. Lựa chọn B C. Lựa chọn C D. Lựa chọn D | G21: =IF(ISBLANK(F21), "⏳ Chờ đáp án", IF(UPPER(TRIM(F21))="A", "✅ Đúng", "❌ Sai")) | I21: =IF(ISBLANK(H21), "", IF(UPPER(TRIM(H21))="A", "✅ Đúng", "❌ Sai")) | K21: =IF(ISBLANK(J21), "", IF(UPPER(TRIM(J21))="A", "✅ Đúng", "❌ Sai")) | L21: =COUNTIF(G21, "❌ Sai") + COUNTIF(I21, "❌ Sai") + COUNTIF(K21, "❌ Sai") | M21: =IF(ISBLANK(F21), "⏳ Chờ làm", IF(G21="✅ Đúng", "✅ Đúng ngay L1", IF(I21="✅ Đúng", "✅ Đúng ở L2", IF(K21="✅ Đúng", "✅ Đúng ở L3", "❌ Chưa đúng sau 3 lần")))) | N21: =IF(G21="✅ Đúng", 1, IF(I21="✅ Đúng", 0.667, IF(K21="✅ Đúng", 0.333, 0))) | O21: =IF(ISBLANK(F21), "💡 Nhập đáp án vào Lần thử 1", IF(OR(G21="✅ Đúng", I21="✅ Đúng", K21="✅ Đúng"), "✨ Xuất sắc! Bạn đã làm đúng.", IF(NOT(ISBLANK(J21)), "💡 Gợi ý Tầng 3 (Chốt phương pháp): " & "Tính tỉ số lượng giác (sin = Đối/Huyền, cos = Kề/Huyền, tan = Đối/Kề) tương ứng.", IF(NOT(ISBLANK(H21)), "💡 Gợi ý Tầng 2 (Manh mối cấu trúc & Loại trừ): " & "Sử dụng định lý Pitago a^2 + b^2 = c^2 để tìm độ dài cạnh còn thiếu.", "💡 Gợi ý Tầng 1 (Định hướng bối cảnh): " & "Áp dụng tỉ số lượng giác trong tam giác vuông.")))) | P21: =IF(OR(G21="✅ Đúng", I21="✅ Đúng", K21="✅ Đúng"), "5-12-13 Right Triangle: cos A = 5/13 => sin A = 12/13 => tan A = 12/5.", "🔒 Trả lời đúng để mở khóa Strategic Tip!")
A22: Q18 | B22: Percentages (Percent Increase) | C22: Guests used the pool for t hours in March and 3.41t hours in April. | D22: Calculator Allowed. What is the percent increase in pool usage from March to April? | E22: A. Lựa chọn A B. Lựa chọn B C. Lựa chọn C D. Lựa chọn D | G22: =IF(ISBLANK(F22), "⏳ Chờ đáp án", IF(UPPER(TRIM(F22))="C", "✅ Đúng", "❌ Sai")) | I22: =IF(ISBLANK(H22), "", IF(UPPER(TRIM(H22))="C", "✅ Đúng", "❌ Sai")) | K22: =IF(ISBLANK(J22), "", IF(UPPER(TRIM(J22))="C", "✅ Đúng", "❌ Sai")) | L22: =COUNTIF(G22, "❌ Sai") + COUNTIF(I22, "❌ Sai") + COUNTIF(K22, "❌ Sai") | M22: =IF(ISBLANK(F22), "⏳ Chờ làm", IF(G22="✅ Đúng", "✅ Đúng ngay L1", IF(I22="✅ Đúng", "✅ Đúng ở L2", IF(K22="✅ Đúng", "✅ Đúng ở L3", "❌ Chưa đúng sau 3 lần")))) | N22: =IF(G22="✅ Đúng", 1, IF(I22="✅ Đúng", 0.667, IF(K22="✅ Đúng", 0.333, 0))) | O22: =IF(ISBLANK(F22), "💡 Nhập đáp án vào Lần thử 1", IF(OR(G22="✅ Đúng", I22="✅ Đúng", K22="✅ Đúng"), "✨ Xuất sắc! Bạn đã làm đúng.", IF(NOT(ISBLANK(J22)), "💡 Gợi ý Tầng 3 (Chốt phương pháp): " & "Thực hiện phép chia rồi nhân với 100%.", IF(NOT(ISBLANK(H22)), "💡 Gợi ý Tầng 2 (Manh mối cấu trúc & Loại trừ): " & "Áp dụng công thức Percent Increase = (Mới - Cũ) / Cũ x 100%.", "💡 Gợi ý Tầng 1 (Định hướng bối cảnh): " & "Tính tỉ lệ phần trăm tăng giữa hai giá trị.")))) | P22: =IF(OR(G22="✅ Đúng", I22="✅ Đúng", K22="✅ Đúng"), "Percent Increase = (3.41 - 1) * 100% = 241%.", "🔒 Trả lời đúng để mở khóa Strategic Tip!")
A23: Q19 | B23: Algebraic Expansion & Coefficients | C23: The expression [4(3x - 4)^2 + 6(3x - 2)^2] / 4 can be rewritten as (a/4)x^2 + (b/4)x + (c/4). | D23: Calculator Allowed. What is the value of a + b + c? | E23: A. Lựa chọn A B. Lựa chọn B C. Lựa chọn C D. Lựa chọn D | G23: =IF(ISBLANK(F23), "⏳ Chờ đáp án", IF(UPPER(TRIM(F23))="A", "✅ Đúng", "❌ Sai")) | I23: =IF(ISBLANK(H23), "", IF(UPPER(TRIM(H23))="A", "✅ Đúng", "❌ Sai")) | K23: =IF(ISBLANK(J23), "", IF(UPPER(TRIM(J23))="A", "✅ Đúng", "❌ Sai")) | L23: =COUNTIF(G23, "❌ Sai") + COUNTIF(I23, "❌ Sai") + COUNTIF(K23, "❌ Sai") | M23: =IF(ISBLANK(F23), "⏳ Chờ làm", IF(G23="✅ Đúng", "✅ Đúng ngay L1", IF(I23="✅ Đúng", "✅ Đúng ở L2", IF(K23="✅ Đúng", "✅ Đúng ở L3", "❌ Chưa đúng sau 3 lần")))) | N23: =IF(G23="✅ Đúng", 1, IF(I23="✅ Đúng", 0.667, IF(K23="✅ Đúng", 0.333, 0))) | O23: =IF(ISBLANK(F23), "💡 Nhập đáp án vào Lần thử 1", IF(OR(G23="✅ Đúng", I23="✅ Đúng", K23="✅ Đúng"), "✨ Xuất sắc! Bạn đã làm đúng.", IF(NOT(ISBLANK(J23)), "💡 Gợi ý Tầng 3 (Chốt phương pháp): " & "Đồng nhất các hệ số tương ứng ở hai vế để tính tổng các hệ số.", IF(NOT(ISBLANK(H23)), "💡 Gợi ý Tầng 2 (Manh mối cấu trúc & Loại trừ): " & "Nhân các đa thức và nhóm các số hạng đồng dạng.", "💡 Gợi ý Tầng 1 (Định hướng bối cảnh): " & "Khai triển và thu gọn biểu thức đa thức.")))) | P23: =IF(OR(G23="✅ Đúng", I23="✅ Đúng", K23="✅ Đúng"), "Evaluate at x = 1 to find sum of coefficients a + b + c.", "🔒 Trả lời đúng để mở khóa Strategic Tip!")
A24: Q20 | B24: Consecutive Integers Inequality | C24: The sum of three consecutive even integers is less than 123. The least integer is x. | D24: Calculator Allowed. What is the greatest possible value of x? | E24: A. Lựa chọn A B. Lựa chọn B C. Lựa chọn C D. Lựa chọn D | G24: =IF(ISBLANK(F24), "⏳ Chờ đáp án", IF(UPPER(TRIM(F24))="D", "✅ Đúng", "❌ Sai")) | I24: =IF(ISBLANK(H24), "", IF(UPPER(TRIM(H24))="D", "✅ Đúng", "❌ Sai")) | K24: =IF(ISBLANK(J24), "", IF(UPPER(TRIM(J24))="D", "✅ Đúng", "❌ Sai")) | L24: =COUNTIF(G24, "❌ Sai") + COUNTIF(I24, "❌ Sai") + COUNTIF(K24, "❌ Sai") | M24: =IF(ISBLANK(F24), "⏳ Chờ làm", IF(G24="✅ Đúng", "✅ Đúng ngay L1", IF(I24="✅ Đúng", "✅ Đúng ở L2", IF(K24="✅ Đúng", "✅ Đúng ở L3", "❌ Chưa đúng sau 3 lần")))) | N24: =IF(G24="✅ Đúng", 1, IF(I24="✅ Đúng", 0.667, IF(K24="✅ Đúng", 0.333, 0))) | O24: =IF(ISBLANK(F24), "💡 Nhập đáp án vào Lần thử 1", IF(OR(G24="✅ Đúng", I24="✅ Đúng", K24="✅ Đúng"), "✨ Xuất sắc! Bạn đã làm đúng.", IF(NOT(ISBLANK(J24)), "💡 Gợi ý Tầng 3 (Chốt phương pháp): " & "Giải bất phương trình thu được để tìm giá trị số nguyên lớn nhất thỏa mãn.", IF(NOT(ISBLANK(H24)), "💡 Gợi ý Tầng 2 (Manh mối cấu trúc & Loại trừ): " & "Biểu diễn các số nguyên liên tiếp dưới dạng x, x + 2, x + 4 (nếu là số chẵn/lẻ).", "💡 Gợi ý Tầng 1 (Định hướng bối cảnh): " & "Thiết lập bất phương trình cho tổng các số nguyên liên tiếp.")))) | P24: =IF(OR(G24="✅ Đúng", I24="✅ Đúng", K24="✅ Đúng"), "3x + 6 < 123 => x < 39. Greatest even integer is 38.", "🔒 Trả lời đúng để mở khóa Strategic Tip!")
A25: Q21 | B25: Similar 3D Solids (Area & Volume Ratios) | C25: Prism X is similar to Prism Y. Surface area X = 52 cm^2, Surface area Y = 832 cm^2. Volume X = 10.5 cm^3. | D25: Calculator Allowed. What is the volume, in cm^3, of right rectangular prism Y? | E25: Student-Produced Response (Grid-in) | G25: =IF(ISBLANK(F25), "⏳ Chờ đáp án", IF(UPPER(TRIM(F25))="672", "✅ Đúng", "❌ Sai")) | I25: =IF(ISBLANK(H25), "", IF(UPPER(TRIM(H25))="672", "✅ Đúng", "❌ Sai")) | K25: =IF(ISBLANK(J25), "", IF(UPPER(TRIM(J25))="672", "✅ Đúng", "❌ Sai")) | L25: =COUNTIF(G25, "❌ Sai") + COUNTIF(I25, "❌ Sai") + COUNTIF(K25, "❌ Sai") | M25: =IF(ISBLANK(F25), "⏳ Chờ làm", IF(G25="✅ Đúng", "✅ Đúng ngay L1", IF(I25="✅ Đúng", "✅ Đúng ở L2", IF(K25="✅ Đúng", "✅ Đúng ở L3", "❌ Chưa đúng sau 3 lần")))) | N25: =IF(G25="✅ Đúng", 1, IF(I25="✅ Đúng", 0.667, IF(K25="✅ Đúng", 0.333, 0))) | O25: =IF(ISBLANK(F25), "💡 Nhập đáp án vào Lần thử 1", IF(OR(G25="✅ Đúng", I25="✅ Đúng", K25="✅ Đúng"), "✨ Xuất sắc! Bạn đã làm đúng.", IF(NOT(ISBLANK(J25)), "💡 Gợi ý Tầng 3 (Chốt phương pháp): " & "Nhân thể tích hình ban đầu với tỉ lệ k^3 để tìm thể tích hình mới.", IF(NOT(ISBLANK(H25)), "💡 Gợi ý Tầng 2 (Manh mối cấu trúc & Loại trừ): " & "Nếu tỉ lệ diện tích là k^2, suy ra tỉ lệ chiều dài là k và tỉ lệ thể tích là k^3.", "💡 Gợi ý Tầng 1 (Định hướng bối cảnh): " & "Áp dụng mối quan hệ giữa tỉ lệ kích thước, diện tích và thể tích của hai hình đồng dạng.")))) | P25: =IF(OR(G25="✅ Đúng", I25="✅ Đúng", K25="✅ Đúng"), "Area ratio k^2 = 16 => k = 4 => Volume ratio k^3 = 64 => Vol Y = 10.5 * 64 = 672.", "🔒 Trả lời đúng để mở khóa Strategic Tip!")
A26: Q22 | B26: Quadratic Equation (Sum of Roots) | C26: Equation: 18(w - a)(w + 5) = 6(w + 5). The sum of solutions is 37/3. | D26: Calculator Allowed. What is the value of a? | E26: Student-Produced Response (Grid-in) | G26: =IF(ISBLANK(F26), "⏳ Chờ đáp án", IF(UPPER(TRIM(F26))="17", "✅ Đúng", "❌ Sai")) | I26: =IF(ISBLANK(H26), "", IF(UPPER(TRIM(H26))="17", "✅ Đúng", "❌ Sai")) | K26: =IF(ISBLANK(J26), "", IF(UPPER(TRIM(J26))="17", "✅ Đúng", "❌ Sai")) | L26: =COUNTIF(G26, "❌ Sai") + COUNTIF(I26, "❌ Sai") + COUNTIF(K26, "❌ Sai") | M26: =IF(ISBLANK(F26), "⏳ Chờ làm", IF(G26="✅ Đúng", "✅ Đúng ngay L1", IF(I26="✅ Đúng", "✅ Đúng ở L2", IF(K26="✅ Đúng", "✅ Đúng ở L3", "❌ Chưa đúng sau 3 lần")))) | N26: =IF(G26="✅ Đúng", 1, IF(I26="✅ Đúng", 0.667, IF(K26="✅ Đúng", 0.333, 0))) | O26: =IF(ISBLANK(F26), "💡 Nhập đáp án vào Lần thử 1", IF(OR(G26="✅ Đúng", I26="✅ Đúng", K26="✅ Đúng"), "✨ Xuất sắc! Bạn đã làm đúng.", IF(NOT(ISBLANK(J26)), "💡 Gợi ý Tầng 3 (Chốt phương pháp): " & "Sử dụng nghiệm đã biết để giải tìm ẩn số a.", IF(NOT(ISBLANK(H26)), "💡 Gợi ý Tầng 2 (Manh mối cấu trúc & Loại trừ): " & "Tổng hai nghiệm x1 + x2 = -b / a.", "💡 Gợi ý Tầng 1 (Định hướng bối cảnh): " & "Áp dụng định lý Viète về tổng các nghiệm của phương trình bậc hai ax^2 + bx + c = 0.")))) | P26: =IF(OR(G26="✅ Đúng", I26="✅ Đúng", K26="✅ Đúng"), "Roots are w1 = -5 and w2 = a + 1/3 => -5 + a + 1/3 = 37/3 => a = 17.", "🔒 Trả lời đúng để mở khóa Strategic Tip!")

Sheet Master_All_98_Questions
A1: MASTER QUESTION BANK: ALL 98 QUESTIONS (OCTOBER 2026 TEST)
A2: Tập hợp toàn bộ 98 câu hỏi liên tục từ ID M1 đến M98 của cả 4 Modules để thi thử tổng hợp
A4: Master ID | B4: Module Nguồn | C4: Topic / Skill Focus | D4: Passage & Context | E4: Question Prompt / Calculator | F4: Options / Choices (No Answer) | G4: Lần thử 1 | H4: Kết quả L1 | I4: Lần thử 2 | J4: Kết quả L2 | K4: Lần thử 3 | L4: Kết quả L3 | M4: Tổng số cột Sai | N4: Trạng thái Hoàn thành | O4: Hiệu suất (%) | P4: Hint / Gợi ý Đa tầng (Không đáp án) | Q4: Strategic Tip / Formula
A5: M1 | B5: Reading & Writing Module 1 | C5: Vocabulary in Context (Precision) | D5: ______ the source of a malfunction in a complex electrical system can be a painstaking, time-consuming process: a repair technician may need to test each individual component one by one until the specific part causing the problematic behavior is identified. | E5: Which choice completes the text with the most logical and precise word or phrase? | F5: A. Lựa chọn A B. Lựa chọn B C. Lựa chọn C D. Lựa chọn D | H5: =IF(ISBLANK(G5), "⏳ Chờ đáp án", IF(UPPER(TRIM(G5))="B", "✅ Đúng", "❌ Sai")) | J5: =IF(ISBLANK(I5), "", IF(UPPER(TRIM(I5))="B", "✅ Đúng", "❌ Sai")) | L5: =IF(ISBLANK(K5), "", IF(UPPER(TRIM(K5))="B", "✅ Đúng", "❌ Sai")) | M5: =COUNTIF(H5, "❌ Sai") + COUNTIF(J5, "❌ Sai") + COUNTIF(L5, "❌ Sai") | N5: =IF(ISBLANK(G5), "⏳ Chờ làm", IF(H5="✅ Đúng", "✅ Đúng ngay L1", IF(J5="✅ Đúng", "✅ Đúng ở L2", IF(L5="✅ Đúng", "✅ Đúng ở L3", "❌ Chưa đúng sau 3 lần")))) | O5: =IF(ISBLANK(F5), "💡 Nhập đáp án vào Lần thử 1", IF(G5="✅ Đúng", "✨ Xuất sắc! Bạn đã làm đúng.", "💡 Gợi ý: " & "Xác định thái độ của tác giả và mối quan hệ logic trong câu; chú ý các từ ngữ miêu tả mục đích chính xác của hành động.")) | P5: =IF(ISBLANK(G5), "💡 Nhập đáp án vào Lần thử 1", IF(OR(H5="✅ Đúng", J5="✅ Đúng", L5="✅ Đúng"), "✨ Xuất sắc! Bạn đã làm đúng.", IF(NOT(ISBLANK(K5)), "💡 Gợi ý Tầng 3 (Chốt phương pháp): " & "Loại trừ các từ mang nghĩa tạo mới hay điều chỉnh chung; chọn động từ chỉ việc cô lập/xác định nguyên nhân đơn lẻ.", IF(NOT(ISBLANK(I5)), "💡 Gợi ý Tầng 2 (Manh mối cấu trúc & Loại trừ): " & "Chú ý cụm từ 'test each individual component one by one' thể hiện việc khoanh vùng chính xác bộ phận lỗi.", "💡 Gợi ý Tầng 1 (Định hướng bối cảnh): " & "Xác định vai trò của động từ cần điền trong bối cảnh kỹ thuật sửa chữa hệ thống điện.")))) | Q5: =IF(OR(H5="✅ Đúng", J5="✅ Đúng", L5="✅ Đúng"), "Isolating = identifying/singling out the specific cause of a problem.", "🔒 Trả lời đúng để mở khóa Strategic Tip!")
A6: M2 | B6: Reading & Writing Module 1 | C6: Vocabulary in Context (Biological Processes) | D6: Single-celled foraminifera inhabiting coastal waters experience significant environmental salinity changes during tidal cycles. How, then, do they ______ internal salt levels? Some organisms maintain high concentrations of phosphates that allow them to affect the concentration of internal electrolytes— including salt—in response to external changes. It may be that coastal foraminifera do the same. | E6: Which choice completes the text with the most logical and precise word or phrase? | F6: A. Lựa chọn A B. Lựa chọn B C. Lựa chọn C D. Lựa chọn D | H6: =IF(ISBLANK(G6), "⏳ Chờ đáp án", IF(UPPER(TRIM(G6))="D", "✅ Đúng", "❌ Sai")) | J6: =IF(ISBLANK(I6), "", IF(UPPER(TRIM(I6))="D", "✅ Đúng", "❌ Sai")) | L6: =IF(ISBLANK(K6), "", IF(UPPER(TRIM(K6))="D", "✅ Đúng", "❌ Sai")) | M6: =COUNTIF(H6, "❌ Sai") + COUNTIF(J6, "❌ Sai") + COUNTIF(L6, "❌ Sai") | N6: =IF(ISBLANK(G6), "⏳ Chờ làm", IF(H6="✅ Đúng", "✅ Đúng ngay L1", IF(J6="✅ Đúng", "✅ Đúng ở L2", IF(L6="✅ Đúng", "✅ Đúng ở L3", "❌ Chưa đúng sau 3 lần")))) | O6: =IF(ISBLANK(F6), "💡 Nhập đáp án vào Lần thử 1", IF(G6="✅ Đúng", "✨ Xuất sắc! Bạn đã làm đúng.", "💡 Gợi ý: " & "Phân tích ngữ cảnh sinh học trong đoạn văn và xác định động từ thể hiện đúng chức năng của cơ chế được mô tả.")) | P6: =IF(ISBLANK(G6), "💡 Nhập đáp án vào Lần thử 1", IF(OR(H6="✅ Đúng", J6="✅ Đúng", L6="✅ Đúng"), "✨ Xuất sắc! Bạn đã làm đúng.", IF(NOT(ISBLANK(K6)), "💡 Gợi ý Tầng 3 (Chốt phương pháp): " & "Loại bỏ các động từ mang nghĩa phá hủy hay làm xáo trộn; tìm từ chỉ sự điều hòa/kiểm soát sinh học.", IF(NOT(ISBLANK(I6)), "💡 Gợi ý Tầng 2 (Manh mối cấu trúc & Loại trừ): " & "Cần một động từ miêu tả việc kiểm soát và duy trì mức độ ổn định của nồng độ muối.", "💡 Gợi ý Tầng 1 (Định hướng bối cảnh): " & "Phân tích cơ chế sinh học điều chỉnh độ mặn nội bào của loài cá ngừ được miêu tả.")))) | Q6: =IF(OR(H6="✅ Đúng", J6="✅ Đúng", L6="✅ Đúng"), "Regulate = control or maintain at a steady level.", "🔒 Trả lời đúng để mở khóa Strategic Tip!")
A7: M3 | B7: Reading & Writing Module 1 | C7: Vocabulary in Context (Research Approaches) | D7: Though most studies of the effect of altitude on blood chemistry usually concentrate on people who live above sea level, researchers Suleiman A. Al-Sweedan and Moath Alhaj have instead chosen the ______ path in their recent work of studying the blood of people who live below sea level, in locations such as the California towns of Westmorland and Thermal. | E7: Which choice completes the text with the most logical and precise word or phrase? | F7: A. Lựa chọn A B. Lựa chọn B C. Lựa chọn C D. Lựa chọn D | H7: =IF(ISBLANK(G7), "⏳ Chờ đáp án", IF(UPPER(TRIM(G7))="B", "✅ Đúng", "❌ Sai")) | J7: =IF(ISBLANK(I7), "", IF(UPPER(TRIM(I7))="B", "✅ Đúng", "❌ Sai")) | L7: =IF(ISBLANK(K7), "", IF(UPPER(TRIM(K7))="B", "✅ Đúng", "❌ Sai")) | M7: =COUNTIF(H7, "❌ Sai") + COUNTIF(J7, "❌ Sai") + COUNTIF(L7, "❌ Sai") | N7: =IF(ISBLANK(G7), "⏳ Chờ làm", IF(H7="✅ Đúng", "✅ Đúng ngay L1", IF(J7="✅ Đúng", "✅ Đúng ở L2", IF(L7="✅ Đúng", "✅ Đúng ở L3", "❌ Chưa đúng sau 3 lần")))) | O7: =IF(ISBLANK(F7), "💡 Nhập đáp án vào Lần thử 1", IF(G7="✅ Đúng", "✨ Xuất sắc! Bạn đã làm đúng.", "💡 Gợi ý: " & "Chú ý từ nối đối lập hoặc tương phản trong câu để xác định hướng nghiên cứu trái ngược với phương pháp truyền thống.")) | P7: =IF(ISBLANK(G7), "💡 Nhập đáp án vào Lần thử 1", IF(OR(H7="✅ Đúng", J7="✅ Đúng", L7="✅ Đúng"), "✨ Xuất sắc! Bạn đã làm đúng.", IF(NOT(ISBLANK(K7)), "💡 Gợi ý Tầng 3 (Chốt phương pháp): " & "Cần từ miêu tả phương pháp làm việc khác biệt, đi ngược hoặc khác với lối tư duy truyền thống.", IF(NOT(ISBLANK(I7)), "💡 Gợi ý Tầng 2 (Manh mối cấu trúc & Loại trừ): " & "Chú ý từ nối hoặc ngữ cảnh đối lập giữa việc nghiên cứu trên đất liền và độ sâu dưới mực nước biển.", "💡 Gợi ý Tầng 1 (Định hướng bối cảnh): " & "Phân tích hướng tiếp cận nghiên cứu của nhóm tác giả đối với môi trường đại dương.")))) | Q7: =IF(OR(H7="✅ Đúng", J7="✅ Đúng", L7="✅ Đúng"), "Innovative = introducing new, original, or unusual methods.", "🔒 Trả lời đúng để mở khóa Strategic Tip!")
A8: M4 | B8: Reading & Writing Module 1 | C8: Vocabulary in Context (Sufficiency) | D8: While once ______, basic computer security training that only teaches recognition of obvious scams cannot provide enough protection against today’s sophisticated fake emails, which employ such subtle deception techniques that many organizations now require their staff to complete comprehensive cybersecurity education programs. | E8: Which choice completes the text with the most logical and precise word or phrase? | F8: A. Lựa chọn A B. Lựa chọn B C. Lựa chọn C D. Lựa chọn D | H8: =IF(ISBLANK(G8), "⏳ Chờ đáp án", IF(UPPER(TRIM(G8))="C", "✅ Đúng", "❌ Sai")) | J8: =IF(ISBLANK(I8), "", IF(UPPER(TRIM(I8))="C", "✅ Đúng", "❌ Sai")) | L8: =IF(ISBLANK(K8), "", IF(UPPER(TRIM(K8))="C", "✅ Đúng", "❌ Sai")) | M8: =COUNTIF(H8, "❌ Sai") + COUNTIF(J8, "❌ Sai") + COUNTIF(L8, "❌ Sai") | N8: =IF(ISBLANK(G8), "⏳ Chờ làm", IF(H8="✅ Đúng", "✅ Đúng ngay L1", IF(J8="✅ Đúng", "✅ Đúng ở L2", IF(L8="✅ Đúng", "✅ Đúng ở L3", "❌ Chưa đúng sau 3 lần")))) | O8: =IF(ISBLANK(F8), "💡 Nhập đáp án vào Lần thử 1", IF(G8="✅ Đúng", "✨ Xuất sắc! Bạn đã làm đúng.", "💡 Gợi ý: " & "Đọc kỹ câu văn để xác định mức độ hoặc giới hạn của việc đào tạo được đề cập trước khi đưa ra lựa chọn.")) | P8: =IF(ISBLANK(G8), "💡 Nhập đáp án vào Lần thử 1", IF(OR(H8="✅ Đúng", J8="✅ Đúng", L8="✅ Đúng"), "✨ Xuất sắc! Bạn đã làm đúng.", IF(NOT(ISBLANK(K8)), "💡 Gợi ý Tầng 3 (Chốt phương pháp): " & "Chọn từ miêu tả sự đầy đủ/thỏa đáng; loại các từ mang nghĩa thái quá hoặc không đủ.", IF(NOT(ISBLANK(I8)), "💡 Gợi ý Tầng 2 (Manh mối cấu trúc & Loại trừ): " & "Chú ý vế đối lập phía sau về các đòn tấn công tinh vi đòi hỏi cấp độ bảo vệ cao hơn.", "💡 Gợi ý Tầng 1 (Định hướng bối cảnh): " & "Đọc kỹ câu văn để xác định mức độ hoặc giới hạn bảo vệ của việc đào tạo cơ bản.")))) | Q8: =IF(OR(H8="✅ Đúng", J8="✅ Đúng", L8="✅ Đúng"), "Sufficient = adequate or enough for a specific requirement.", "🔒 Trả lời đúng để mở khóa Strategic Tip!")
A9: M5 | B9: Reading & Writing Module 1 | C9: Text Structure & Overall Purpose | D9: What is a city? The answer depends on where you live! Many countries define an area as a city based on how many people live there. However, not every country uses the same numbers. Iceland defines a city as an area with a population of at least 200, while the Netherlands defines a city as having a minimum population of 20,000. Some countries even define cities using other factors, like if there is a local government. | E9: Which choice best describes the overall structure of the text? | F9: A. Lựa chọn A B. Lựa chọn B C. Lựa chọn C D. Lựa chọn D | H9: =IF(ISBLANK(G9), "⏳ Chờ đáp án", IF(UPPER(TRIM(G9))="B", "✅ Đúng", "❌ Sai")) | J9: =IF(ISBLANK(I9), "", IF(UPPER(TRIM(I9))="B", "✅ Đúng", "❌ Sai")) | L9: =IF(ISBLANK(K9), "", IF(UPPER(TRIM(K9))="B", "✅ Đúng", "❌ Sai")) | M9: =COUNTIF(H9, "❌ Sai") + COUNTIF(J9, "❌ Sai") + COUNTIF(L9, "❌ Sai") | N9: =IF(ISBLANK(G9), "⏳ Chờ làm", IF(H9="✅ Đúng", "✅ Đúng ngay L1", IF(J9="✅ Đúng", "✅ Đúng ở L2", IF(L9="✅ Đúng", "✅ Đúng ở L3", "❌ Chưa đúng sau 3 lần")))) | O9: =IF(ISBLANK(F9), "💡 Nhập đáp án vào Lần thử 1", IF(G9="✅ Đúng", "✨ Xuất sắc! Bạn đã làm đúng.", "💡 Gợi ý: " & "Xác định câu hỏi mở đầu và phân tích cách tác giả phát triển các quan điểm khác nhau qua từng phần của bài đọc.")) | P9: =IF(ISBLANK(G9), "💡 Nhập đáp án vào Lần thử 1", IF(OR(H9="✅ Đúng", J9="✅ Đúng", L9="✅ Đúng"), "✨ Xuất sắc! Bạn đã làm đúng.", IF(NOT(ISBLANK(K9)), "💡 Gợi ý Tầng 3 (Chốt phương pháp): " & "Mục đích chính là trình bày các quan điểm đa dạng về một khái niệm thay vì chỉ bảo vệ một góc nhìn duy nhất.", IF(NOT(ISBLANK(I9)), "💡 Gợi ý Tầng 2 (Manh mối cấu trúc & Loại trừ): " & "Bài đọc bắt đầu bằng câu hỏi 'What is a city?' và đưa ra các góc nhìn định nghĩa khác nhau.", "💡 Gợi ý Tầng 1 (Định hướng bối cảnh): " & "Xác định cấu trúc tổng thể của bài đọc từ câu hỏi mở đầu đến các câu tiếp theo.")))) | Q9: =IF(OR(H9="✅ Đúng", J9="✅ Đúng", L9="✅ Đúng"), "Mô hình cấu trúc: Question -> Multiple Explanations/Answers.", "🔒 Trả lời đúng để mở khóa Strategic Tip!")
A10: M6 | B10: Reading & Writing Module 1 | C10: Main Purpose (Literary Narrative) | D10: The following text is adapted from the 1940 novel The Hamlet by William Faulkner. In rural Mississippi, a man is riding a horse toward the residence of someone he intends to meet with about a business matter. He was breathing hard but not because he had been galloping. On the contrary, since he had approached near enough to his destination to believe he could have seen smoke if there had been smoke, he had ridden slower and slower. Nevertheless he now sat the horse before the gap in the fence, breathing hard enough through his nose and even sweating a little, looking at the sagging broken-backed cabin set in its inevitable treeless and grassless plot and weathered to the color of an old bee-hive, with that expression of tense and rapid speculation of a man approaching a dud howitzer [artillery] shell. ©1967 by Estelle Faulkner and Jill Faulkner Summers | E10: Which choice best states the main purpose of the text? | F10: A. Lựa chọn A B. Lựa chọn B C. Lựa chọn C D. Lựa chọn D | H10: =IF(ISBLANK(G10), "⏳ Chờ đáp án", IF(UPPER(TRIM(G10))="D", "✅ Đúng", "❌ Sai")) | J10: =IF(ISBLANK(I10), "", IF(UPPER(TRIM(I10))="D", "✅ Đúng", "❌ Sai")) | L10: =IF(ISBLANK(K10), "", IF(UPPER(TRIM(K10))="D", "✅ Đúng", "❌ Sai")) | M10: =COUNTIF(H10, "❌ Sai") + COUNTIF(J10, "❌ Sai") + COUNTIF(L10, "❌ Sai") | N10: =IF(ISBLANK(G10), "⏳ Chờ làm", IF(H10="✅ Đúng", "✅ Đúng ngay L1", IF(J10="✅ Đúng", "✅ Đúng ở L2", IF(L10="✅ Đúng", "✅ Đúng ở L3", "❌ Chưa đúng sau 3 lần")))) | O10: =IF(ISBLANK(F10), "💡 Nhập đáp án vào Lần thử 1", IF(G10="✅ Đúng", "✨ Xuất sắc! Bạn đã làm đúng.", "💡 Gợi ý: " & "Tập trung vào các chi tiết miêu tả cảm xúc và hành vi của nhân vật để rút ra chủ đề chính của đoạn văn.")) | P10: =IF(ISBLANK(G10), "💡 Nhập đáp án vào Lần thử 1", IF(OR(H10="✅ Đúng", J10="✅ Đúng", L10="✅ Đúng"), "✨ Xuất sắc! Bạn đã làm đúng.", IF(NOT(ISBLANK(K10)), "💡 Gợi ý Tầng 3 (Chốt phương pháp): " & "Mục đích chính là thể hiện trạng thái tâm lý lo âu/căng thẳng của nhân vật qua hành vi cụ thể.", IF(NOT(ISBLANK(I10)), "💡 Gợi ý Tầng 2 (Manh mối cấu trúc & Loại trừ): " & "Chú ý các dấu hiệu như thở gấp, đổ mồ hôi và nét mặt căng thẳng trong bối cảnh truyện.", "💡 Gợi ý Tầng 1 (Định hướng bối cảnh): " & "Tập trung vào các chi tiết miêu tả cảm xúc và biểu hiện thể chất của nhân vật.")))) | Q10: =IF(OR(H10="✅ Đúng", J10="✅ Đúng", L10="✅ Đúng"), "Văn xuôi hư cấu: Biểu hiện thể chất phản ánh trạng thái tâm lý nhân vật.", "🔒 Trả lời đúng để mở khóa Strategic Tip!")
A11: M7 | B11: Reading & Writing Module 1 | C11: Main Purpose (Informational Text) | D11: Modern forestry offers diverse career opportunities that integrate scientific knowledge with hands-on environmental work. Arborists assess tree health and perform maintenance such as pruning to promote safety and prevent problems. Forestry technicians collect data on growth patterns and biodiversity in the wild. Forest ecologists conduct field research and analyze ecosystems to understand how forests respond to changes in weather patterns. With this blend of scientific understanding and practical application, forestry professionals address a variety of complex environmental challenges. | E11: Which choice best describes the main purpose of the text? | F11: A. Lựa chọn A B. Lựa chọn B C. Lựa chọn C D. Lựa chọn D | H11: =IF(ISBLANK(G11), "⏳ Chờ đáp án", IF(UPPER(TRIM(G11))="D", "✅ Đúng", "❌ Sai")) | J11: =IF(ISBLANK(I11), "", IF(UPPER(TRIM(I11))="D", "✅ Đúng", "❌ Sai")) | L11: =IF(ISBLANK(K11), "", IF(UPPER(TRIM(K11))="D", "✅ Đúng", "❌ Sai")) | M11: =COUNTIF(H11, "❌ Sai") + COUNTIF(J11, "❌ Sai") + COUNTIF(L11, "❌ Sai") | N11: =IF(ISBLANK(G11), "⏳ Chờ làm", IF(H11="✅ Đúng", "✅ Đúng ngay L1", IF(J11="✅ Đúng", "✅ Đúng ở L2", IF(L11="✅ Đúng", "✅ Đúng ở L3", "❌ Chưa đúng sau 3 lần")))) | O11: =IF(ISBLANK(F11), "💡 Nhập đáp án vào Lần thử 1", IF(G11="✅ Đúng", "✨ Xuất sắc! Bạn đã làm đúng.", "💡 Gợi ý: " & "So sánh câu mở đầu và câu kết thúc của bài đọc để tổng hợp mục đích chung mà tác giả muốn truyền tải.")) | P11: =IF(ISBLANK(G11), "💡 Nhập đáp án vào Lần thử 1", IF(OR(H11="✅ Đúng", J11="✅ Đúng", L11="✅ Đúng"), "✨ Xuất sắc! Bạn đã làm đúng.", IF(NOT(ISBLANK(K11)), "💡 Gợi ý Tầng 3 (Chốt phương pháp): " & "Mục đích là tổng quan các cơ hội nghề nghiệp đa dạng trong lĩnh vực được nêu.", IF(NOT(ISBLANK(I11)), "💡 Gợi ý Tầng 2 (Manh mối cấu trúc & Loại trừ): " & "Đoạn văn liệt kê các hướng đi công việc và cơ hội phát triển trong ngành lâm nghiệp.", "💡 Gợi ý Tầng 1 (Định hướng bối cảnh): " & "So sánh câu mở đầu và câu kết thúc của bài đọc để xác định chủ đề xuyên suốt.")))) | Q11: =IF(OR(H11="✅ Đúng", J11="✅ Đúng", L11="✅ Đúng"), "Main Purpose = Topic (Forestry Careers) + So What? (Integrate science and practical work).", "🔒 Trả lời đúng để mở khóa Strategic Tip!")
A12: M8 | B12: Reading & Writing Module 1 | C12: Detail & Literal Comprehension | D12: James Fong and his team claim to have discovered a new color, which they named olo. Olo is a very saturated blue-green color that can’t be seen with the human eye under natural conditions. In the human eye, long, medium, and short cones in the retina help sense bright light and color. Olo can only be seen by activating the medium cones alone. Fong and team activated these cones by using a targeted laser technology to stimulate just the medium cone cells. | E12: According to the text, how can the color olo be seen? | F12: A. Lựa chọn A B. Lựa chọn B C. Lựa chọn C D. Lựa chọn D | H12: =IF(ISBLANK(G12), "⏳ Chờ đáp án", IF(UPPER(TRIM(G12))="A", "✅ Đúng", "❌ Sai")) | J12: =IF(ISBLANK(I12), "", IF(UPPER(TRIM(I12))="A", "✅ Đúng", "❌ Sai")) | L12: =IF(ISBLANK(K12), "", IF(UPPER(TRIM(K12))="A", "✅ Đúng", "❌ Sai")) | M12: =COUNTIF(H12, "❌ Sai") + COUNTIF(J12, "❌ Sai") + COUNTIF(L12, "❌ Sai") | N12: =IF(ISBLANK(G12), "⏳ Chờ làm", IF(H12="✅ Đúng", "✅ Đúng ngay L1", IF(J12="✅ Đúng", "✅ Đúng ở L2", IF(L12="✅ Đúng", "✅ Đúng ở L3", "❌ Chưa đúng sau 3 lần")))) | O12: =IF(ISBLANK(F12), "💡 Nhập đáp án vào Lần thử 1", IF(G12="✅ Đúng", "✨ Xuất sắc! Bạn đã làm đúng.", "💡 Gợi ý: " & "Tìm vị trí từ khóa trong bài đọc và đối chiếu chính xác thông tin được phát biểu trực tiếp.")) | P12: =IF(ISBLANK(G12), "💡 Nhập đáp án vào Lần thử 1", IF(OR(H12="✅ Đúng", J12="✅ Đúng", L12="✅ Đúng"), "✨ Xuất sắc! Bạn đã làm đúng.", IF(NOT(ISBLANK(K12)), "💡 Gợi ý Tầng 3 (Chốt phương pháp): " & "Chọn đáp án diễn đạt lại chính xác (paraphrase) điều kiện kích hoạt được nêu trực tiếp trên mặt chữ.", IF(NOT(ISBLANK(I12)), "💡 Gợi ý Tầng 2 (Manh mối cấu trúc & Loại trừ): " & "Đối chiếu trực tiếp chi tiết về điều kiện nhìn thấy được miêu tả ở phần giữa bài đọc.", "💡 Gợi ý Tầng 1 (Định hướng bối cảnh): " & "Xác định từ khóa tên riêng được đề cập trong câu hỏi và định vị câu chứa thông tin.")))) | Q12: =IF(OR(H12="✅ Đúng", J12="✅ Đúng", L12="✅ Đúng"), "Literal Comprehension: Paraphrase đúng nguyên văn bài đọc, không suy diễn.", "🔒 Trả lời đúng để mở khóa Strategic Tip!")
